Workbook

Sheet Japanese Results
A1: =IFERROR(__xludf.DUMMYFUNCTION("IMPORTRANGE(""https://docs.google.com/spreadsheets/d/1JRp1QFgRUeO6wUkbMBdCuSKPn0UMXY4laNYwSgpe9m4/edit?gid=0#gid=0"",""Sheet1!A:AB"")"),"Submission ID") -> Submission ID | B1: =IFERROR(__xludf.DUMMYFUNCTION("""COMPUTED_VALUE"""),"Respondent ID") -> Respondent ID | C1: =IFERROR(__xludf.DUMMYFUNCTION("""COMPUTED_VALUE"""),"Submitted at") -> Submitted at | D1: =IFERROR(__xludf.DUMMYFUNCTION("""COMPUTED_VALUE"""),"あなたの年齢層を教えてください。") -> あなたの年齢層を教えてください。 | E1: =IFERROR(__xludf.DUMMYFUNCTION("""COMPUTED_VALUE"""),"ご自身が最も当てはまると感じる性別を教えてください。") -> ご自身が最も当てはまると感じる性別を教えてください。 | F1: =IFERROR(__xludf.DUMMYFUNCTION("""COMPUTED_VALUE"""),"世帯年収（税引き前）を教えてください。") -> 世帯年収（税引き前）を教えてください。 | G1: =IFERROR(__xludf.DUMMYFUNCTION("""COMPUTED_VALUE"""),"主にお住まいの地域はどこですか。") -> 主にお住まいの地域はどこですか。 | H1: =IFERROR(__xludf.DUMMYFUNCTION("""COMPUTED_VALUE"""),"どのくらいの頻度でコーヒーを飲みますか。") -> どのくらいの頻度でコーヒーを飲みますか。 | I1: =IFERROR(__xludf.DUMMYFUNCTION("""COMPUTED_VALUE"""),"普段よく飲むコーヒーの種類は何ですか。") -> 普段よく飲むコーヒーの種類は何ですか。 | J1: =IFERROR(__xludf.DUMMYFUNCTION("""COMPUTED_VALUE"""),"Untitled short answer field") -> Untitled short answer field | K1: =IFERROR(__xludf.DUMMYFUNCTION("""COMPUTED_VALUE"""),"どのくらいの頻度で抹茶を飲みますか。") -> どのくらいの頻度で抹茶を飲みますか。 | L1: =IFERROR(__xludf.DUMMYFUNCTION("""COMPUTED_VALUE"""),"普段よく飲む抹茶の種類は何ですか。") -> 普段よく飲む抹茶の種類は何ですか。 | M1: =IFERROR(__xludf.DUMMYFUNCTION("""COMPUTED_VALUE"""),"Untitled short answer field") -> Untitled short answer field | N1: =IFERROR(__xludf.DUMMYFUNCTION("""COMPUTED_VALUE"""),"コーヒーと抹茶のどちらを選ぶか決める際、特に影響する要因は何ですか。（最大2つまで）") -> コーヒーと抹茶のどちらを選ぶか決める際、特に影響する要因は何ですか。（最大2つまで） | O1: =IFERROR(__xludf.DUMMYFUNCTION("""COMPUTED_VALUE"""),"Untitled short answer field") -> Untitled short answer field | P1: =IFERROR(__xludf.DUMMYFUNCTION("""COMPUTED_VALUE"""),"これらの飲み物をどのようにして飲むことが多いですか。（該当するものすべて）") -> これらの飲み物をどのようにして飲むことが多いですか。（該当するものすべて） | Q1: =IFERROR(__xludf.DUMMYFUNCTION("""COMPUTED_VALUE"""),"Untitled short answer field") -> Untitled short answer field | R1: =IFERROR(__xludf.DUMMYFUNCTION("""COMPUTED_VALUE"""),"どのくらいの頻度でカフェに行きますか。") -> どのくらいの頻度でカフェに行きますか。 | S1: =IFERROR(__xludf.DUMMYFUNCTION("""COMPUTED_VALUE"""),"カフェに行く主な理由は何ですか。") -> カフェに行く主な理由は何ですか。 | T1: =IFERROR(__xludf.DUMMYFUNCTION("""COMPUTED_VALUE"""),"Untitled short answer field") -> Untitled short answer field | U1: =IFERROR(__xludf.DUMMYFUNCTION("""COMPUTED_VALUE"""),"あなたにとって、良いカフェ体験とは何ですか。") -> あなたにとって、良いカフェ体験とは何ですか。 | V1: =IFERROR(__xludf.DUMMYFUNCTION("""COMPUTED_VALUE"""),"Untitled short answer field") -> Untitled short answer field | W1: =IFERROR(__xludf.DUMMYFUNCTION("""COMPUTED_VALUE"""),"コーヒーに特定の文化やイメージを結びつけますか。") -> コーヒーに特定の文化やイメージを結びつけますか。 | X1: =IFERROR(__xludf.DUMMYFUNCTION("""COMPUTED_VALUE"""),"抹茶に特定の文化やイメージを結びつけますか。") -> 抹茶に特定の文化やイメージを結びつけますか。 | Y1: =IFERROR(__xludf.DUMMYFUNCTION("""COMPUTED_VALUE"""),"以下の意見について、どの程度同意しますか。") -> 以下の意見について、どの程度同意しますか。 | Z1: =IFERROR(__xludf.DUMMYFUNCTION("""COMPUTED_VALUE"""),"Untitled linear scale field") -> Untitled linear scale field | AA1: =IFERROR(__xludf.DUMMYFUNCTION("""COMPUTED_VALUE"""),"Untitled linear scale field") -> Untitled linear scale field | AB1: =IFERROR(__xludf.DUMMYFUNCTION("""COMPUTED_VALUE"""),"コーヒー、抹茶、カフェ文化について、より詳しくお話を伺うための短いフォローアップ・インタビュー（15～20分・英語）に参加してもよいですか？※インタビューにご参加いただいた方には、謝礼として無料ドリンクまたはギフトカードを差し上げます。") -> コーヒー、抹茶、カフェ文化について、より詳しくお話を伺うための短いフォローアップ・インタビュー（15～20分・英語）に参加してもよいですか？※インタビューにご参加いただいた方には、謝礼として無料ドリンクまたはギフトカードを差し上げます。 | AK1: Submission ID | AL1: Respondent ID | AM1: Submitted at | AN1: What age group do you fall into? Translation | AO1: To which gender do you identify most with? Translation | AP1: What is your total household income before taxes? Translation | AQ1: What region of Japan do you primarily live in? Translation | AR1: How often do you drink coffee? Translation | AS1: What coffee beverage do you usually drink? | AT1: Untitled short answer field | AU1: How often do you drink matcha? | AV1: What matcha beverage do you usually drink? | AW1: Untitled short answer field | AX1: When choosing between coffee and matcha, what factors influence your choice most? (Select up to two) | AY1: Untitled short answer field | AZ1: How do you usually consume these drinks? (Select all that apply) | BA1: Untitled short answer field | BB1: How often do you visit cafés? | BC1: What is your main reason for visiting a café? | BD1: Untitled short answer field | BE1: In your opinion, what makes a good café experience? | BF1: Untitled short answer field | BG1: Do you associate coffee with any particular culture or image? | BH1: Do you associate matcha with any particular culture or image? | BI1: How strongly do you agree with the following statements: | BJ1: Untitled linear scale field | BK1: Untitled linear scale field | BL1: Would you be open to a short (15–20 minute) follow-up interview in English to discuss your thoughts about coffee, matcha, and café culture in more detail? Participants who take part in a follow-up interview will be offered a free drink/gift card as a thank-you for their time. | BM1: Please provide your email address so I can contact you:
A2: =IFERROR(__xludf.DUMMYFUNCTION("""COMPUTED_VALUE"""),"EkoA68o") -> EkoA68o | B2: =IFERROR(__xludf.DUMMYFUNCTION("""COMPUTED_VALUE"""),"LZp8NDy") -> LZp8NDy | C2: =IFERROR(__xludf.DUMMYFUNCTION("""COMPUTED_VALUE"""),46028.188055555554) -> 46028.188 | D2: =IFERROR(__xludf.DUMMYFUNCTION("""COMPUTED_VALUE"""),"18〜25歳") -> 18〜25歳 | E2: =IFERROR(__xludf.DUMMYFUNCTION("""COMPUTED_VALUE"""),"男性") -> 男性 | F2: =IFERROR(__xludf.DUMMYFUNCTION("""COMPUTED_VALUE"""),"1,200万円以上") -> 1,200万円以上 | G2: =IFERROR(__xludf.DUMMYFUNCTION("""COMPUTED_VALUE"""),"関東") -> 関東 | H2: =IFERROR(__xludf.DUMMYFUNCTION("""COMPUTED_VALUE"""),"まったく飲まない") -> まったく飲まない | K2: =IFERROR(__xludf.DUMMYFUNCTION("""COMPUTED_VALUE"""),"ほとんど飲まない") -> ほとんど飲まない | L2: =IFERROR(__xludf.DUMMYFUNCTION("""COMPUTED_VALUE"""),"薄茶") -> 薄茶 | N2: =IFERROR(__xludf.DUMMYFUNCTION("""COMPUTED_VALUE"""),"味・風味, 健康面のメリット") -> 味・風味, 健康面のメリット | P2: =IFERROR(__xludf.DUMMYFUNCTION("""COMPUTED_VALUE"""),"自動販売機, コンビニ（セブンイレブン、ローソンなど）") -> 自動販売機, コンビニ（セブンイレブン、ローソンなど） | R2: =IFERROR(__xludf.DUMMYFUNCTION("""COMPUTED_VALUE"""),"ほとんど行かない") -> ほとんど行かない | S2: =IFERROR(__xludf.DUMMYFUNCTION("""COMPUTED_VALUE"""),"友人と会うため") -> 友人と会うため | U2: =IFERROR(__xludf.DUMMYFUNCTION("""COMPUTED_VALUE"""),"飲み物の味・品質") -> 飲み物の味・品質 | W2: =IFERROR(__xludf.DUMMYFUNCTION("""COMPUTED_VALUE"""),"はい（西洋的）") -> はい（西洋的） | X2: =IFERROR(__xludf.DUMMYFUNCTION("""COMPUTED_VALUE"""),"はい（日本的）") -> はい（日本的） | Y2: =IFERROR(__xludf.DUMMYFUNCTION("""COMPUTED_VALUE"""),4.0) -> 4 | Z2: =IFERROR(__xludf.DUMMYFUNCTION("""COMPUTED_VALUE"""),6.0) -> 6 | AA2: =IFERROR(__xludf.DUMMYFUNCTION("""COMPUTED_VALUE"""),4.0) -> 4 | AB2: =IFERROR(__xludf.DUMMYFUNCTION("""COMPUTED_VALUE"""),"いいえ") -> いいえ | AK2: EkoA68o | AL2: LZp8NDy | AM2: 46028.188 | AN2: {=IF(D2:D1000="","",XLOOKUP(D2:D1000, 'Translation Key'!$A:$A, 'Translation Key'!$B:$B))} -> 18-25 | AO2: {=IF(E2:E1000="","",XLOOKUP(E2:E1000, 'Translation Key'!$A:$A, 'Translation Key'!$B:$B))} -> Male | AP2: {=IF(F2:F1000="","",XLOOKUP(F2:F1000, 'Translation Key'!$A:$A, 'Translation Key'!$B:$B))} -> ¥12,000,000 or more | AQ2: {=IF(G2:G1000="","",XLOOKUP(G2:G1000, 'Translation Key'!$A:$A, 'Translation Key'!$B:$B))} -> Kanto | AR2: {=IF(H2:H1000="","",XLOOKUP(H2:H1000, 'Translation Key'!$A:$A, 'Translation Key'!$B:$B))} -> Never | AS2: {=IF(I2:I1000="","",XLOOKUP(I2:I1000, 'Translation Key'!$A:$A, 'Translation Key'!$B:$B))} | AU2: {=IF(K2:K1000="","",XLOOKUP(K2:K1000, 'Translation Key'!$A:$A, 'Translation Key'!$B:$B))} -> Rarely | AV2: {=IF(L2:L1000="","",XLOOKUP(L2:L1000, 'Translation Key'!$A:$A, 'Translation Key'!$B:$B))} -> Usucha | AX2: =IFERROR(__xludf.DUMMYFUNCTION("ARRAYFORMULA(IF(N2:N1000="""","""", BYROW(N2:N1000, LAMBDA(cell, IF(cell="""","""", JOIN("", "", ARRAYFORMULA( IFERROR( XLOOKUP( TRIM(TRANSPOSE(SPLIT(cell,"",""))), 'Translation Key'!$A:$A, 'Translation Key'!$B:$B ), TRIM(TRANSPOSE(SPLIT(cell,"&""",""))) ) ) ) ) )) ))"),"Taste/Flavor, Health benefits") -> Taste/Flavor, Health benefits | AZ2: =IFERROR(__xludf.DUMMYFUNCTION("ARRAYFORMULA(IF(P2:P1000="""","""", BYROW(P2:P1000, LAMBDA(cell, IF(cell="""","""", JOIN("", "", ARRAYFORMULA( IFERROR( XLOOKUP( TRIM(TRANSPOSE(SPLIT(cell,"",""))), 'Translation Key'!$A:$A, 'Translation Key'!$B:$B ), TRIM(TRANSPOSE(SPLIT(cell,"&""",""))) ) ) ) ) )) ))"),"From vending machines, From convenience stores (7-Eleven, Lawson, etc.)") -> From vending machines, From convenience stores (7-Eleven, Lawson, etc.) | BB2: {=IF(R2:R1000="","",XLOOKUP(R2:R1000, 'Translation Key'!$A:$A, 'Translation Key'!$B:$B))} -> Rarely | BC2: {=IF(S2:S1000="","",XLOOKUP(S2:S1000, 'Translation Key'!$A:$A, 'Translation Key'!$B:$B))} -> To meet friends | BE2: {=IF(U2:U1000="","",XLOOKUP(U2:U1000, 'Translation Key'!$A:$A, 'Translation Key'!$B:$B))} -> Quality of drinks | BG2: {=IF(W2:W1000="","",XLOOKUP(W2:W1000, 'Translation Key'!$A:$A, 'Translation Key'!$B:$B))} -> Yes, Western | BH2: {=IF(X2:X1000="","",XLOOKUP(X2:X1000, 'Translation Key'!$A:$A, 'Translation Key'!$B:$B))} -> Yes, Japanese | BI2: {=IF(Y2:Y1000="","",XLOOKUP(Y2:Y1000, 'Translation Key'!$A:$A, 'Translation Key'!$B:$B))} -> 4 | BJ2: {=IF(Z2:Z1000="","",XLOOKUP(Z2:Z1000, 'Translation Key'!$A:$A, 'Translation Key'!$B:$B))} -> 6 | BK2: {=IF(AA2:AA1000="","",XLOOKUP(AA2:AA1000, 'Translation Key'!$A:$A, 'Translation Key'!$B:$B))} -> 4 | BL2: {=IF(AB2:AB1000="","",XLOOKUP(AB2:AB1000, 'Translation Key'!$A:$A, 'Translation Key'!$B:$B))} -> No
A3: =IFERROR(__xludf.DUMMYFUNCTION("""COMPUTED_VALUE"""),"J9Ey24r") -> J9Ey24r | B3: =IFERROR(__xludf.DUMMYFUNCTION("""COMPUTED_VALUE"""),"xXarWEd") -> xXarWEd | C3: =IFERROR(__xludf.DUMMYFUNCTION("""COMPUTED_VALUE"""),46029.96582175926) -> 46029.966 | D3: =IFERROR(__xludf.DUMMYFUNCTION("""COMPUTED_VALUE"""),"26〜35歳") -> 26〜35歳 | E3: =IFERROR(__xludf.DUMMYFUNCTION("""COMPUTED_VALUE"""),"女性") -> 女性 | F3: =IFERROR(__xludf.DUMMYFUNCTION("""COMPUTED_VALUE"""),"300万円未満") -> 300万円未満 | G3: =IFERROR(__xludf.DUMMYFUNCTION("""COMPUTED_VALUE"""),"関東") -> 関東 | H3: =IFERROR(__xludf.DUMMYFUNCTION("""COMPUTED_VALUE"""),"週に数回") -> 週に数回 | I3: =IFERROR(__xludf.DUMMYFUNCTION("""COMPUTED_VALUE"""),"ドリップコーヒー") -> ドリップコーヒー | K3: =IFERROR(__xludf.DUMMYFUNCTION("""COMPUTED_VALUE"""),"週に数回") -> 週に数回 | L3: =IFERROR(__xludf.DUMMYFUNCTION("""COMPUTED_VALUE"""),"薄茶") -> 薄茶 | N3: =IFERROR(__xludf.DUMMYFUNCTION("""COMPUTED_VALUE"""),"価格, 味・風味") -> 価格, 味・風味 | P3: =IFERROR(__xludf.DUMMYFUNCTION("""COMPUTED_VALUE"""),"自宅で") -> 自宅で | R3: =IFERROR(__xludf.DUMMYFUNCTION("""COMPUTED_VALUE"""),"週に数回") -> 週に数回 | S3: =IFERROR(__xludf.DUMMYFUNCTION("""COMPUTED_VALUE"""),"友人と会うため") -> 友人と会うため | U3: =IFERROR(__xludf.DUMMYFUNCTION("""COMPUTED_VALUE"""),"雰囲気・心地良さ") -> 雰囲気・心地良さ | W3: =IFERROR(__xludf.DUMMYFUNCTION("""COMPUTED_VALUE"""),"はい（西洋的）") -> はい（西洋的） | X3: =IFERROR(__xludf.DUMMYFUNCTION("""COMPUTED_VALUE"""),"はい（日本的）") -> はい（日本的） | Y3: =IFERROR(__xludf.DUMMYFUNCTION("""COMPUTED_VALUE"""),3.0) -> 3 | Z3: =IFERROR(__xludf.DUMMYFUNCTION("""COMPUTED_VALUE"""),6.0) -> 6 | AA3: =IFERROR(__xludf.DUMMYFUNCTION("""COMPUTED_VALUE"""),5.0) -> 5 | AB3: =IFERROR(__xludf.DUMMYFUNCTION("""COMPUTED_VALUE"""),"いいえ") -> いいえ | AK3: J9Ey24r | AL3: xXarWEd | AM3: 46029.966 | AN3: 26-35 | AO3: Female | AP3: Under ¥3,000,000 | AQ3: Kanto | AR3: Several times a week | AS3: Drip | AU3: Several times a week | AV3: Usucha | AX3: =IFERROR(__xludf.DUMMYFUNCTION("""COMPUTED_VALUE"""),"Price, Taste/Flavor") -> Price, Taste/Flavor | AZ3: =IFERROR(__xludf.DUMMYFUNCTION("""COMPUTED_VALUE"""),"At home") -> At home | BB3: Several times a week | BC3: To meet friends | BE3: Atmosphere | BG3: Yes, Western | BH3: Yes, Japanese | BI3: 3 | BJ3: 6 | BK3: 5 | BL3: No
A4: =IFERROR(__xludf.DUMMYFUNCTION("""COMPUTED_VALUE"""),"ODxRYQA") -> ODxRYQA | B4: =IFERROR(__xludf.DUMMYFUNCTION("""COMPUTED_VALUE"""),"Y5WP1Lv") -> Y5WP1Lv | C4: =IFERROR(__xludf.DUMMYFUNCTION("""COMPUTED_VALUE"""),46029.97939814815) -> 46029.979 | D4: =IFERROR(__xludf.DUMMYFUNCTION("""COMPUTED_VALUE"""),"18〜25歳") -> 18〜25歳 | E4: =IFERROR(__xludf.DUMMYFUNCTION("""COMPUTED_VALUE"""),"男性") -> 男性 | F4: =IFERROR(__xludf.DUMMYFUNCTION("""COMPUTED_VALUE"""),"600万円〜899万9,999円") -> 600万円〜899万9,999円 | G4: =IFERROR(__xludf.DUMMYFUNCTION("""COMPUTED_VALUE"""),"関東") -> 関東 | H4: =IFERROR(__xludf.DUMMYFUNCTION("""COMPUTED_VALUE"""),"毎日") -> 毎日 | I4: =IFERROR(__xludf.DUMMYFUNCTION("""COMPUTED_VALUE"""),"ドリップコーヒー") -> ドリップコーヒー | K4: =IFERROR(__xludf.DUMMYFUNCTION("""COMPUTED_VALUE"""),"毎日") -> 毎日 | L4: =IFERROR(__xludf.DUMMYFUNCTION("""COMPUTED_VALUE"""),"濃茶") -> 濃茶 | N4: =IFERROR(__xludf.DUMMYFUNCTION("""COMPUTED_VALUE"""),"味・風味, エナジー／カフェイン") -> 味・風味, エナジー／カフェイン | P4: =IFERROR(__xludf.DUMMYFUNCTION("""COMPUTED_VALUE"""),"カフェで, 自宅で") -> カフェで, 自宅で | R4: =IFERROR(__xludf.DUMMYFUNCTION("""COMPUTED_VALUE"""),"週に数回") -> 週に数回 | S4: =IFERROR(__xludf.DUMMYFUNCTION("""COMPUTED_VALUE"""),"新しい飲み物を試すため") -> 新しい飲み物を試すため | U4: =IFERROR(__xludf.DUMMYFUNCTION("""COMPUTED_VALUE"""),"飲み物の味・品質") -> 飲み物の味・品質 | W4: =IFERROR(__xludf.DUMMYFUNCTION("""COMPUTED_VALUE"""),"はい（グローバル）") -> はい（グローバル） | X4: =IFERROR(__xludf.DUMMYFUNCTION("""COMPUTED_VALUE"""),"はい（日本的）") -> はい（日本的） | Y4: =IFERROR(__xludf.DUMMYFUNCTION("""COMPUTED_VALUE"""),3.0) -> 3 | Z4: =IFERROR(__xludf.DUMMYFUNCTION("""COMPUTED_VALUE"""),4.0) -> 4 | AA4: =IFERROR(__xludf.DUMMYFUNCTION("""COMPUTED_VALUE"""),3.0) -> 3 | AB4: =IFERROR(__xludf.DUMMYFUNCTION("""COMPUTED_VALUE"""),"いいえ") -> いいえ | AK4: ODxRYQA | AL4: Y5WP1Lv | AM4: 46029.979 | AN4: 18-25 | AO4: Male | AP4: ¥6,000,000 – ¥8,999,999 | AQ4: Kanto | AR4: Daily | AS4: Drip | AU4: Daily | AV4: Koicha | AX4: =IFERROR(__xludf.DUMMYFUNCTION("""COMPUTED_VALUE"""),"Taste/Flavor, Energy boost/Caffeine") -> Taste/Flavor, Energy boost/Caffeine | AZ4: =IFERROR(__xludf.DUMMYFUNCTION("""COMPUTED_VALUE"""),"At cafés, At home") -> At cafés, At home | BB4: Several times a week | BC4: To try a new drink | BE4: Quality of drinks | BG4: Yes, Global | BH4: Yes, Japanese | BI4: 3 | BJ4: 4 | BK4: 3 | BL4: No
A5: =IFERROR(__xludf.DUMMYFUNCTION("""COMPUTED_VALUE"""),"Zjb0xWz") -> Zjb0xWz | B5: =IFERROR(__xludf.DUMMYFUNCTION("""COMPUTED_VALUE"""),"q4Aa8P9") -> q4Aa8P9 | C5: =IFERROR(__xludf.DUMMYFUNCTION("""COMPUTED_VALUE"""),46030.24071759259) -> 46030.241 | D5: =IFERROR(__xludf.DUMMYFUNCTION("""COMPUTED_VALUE"""),"36〜45歳") -> 36〜45歳 | E5: =IFERROR(__xludf.DUMMYFUNCTION("""COMPUTED_VALUE"""),"男性") -> 男性 | F5: =IFERROR(__xludf.DUMMYFUNCTION("""COMPUTED_VALUE"""),"回答しない") -> 回答しない | G5: =IFERROR(__xludf.DUMMYFUNCTION("""COMPUTED_VALUE"""),"関東") -> 関東 | H5: =IFERROR(__xludf.DUMMYFUNCTION("""COMPUTED_VALUE"""),"毎日") -> 毎日 | I5: =IFERROR(__xludf.DUMMYFUNCTION("""COMPUTED_VALUE"""),"プアオーバー（ハンドドリップ）") -> プアオーバー（ハンドドリップ） | K5: =IFERROR(__xludf.DUMMYFUNCTION("""COMPUTED_VALUE"""),"週に数回") -> 週に数回 | L5: =IFERROR(__xludf.DUMMYFUNCTION("""COMPUTED_VALUE"""),"薄茶") -> 薄茶 | N5: =IFERROR(__xludf.DUMMYFUNCTION("""COMPUTED_VALUE"""),"味・風味") -> 味・風味 | P5: =IFERROR(__xludf.DUMMYFUNCTION("""COMPUTED_VALUE"""),"カフェで") -> カフェで | R5: =IFERROR(__xludf.DUMMYFUNCTION("""COMPUTED_VALUE"""),"週に数回") -> 週に数回 | S5: =IFERROR(__xludf.DUMMYFUNCTION("""COMPUTED_VALUE"""),"その他：") -> その他： | T5: =IFERROR(__xludf.DUMMYFUNCTION("""COMPUTED_VALUE"""),"お店の人と会話をしたいため") -> お店の人と会話をしたいため | U5: =IFERROR(__xludf.DUMMYFUNCTION("""COMPUTED_VALUE"""),"その他：") -> その他： | V5: =IFERROR(__xludf.DUMMYFUNCTION("""COMPUTED_VALUE"""),"その時の利用目的による") -> その時の利用目的による | W5: =IFERROR(__xludf.DUMMYFUNCTION("""COMPUTED_VALUE"""),"はい（グローバル）") -> はい（グローバル） | X5: =IFERROR(__xludf.DUMMYFUNCTION("""COMPUTED_VALUE"""),"はい（グローバル）") -> はい（グローバル） | Y5: =IFERROR(__xludf.DUMMYFUNCTION("""COMPUTED_VALUE"""),7.0) -> 7 | Z5: =IFERROR(__xludf.DUMMYFUNCTION("""COMPUTED_VALUE"""),7.0) -> 7 | AA5: =IFERROR(__xludf.DUMMYFUNCTION("""COMPUTED_VALUE"""),7.0) -> 7 | AB5: =IFERROR(__xludf.DUMMYFUNCTION("""COMPUTED_VALUE"""),"いいえ") -> いいえ | AK5: Zjb0xWz | AL5: q4Aa8P9 | AM5: 46030.241 | AN5: 36-45 | AO5: Male | AP5: Prefer not to say | AQ5: Kanto | AR5: Daily | AS5: Pour Over | AU5: Several times a week | AV5: Usucha | AX5: =IFERROR(__xludf.DUMMYFUNCTION("""COMPUTED_VALUE"""),"Taste/Flavor") -> Taste/Flavor | AZ5: =IFERROR(__xludf.DUMMYFUNCTION("""COMPUTED_VALUE"""),"At cafés") -> At cafés | BB5: Several times a week | BC5: Other: | BD5: Because I want to talk with the staff. | BE5: Other: | BF5: It depends on the purpose at that time. | BG5: Yes, Global | BH5: Yes, Global | BI5: 7 | BJ5: 7 | BK5: 7 | BL5: No
A6: =IFERROR(__xludf.DUMMYFUNCTION("""COMPUTED_VALUE"""),"GxAKvz2") -> GxAKvz2 | B6: =IFERROR(__xludf.DUMMYFUNCTION("""COMPUTED_VALUE"""),"jaQQQKx") -> jaQQQKx | C6: =IFERROR(__xludf.DUMMYFUNCTION("""COMPUTED_VALUE"""),46031.24113425926) -> 46031.241 | D6: =IFERROR(__xludf.DUMMYFUNCTION("""COMPUTED_VALUE"""),"18〜25歳") -> 18〜25歳 | E6: =IFERROR(__xludf.DUMMYFUNCTION("""COMPUTED_VALUE"""),"女性") -> 女性 | F6: =IFERROR(__xludf.DUMMYFUNCTION("""COMPUTED_VALUE"""),"回答しない") -> 回答しない | G6: =IFERROR(__xludf.DUMMYFUNCTION("""COMPUTED_VALUE"""),"関東") -> 関東 | H6: =IFERROR(__xludf.DUMMYFUNCTION("""COMPUTED_VALUE"""),"毎日") -> 毎日 | I6: =IFERROR(__xludf.DUMMYFUNCTION("""COMPUTED_VALUE"""),"ドリップコーヒー") -> ドリップコーヒー | K6: =IFERROR(__xludf.DUMMYFUNCTION("""COMPUTED_VALUE"""),"週に数回") -> 週に数回 | L6: =IFERROR(__xludf.DUMMYFUNCTION("""COMPUTED_VALUE"""),"抹茶ラテ") -> 抹茶ラテ | N6: =IFERROR(__xludf.DUMMYFUNCTION("""COMPUTED_VALUE"""),"味・風味") -> 味・風味 | P6: =IFERROR(__xludf.DUMMYFUNCTION("""COMPUTED_VALUE"""),"自宅で") -> 自宅で | R6: =IFERROR(__xludf.DUMMYFUNCTION("""COMPUTED_VALUE"""),"月に数回") -> 月に数回 | S6: =IFERROR(__xludf.DUMMYFUNCTION("""COMPUTED_VALUE"""),"休憩・リラックスするため") -> 休憩・リラックスするため | U6: =IFERROR(__xludf.DUMMYFUNCTION("""COMPUTED_VALUE"""),"飲み物の味・品質") -> 飲み物の味・品質 | W6: =IFERROR(__xludf.DUMMYFUNCTION("""COMPUTED_VALUE"""),"はい（西洋的）") -> はい（西洋的） | X6: =IFERROR(__xludf.DUMMYFUNCTION("""COMPUTED_VALUE"""),"はい（日本的）") -> はい（日本的） | Y6: =IFERROR(__xludf.DUMMYFUNCTION("""COMPUTED_VALUE"""),7.0) -> 7 | Z6: =IFERROR(__xludf.DUMMYFUNCTION("""COMPUTED_VALUE"""),7.0) -> 7 | AA6: =IFERROR(__xludf.DUMMYFUNCTION("""COMPUTED_VALUE"""),4.0) -> 4 | AB6: =IFERROR(__xludf.DUMMYFUNCTION("""COMPUTED_VALUE"""),"いいえ") -> いいえ | AK6: GxAKvz2 | AL6: jaQQQKx | AM6: 46031.241 | AN6: 18-25 | AO6: Female | AP6: Prefer not to say | AQ6: Kanto | AR6: Daily | AS6: Drip | AU6: Several times a week | AV6: Matcha Latte | AX6: =IFERROR(__xludf.DUMMYFUNCTION("""COMPUTED_VALUE"""),"Taste/Flavor") -> Taste/Flavor | AZ6: =IFERROR(__xludf.DUMMYFUNCTION("""COMPUTED_VALUE"""),"At home") -> At home | BB6: A few times a month | BC6: To relax or take a break | BE6: Quality of drinks | BG6: Yes, Western | BH6: Yes, Japanese | BI6: 7 | BJ6: 7 | BK6: 4 | BL6: No
A7: =IFERROR(__xludf.DUMMYFUNCTION("""COMPUTED_VALUE"""),"814zo8o") -> 814zo8o | B7: =IFERROR(__xludf.DUMMYFUNCTION("""COMPUTED_VALUE"""),"EkQQQyN") -> EkQQQyN | C7: =IFERROR(__xludf.DUMMYFUNCTION("""COMPUTED_VALUE"""),46031.24151620371) -> 46031.242 | D7: =IFERROR(__xludf.DUMMYFUNCTION("""COMPUTED_VALUE"""),"18〜25歳") -> 18〜25歳 | E7: =IFERROR(__xludf.DUMMYFUNCTION("""COMPUTED_VALUE"""),"女性") -> 女性 | F7: =IFERROR(__xludf.DUMMYFUNCTION("""COMPUTED_VALUE"""),"300万円〜599万9,999円") -> 300万円〜599万9,999円 | G7: =IFERROR(__xludf.DUMMYFUNCTION("""COMPUTED_VALUE"""),"関東") -> 関東 | H7: =IFERROR(__xludf.DUMMYFUNCTION("""COMPUTED_VALUE"""),"週に数回") -> 週に数回 | I7: =IFERROR(__xludf.DUMMYFUNCTION("""COMPUTED_VALUE"""),"ラテ") -> ラテ | K7: =IFERROR(__xludf.DUMMYFUNCTION("""COMPUTED_VALUE"""),"週に数回") -> 週に数回 | L7: =IFERROR(__xludf.DUMMYFUNCTION("""COMPUTED_VALUE"""),"抹茶ラテ") -> 抹茶ラテ | N7: =IFERROR(__xludf.DUMMYFUNCTION("""COMPUTED_VALUE"""),"味・風味") -> 味・風味 | P7: =IFERROR(__xludf.DUMMYFUNCTION("""COMPUTED_VALUE"""),"カフェで, 自宅で") -> カフェで, 自宅で | R7: =IFERROR(__xludf.DUMMYFUNCTION("""COMPUTED_VALUE"""),"月に数回") -> 月に数回 | S7: =IFERROR(__xludf.DUMMYFUNCTION("""COMPUTED_VALUE"""),"新しい飲み物を試すため") -> 新しい飲み物を試すため | U7: =IFERROR(__xludf.DUMMYFUNCTION("""COMPUTED_VALUE"""),"雰囲気・心地良さ") -> 雰囲気・心地良さ | W7: =IFERROR(__xludf.DUMMYFUNCTION("""COMPUTED_VALUE"""),"わからない") -> わからない | X7: =IFERROR(__xludf.DUMMYFUNCTION("""COMPUTED_VALUE"""),"はい（日本的）") -> はい（日本的） | Y7: =IFERROR(__xludf.DUMMYFUNCTION("""COMPUTED_VALUE"""),4.0) -> 4 | Z7: =IFERROR(__xludf.DUMMYFUNCTION("""COMPUTED_VALUE"""),5.0) -> 5 | AA7: =IFERROR(__xludf.DUMMYFUNCTION("""COMPUTED_VALUE"""),6.0) -> 6 | AB7: =IFERROR(__xludf.DUMMYFUNCTION("""COMPUTED_VALUE"""),"いいえ") -> いいえ | AK7: 814zo8o | AL7: EkQQQyN | AM7: 46031.242 | AN7: 18-25 | AO7: Female | AP7: ¥3,000,000 – ¥5,999,999 | AQ7: Kanto | AR7: Several times a week | AS7: Latte | AU7: Several times a week | AV7: Matcha Latte | AX7: =IFERROR(__xludf.DUMMYFUNCTION("""COMPUTED_VALUE"""),"Taste/Flavor") -> Taste/Flavor | AZ7: =IFERROR(__xludf.DUMMYFUNCTION("""COMPUTED_VALUE"""),"At cafés, At home") -> At cafés, At home | BB7: A few times a month | BC7: To try a new drink | BE7: Atmosphere | BG7: Unsure | BH7: Yes, Japanese | BI7: 4 | BJ7: 5 | BK7: 6 | BL7: No
A8: =IFERROR(__xludf.DUMMYFUNCTION("""COMPUTED_VALUE"""),"dWex1GN") -> dWex1GN | B8: =IFERROR(__xludf.DUMMYFUNCTION("""COMPUTED_VALUE"""),"NpWVjdB") -> NpWVjdB | C8: =IFERROR(__xludf.DUMMYFUNCTION("""COMPUTED_VALUE"""),46031.95395833333) -> 46031.954 | D8: =IFERROR(__xludf.DUMMYFUNCTION("""COMPUTED_VALUE"""),"18〜25歳") -> 18〜25歳 | E8: =IFERROR(__xludf.DUMMYFUNCTION("""COMPUTED_VALUE"""),"女性") -> 女性 | F8: =IFERROR(__xludf.DUMMYFUNCTION("""COMPUTED_VALUE"""),"300万円〜599万9,999円") -> 300万円〜599万9,999円 | G8: =IFERROR(__xludf.DUMMYFUNCTION("""COMPUTED_VALUE"""),"関東") -> 関東 | H8: =IFERROR(__xludf.DUMMYFUNCTION("""COMPUTED_VALUE"""),"毎日") -> 毎日 | I8: =IFERROR(__xludf.DUMMYFUNCTION("""COMPUTED_VALUE"""),"プアオーバー（ハンドドリップ）") -> プアオーバー（ハンドドリップ） | K8: =IFERROR(__xludf.DUMMYFUNCTION("""COMPUTED_VALUE"""),"週に1回") -> 週に1回 | L8: =IFERROR(__xludf.DUMMYFUNCTION("""COMPUTED_VALUE"""),"抹茶ラテ") -> 抹茶ラテ | N8: =IFERROR(__xludf.DUMMYFUNCTION("""COMPUTED_VALUE"""),"味・風味") -> 味・風味 | P8: =IFERROR(__xludf.DUMMYFUNCTION("""COMPUTED_VALUE"""),"カフェで") -> カフェで | R8: =IFERROR(__xludf.DUMMYFUNCTION("""COMPUTED_VALUE"""),"週に数回") -> 週に数回 | S8: =IFERROR(__xludf.DUMMYFUNCTION("""COMPUTED_VALUE"""),"休憩・リラックスするため") -> 休憩・リラックスするため | U8: =IFERROR(__xludf.DUMMYFUNCTION("""COMPUTED_VALUE"""),"サービス") -> サービス | W8: =IFERROR(__xludf.DUMMYFUNCTION("""COMPUTED_VALUE"""),"はい（グローバル）") -> はい（グローバル） | X8: =IFERROR(__xludf.DUMMYFUNCTION("""COMPUTED_VALUE"""),"はい（日本的）") -> はい（日本的） | Y8: =IFERROR(__xludf.DUMMYFUNCTION("""COMPUTED_VALUE"""),4.0) -> 4 | Z8: =IFERROR(__xludf.DUMMYFUNCTION("""COMPUTED_VALUE"""),5.0) -> 5 | AA8: =IFERROR(__xludf.DUMMYFUNCTION("""COMPUTED_VALUE"""),5.0) -> 5 | AB8: =IFERROR(__xludf.DUMMYFUNCTION("""COMPUTED_VALUE"""),"はい") -> はい | AK8: dWex1GN | AL8: NpWVjdB | AM8: 46031.954 | AN8: 18-25 | AO8: Female | AP8: ¥3,000,000 – ¥5,999,999 | AQ8: Kanto | AR8: Daily | AS8: Pour Over | AU8: Once a week | AV8: Matcha Latte | AX8: =IFERROR(__xludf.DUMMYFUNCTION("""COMPUTED_VALUE"""),"Taste/Flavor") -> Taste/Flavor | AZ8: =IFERROR(__xludf.DUMMYFUNCTION("""COMPUTED_VALUE"""),"At cafés") -> At cafés | BB8: Several times a week | BC8: To relax or take a break | BE8: Service | BG8: Yes, Global | BH8: Yes, Japanese | BI8: 4 | BJ8: 5 | BK8: 5 | BL8: Yes
A9: =IFERROR(__xludf.DUMMYFUNCTION("""COMPUTED_VALUE"""),"rjM6VAp") -> rjM6VAp | B9: =IFERROR(__xludf.DUMMYFUNCTION("""COMPUTED_VALUE"""),"RG5L4bP") -> RG5L4bP | C9: =IFERROR(__xludf.DUMMYFUNCTION("""COMPUTED_VALUE"""),46032.076203703706) -> 46032.076 | D9: =IFERROR(__xludf.DUMMYFUNCTION("""COMPUTED_VALUE"""),"26〜35歳") -> 26〜35歳 | E9: =IFERROR(__xludf.DUMMYFUNCTION("""COMPUTED_VALUE"""),"女性") -> 女性 | F9: =IFERROR(__xludf.DUMMYFUNCTION("""COMPUTED_VALUE"""),"300万円未満") -> 300万円未満 | G9: =IFERROR(__xludf.DUMMYFUNCTION("""COMPUTED_VALUE"""),"関東") -> 関東 | H9: =IFERROR(__xludf.DUMMYFUNCTION("""COMPUTED_VALUE"""),"週に数回") -> 週に数回 | I9: =IFERROR(__xludf.DUMMYFUNCTION("""COMPUTED_VALUE"""),"ラテ") -> ラテ | K9: =IFERROR(__xludf.DUMMYFUNCTION("""COMPUTED_VALUE"""),"ほとんど飲まない") -> ほとんど飲まない | L9: =IFERROR(__xludf.DUMMYFUNCTION("""COMPUTED_VALUE"""),"濃茶") -> 濃茶 | N9: =IFERROR(__xludf.DUMMYFUNCTION("""COMPUTED_VALUE"""),"味・風味") -> 味・風味 | P9: =IFERROR(__xludf.DUMMYFUNCTION("""COMPUTED_VALUE"""),"カフェで, コンビニ（セブンイレブン、ローソンなど）") -> カフェで, コンビニ（セブンイレブン、ローソンなど） | R9: =IFERROR(__xludf.DUMMYFUNCTION("""COMPUTED_VALUE"""),"ほとんど行かない") -> ほとんど行かない | S9: =IFERROR(__xludf.DUMMYFUNCTION("""COMPUTED_VALUE"""),"勉強・仕事をするため") -> 勉強・仕事をするため | U9: =IFERROR(__xludf.DUMMYFUNCTION("""COMPUTED_VALUE"""),"雰囲気・心地良さ") -> 雰囲気・心地良さ | W9: =IFERROR(__xludf.DUMMYFUNCTION("""COMPUTED_VALUE"""),"はい（西洋的）") -> はい（西洋的） | X9: =IFERROR(__xludf.DUMMYFUNCTION("""COMPUTED_VALUE"""),"はい（日本的）") -> はい（日本的） | Y9: =IFERROR(__xludf.DUMMYFUNCTION("""COMPUTED_VALUE"""),7.0) -> 7 | Z9: =IFERROR(__xludf.DUMMYFUNCTION("""COMPUTED_VALUE"""),7.0) -> 7 | AA9: =IFERROR(__xludf.DUMMYFUNCTION("""COMPUTED_VALUE"""),5.0) -> 5 | AB9: =IFERROR(__xludf.DUMMYFUNCTION("""COMPUTED_VALUE"""),"いいえ") -> いいえ | AK9: rjM6VAp | AL9: RG5L4bP | AM9: 46032.076 | AN9: 26-35 | AO9: Female | AP9: Under ¥3,000,000 | AQ9: Kanto | AR9: Several times a week | AS9: Latte | AU9: Rarely | AV9: Koicha | AX9: =IFERROR(__xludf.DUMMYFUNCTION("""COMPUTED_VALUE"""),"Taste/Flavor") -> Taste/Flavor | AZ9: =IFERROR(__xludf.DUMMYFUNCTION("""COMPUTED_VALUE"""),"At cafés, From convenience stores (7-Eleven, Lawson, etc.)") -> At cafés, From convenience stores (7-Eleven, Lawson, etc.) | BB9: Rarely | BC9: To study/work | BE9: Atmosphere | BG9: Yes, Western | BH9: Yes, Japanese | BI9: 7 | BJ9: 7 | BK9: 5 | BL9: No
A10: =IFERROR(__xludf.DUMMYFUNCTION("""COMPUTED_VALUE"""),"obLABbe") -> obLABbe | B10: =IFERROR(__xludf.DUMMYFUNCTION("""COMPUTED_VALUE"""),"QK50l5k") -> QK50l5k | C10: =IFERROR(__xludf.DUMMYFUNCTION("""COMPUTED_VALUE"""),46032.25387731481) -> 46032.254 | D10: =IFERROR(__xludf.DUMMYFUNCTION("""COMPUTED_VALUE"""),"18〜25歳") -> 18〜25歳 | E10: =IFERROR(__xludf.DUMMYFUNCTION("""COMPUTED_VALUE"""),"女性") -> 女性 | F10: =IFERROR(__xludf.DUMMYFUNCTION("""COMPUTED_VALUE"""),"300万円未満") -> 300万円未満 | G10: =IFERROR(__xludf.DUMMYFUNCTION("""COMPUTED_VALUE"""),"中部") -> 中部 | H10: =IFERROR(__xludf.DUMMYFUNCTION("""COMPUTED_VALUE"""),"毎日") -> 毎日 | I10: =IFERROR(__xludf.DUMMYFUNCTION("""COMPUTED_VALUE"""),"ラテ") -> ラテ | K10: =IFERROR(__xludf.DUMMYFUNCTION("""COMPUTED_VALUE"""),"ほとんど飲まない") -> ほとんど飲まない | L10: =IFERROR(__xludf.DUMMYFUNCTION("""COMPUTED_VALUE"""),"抹茶ラテ") -> 抹茶ラテ | N10: =IFERROR(__xludf.DUMMYFUNCTION("""COMPUTED_VALUE"""),"味・風味") -> 味・風味 | P10: =IFERROR(__xludf.DUMMYFUNCTION("""COMPUTED_VALUE"""),"カフェで") -> カフェで | R10: =IFERROR(__xludf.DUMMYFUNCTION("""COMPUTED_VALUE"""),"週に1回") -> 週に1回 | S10: =IFERROR(__xludf.DUMMYFUNCTION("""COMPUTED_VALUE"""),"勉強・仕事をするため") -> 勉強・仕事をするため | U10: =IFERROR(__xludf.DUMMYFUNCTION("""COMPUTED_VALUE"""),"雰囲気・心地良さ") -> 雰囲気・心地良さ | W10: =IFERROR(__xludf.DUMMYFUNCTION("""COMPUTED_VALUE"""),"はい（グローバル）") -> はい（グローバル） | X10: =IFERROR(__xludf.DUMMYFUNCTION("""COMPUTED_VALUE"""),"はい（日本的）") -> はい（日本的） | Y10: =IFERROR(__xludf.DUMMYFUNCTION("""COMPUTED_VALUE"""),4.0) -> 4 | Z10: =IFERROR(__xludf.DUMMYFUNCTION("""COMPUTED_VALUE"""),6.0) -> 6 | AA10: =IFERROR(__xludf.DUMMYFUNCTION("""COMPUTED_VALUE"""),6.0) -> 6 | AB10: =IFERROR(__xludf.DUMMYFUNCTION("""COMPUTED_VALUE"""),"いいえ") -> いいえ | AK10: obLABbe | AL10: QK50l5k | AM10: 46032.254 | AN10: 18-25 | AO10: Female | AP10: Under ¥3,000,000 | AQ10: Chubu | AR10: Daily | AS10: Latte | AU10: Rarely | AV10: Matcha Latte | AX10: =IFERROR(__xludf.DUMMYFUNCTION("""COMPUTED_VALUE"""),"Taste/Flavor") -> Taste/Flavor | AZ10: =IFERROR(__xludf.DUMMYFUNCTION("""COMPUTED_VALUE"""),"At cafés") -> At cafés | BB10: Once a week | BC10: To study/work | BE10: Atmosphere | BG10: Yes, Global | BH10: Yes, Japanese | BI10: 4 | BJ10: 6 | BK10: 6 | BL10: No
A11: =IFERROR(__xludf.DUMMYFUNCTION("""COMPUTED_VALUE"""),"KYKWO6z") -> KYKWO6z | B11: =IFERROR(__xludf.DUMMYFUNCTION("""COMPUTED_VALUE"""),"9qDpb2K") -> 9qDpb2K | C11: =IFERROR(__xludf.DUMMYFUNCTION("""COMPUTED_VALUE"""),46034.05730324074) -> 46034.057 | D11: =IFERROR(__xludf.DUMMYFUNCTION("""COMPUTED_VALUE"""),"18〜25歳") -> 18〜25歳 | E11: =IFERROR(__xludf.DUMMYFUNCTION("""COMPUTED_VALUE"""),"男性") -> 男性 | F11: =IFERROR(__xludf.DUMMYFUNCTION("""COMPUTED_VALUE"""),"300万円〜599万9,999円") -> 300万円〜599万9,999円 | G11: =IFERROR(__xludf.DUMMYFUNCTION("""COMPUTED_VALUE"""),"関東") -> 関東 | H11: =IFERROR(__xludf.DUMMYFUNCTION("""COMPUTED_VALUE"""),"毎日") -> 毎日 | I11: =IFERROR(__xludf.DUMMYFUNCTION("""COMPUTED_VALUE"""),"プアオーバー（ハンドドリップ）") -> プアオーバー（ハンドドリップ） | K11: =IFERROR(__xludf.DUMMYFUNCTION("""COMPUTED_VALUE"""),"ほとんど飲まない") -> ほとんど飲まない | L11: =IFERROR(__xludf.DUMMYFUNCTION("""COMPUTED_VALUE"""),"抹茶ラテ") -> 抹茶ラテ | N11: =IFERROR(__xludf.DUMMYFUNCTION("""COMPUTED_VALUE"""),"その他：") -> その他： | O11: =IFERROR(__xludf.DUMMYFUNCTION("""COMPUTED_VALUE"""),"近さ") -> 近さ | P11: =IFERROR(__xludf.DUMMYFUNCTION("""COMPUTED_VALUE"""),"カフェで, 自宅で") -> カフェで, 自宅で | R11: =IFERROR(__xludf.DUMMYFUNCTION("""COMPUTED_VALUE"""),"週に数回") -> 週に数回 | S11: =IFERROR(__xludf.DUMMYFUNCTION("""COMPUTED_VALUE"""),"習慣として") -> 習慣として | U11: =IFERROR(__xludf.DUMMYFUNCTION("""COMPUTED_VALUE"""),"飲み物の味・品質") -> 飲み物の味・品質 | W11: =IFERROR(__xludf.DUMMYFUNCTION("""COMPUTED_VALUE"""),"はい（グローバル）") -> はい（グローバル） | X11: =IFERROR(__xludf.DUMMYFUNCTION("""COMPUTED_VALUE"""),"はい（日本的）") -> はい（日本的） | Y11: =IFERROR(__xludf.DUMMYFUNCTION("""COMPUTED_VALUE"""),6.0) -> 6 | Z11: =IFERROR(__xludf.DUMMYFUNCTION("""COMPUTED_VALUE"""),6.0) -> 6 | AA11: =IFERROR(__xludf.DUMMYFUNCTION("""COMPUTED_VALUE"""),7.0) -> 7 | AB11: =IFERROR(__xludf.DUMMYFUNCTION("""COMPUTED_VALUE"""),"いいえ") -> いいえ | AK11: KYKWO6z | AL11: 9qDpb2K | AM11: 46034.057 | AN11: 18-25 | AO11: Male | AP11: ¥3,000,000 – ¥5,999,999 | AQ11: Kanto | AR11: Daily | AS11: Pour Over | AU11: Rarely | AV11: Matcha Latte | AX11: =IFERROR(__xludf.DUMMYFUNCTION("""COMPUTED_VALUE"""),"Other:") -> Other: | AY11: Proximity/closeness | AZ11: =IFERROR(__xludf.DUMMYFUNCTION("""COMPUTED_VALUE"""),"At cafés, At home") -> At cafés, At home | BB11: Several times a week | BC11: Out of habit | BE11: Quality of drinks | BG11: Yes, Global | BH11: Yes, Japanese | BI11: 6 | BJ11: 6 | BK11: 7 | BL11: No
A12: =IFERROR(__xludf.DUMMYFUNCTION("""COMPUTED_VALUE"""),"gD6Jpg4") -> gD6Jpg4 | B12: =IFERROR(__xludf.DUMMYFUNCTION("""COMPUTED_VALUE"""),"LZWvQYj") -> LZWvQYj | C12: =IFERROR(__xludf.DUMMYFUNCTION("""COMPUTED_VALUE"""),46034.06355324074) -> 46034.064 | D12: =IFERROR(__xludf.DUMMYFUNCTION("""COMPUTED_VALUE"""),"65歳以上") -> 65歳以上 | E12: =IFERROR(__xludf.DUMMYFUNCTION("""COMPUTED_VALUE"""),"男性") -> 男性 | F12: =IFERROR(__xludf.DUMMYFUNCTION("""COMPUTED_VALUE"""),"300万円〜599万9,999円") -> 300万円〜599万9,999円 | G12: =IFERROR(__xludf.DUMMYFUNCTION("""COMPUTED_VALUE"""),"関東") -> 関東 | H12: =IFERROR(__xludf.DUMMYFUNCTION("""COMPUTED_VALUE"""),"毎日") -> 毎日 | I12: =IFERROR(__xludf.DUMMYFUNCTION("""COMPUTED_VALUE"""),"ドリップコーヒー") -> ドリップコーヒー | K12: =IFERROR(__xludf.DUMMYFUNCTION("""COMPUTED_VALUE"""),"毎日") -> 毎日 | L12: =IFERROR(__xludf.DUMMYFUNCTION("""COMPUTED_VALUE"""),"薄茶") -> 薄茶 | N12: =IFERROR(__xludf.DUMMYFUNCTION("""COMPUTED_VALUE"""),"味・風味, 健康面のメリット") -> 味・風味, 健康面のメリット | P12: =IFERROR(__xludf.DUMMYFUNCTION("""COMPUTED_VALUE"""),"自宅で, 自動販売機") -> 自宅で, 自動販売機 | R12: =IFERROR(__xludf.DUMMYFUNCTION("""COMPUTED_VALUE"""),"月に数回") -> 月に数回 | S12: =IFERROR(__xludf.DUMMYFUNCTION("""COMPUTED_VALUE"""),"習慣として") -> 習慣として | U12: =IFERROR(__xludf.DUMMYFUNCTION("""COMPUTED_VALUE"""),"サービス") -> サービス | W12: =IFERROR(__xludf.DUMMYFUNCTION("""COMPUTED_VALUE"""),"はい（グローバル）") -> はい（グローバル） | X12: =IFERROR(__xludf.DUMMYFUNCTION("""COMPUTED_VALUE"""),"はい（日本的）") -> はい（日本的） | Y12: =IFERROR(__xludf.DUMMYFUNCTION("""COMPUTED_VALUE"""),7.0) -> 7 | Z12: =IFERROR(__xludf.DUMMYFUNCTION("""COMPUTED_VALUE"""),7.0) -> 7 | AA12: =IFERROR(__xludf.DUMMYFUNCTION("""COMPUTED_VALUE"""),4.0) -> 4 | AB12: =IFERROR(__xludf.DUMMYFUNCTION("""COMPUTED_VALUE"""),"いいえ") -> いいえ | AK12: gD6Jpg4 | AL12: LZWvQYj | AM12: 46034.064 | AN12: 65+ | AO12: Male | AP12: ¥3,000,000 – ¥5,999,999 | AQ12: Kanto | AR12: Daily | AS12: Drip | AU12: Daily | AV12: Usucha | AX12: =IFERROR(__xludf.DUMMYFUNCTION("""COMPUTED_VALUE"""),"Taste/Flavor, Health benefits") -> Taste/Flavor, Health benefits | AZ12: =IFERROR(__xludf.DUMMYFUNCTION("""COMPUTED_VALUE"""),"At home, From vending machines") -> At home, From vending machines | BB12: A few times a month | BC12: Out of habit | BE12: Service | BG12: Yes, Global | BH12: Yes, Japanese | BI12: 7 | BJ12: 7 | BK12: 4 | BL12: No
A13: =IFERROR(__xludf.DUMMYFUNCTION("""COMPUTED_VALUE"""),"Ek7ZY0N") -> Ek7ZY0N | B13: =IFERROR(__xludf.DUMMYFUNCTION("""COMPUTED_VALUE"""),"44xAgVY") -> 44xAgVY | C13: =IFERROR(__xludf.DUMMYFUNCTION("""COMPUTED_VALUE"""),46034.06655092593) -> 46034.067 | D13: =IFERROR(__xludf.DUMMYFUNCTION("""COMPUTED_VALUE"""),"56〜65歳") -> 56〜65歳 | E13: =IFERROR(__xludf.DUMMYFUNCTION("""COMPUTED_VALUE"""),"男性") -> 男性 | F13: =IFERROR(__xludf.DUMMYFUNCTION("""COMPUTED_VALUE"""),"1,200万円以上") -> 1,200万円以上 | G13: =IFERROR(__xludf.DUMMYFUNCTION("""COMPUTED_VALUE"""),"関西") -> 関西 | H13: =IFERROR(__xludf.DUMMYFUNCTION("""COMPUTED_VALUE"""),"毎日") -> 毎日 | I13: =IFERROR(__xludf.DUMMYFUNCTION("""COMPUTED_VALUE"""),"ドリップコーヒー") -> ドリップコーヒー | K13: =IFERROR(__xludf.DUMMYFUNCTION("""COMPUTED_VALUE"""),"ほとんど飲まない") -> ほとんど飲まない | L13: =IFERROR(__xludf.DUMMYFUNCTION("""COMPUTED_VALUE"""),"抹茶は飲まない") -> 抹茶は飲まない | N13: =IFERROR(__xludf.DUMMYFUNCTION("""COMPUTED_VALUE"""),"習慣, 味・風味") -> 習慣, 味・風味 | P13: =IFERROR(__xludf.DUMMYFUNCTION("""COMPUTED_VALUE"""),"自宅で, その他：") -> 自宅で, その他： | Q13: =IFERROR(__xludf.DUMMYFUNCTION("""COMPUTED_VALUE"""),"At office") -> At office | R13: =IFERROR(__xludf.DUMMYFUNCTION("""COMPUTED_VALUE"""),"ほとんど行かない") -> ほとんど行かない | S13: =IFERROR(__xludf.DUMMYFUNCTION("""COMPUTED_VALUE"""),"休憩・リラックスするため") -> 休憩・リラックスするため | U13: =IFERROR(__xludf.DUMMYFUNCTION("""COMPUTED_VALUE"""),"雰囲気・心地良さ") -> 雰囲気・心地良さ | W13: =IFERROR(__xludf.DUMMYFUNCTION("""COMPUTED_VALUE"""),"はい（西洋的）") -> はい（西洋的） | X13: =IFERROR(__xludf.DUMMYFUNCTION("""COMPUTED_VALUE"""),"はい（日本的）") -> はい（日本的） | Y13: =IFERROR(__xludf.DUMMYFUNCTION("""COMPUTED_VALUE"""),5.0) -> 5 | Z13: =IFERROR(__xludf.DUMMYFUNCTION("""COMPUTED_VALUE"""),6.0) -> 6 | AA13: =IFERROR(__xludf.DUMMYFUNCTION("""COMPUTED_VALUE"""),1.0) -> 1 | AB13: =IFERROR(__xludf.DUMMYFUNCTION("""COMPUTED_VALUE"""),"いいえ") -> いいえ | AK13: Ek7ZY0N | AL13: 44xAgVY | AM13: 46034.067 | AN13: 56-65 | AO13: Male | AP13: ¥12,000,000 or more | AQ13: Kansai | AR13: Daily | AS13: Drip | AU13: Rarely | AV13: I don’t drink matcha | AX13: =IFERROR(__xludf.DUMMYFUNCTION("""COMPUTED_VALUE"""),"Routine/Ritual, Taste/Flavor") -> Routine/Ritual, Taste/Flavor | AZ13: =IFERROR(__xludf.DUMMYFUNCTION("""COMPUTED_VALUE"""),"At home, Other:") -> At home, Other: | BA13: At office | BB13: Rarely | BC13: To relax or take a break | BE13: Atmosphere | BG13: Yes, Western | BH13: Yes, Japanese | BI13: 5 | BJ13: 6 | BK13: 1 | BL13: No
A14: =IFERROR(__xludf.DUMMYFUNCTION("""COMPUTED_VALUE"""),"gD6JBP1") -> gD6JBP1 | B14: =IFERROR(__xludf.DUMMYFUNCTION("""COMPUTED_VALUE"""),"xXaRM7y") -> xXaRM7y | C14: =IFERROR(__xludf.DUMMYFUNCTION("""COMPUTED_VALUE"""),46034.114224537036) -> 46034.114 | D14: =IFERROR(__xludf.DUMMYFUNCTION("""COMPUTED_VALUE"""),"46〜55歳") -> 46〜55歳 | E14: =IFERROR(__xludf.DUMMYFUNCTION("""COMPUTED_VALUE"""),"女性") -> 女性 | F14: =IFERROR(__xludf.DUMMYFUNCTION("""COMPUTED_VALUE"""),"1,200万円以上") -> 1,200万円以上 | G14: =IFERROR(__xludf.DUMMYFUNCTION("""COMPUTED_VALUE"""),"関東") -> 関東 | H14: =IFERROR(__xludf.DUMMYFUNCTION("""COMPUTED_VALUE"""),"毎日") -> 毎日 | I14: =IFERROR(__xludf.DUMMYFUNCTION("""COMPUTED_VALUE"""),"ドリップコーヒー") -> ドリップコーヒー | K14: =IFERROR(__xludf.DUMMYFUNCTION("""COMPUTED_VALUE"""),"ほとんど飲まない") -> ほとんど飲まない | L14: =IFERROR(__xludf.DUMMYFUNCTION("""COMPUTED_VALUE"""),"薄茶") -> 薄茶 | M14: =IFERROR(__xludf.DUMMYFUNCTION("""COMPUTED_VALUE"""),"煎茶を毎日飲みます") -> 煎茶を毎日飲みます | N14: =IFERROR(__xludf.DUMMYFUNCTION("""COMPUTED_VALUE"""),"エナジー／カフェイン, 味・風味") -> エナジー／カフェイン, 味・風味 | R14: =IFERROR(__xludf.DUMMYFUNCTION("""COMPUTED_VALUE"""),"週に数回") -> 週に数回 | S14: =IFERROR(__xludf.DUMMYFUNCTION("""COMPUTED_VALUE"""),"休憩・リラックスするため") -> 休憩・リラックスするため | U14: =IFERROR(__xludf.DUMMYFUNCTION("""COMPUTED_VALUE"""),"飲み物の味・品質") -> 飲み物の味・品質 | W14: =IFERROR(__xludf.DUMMYFUNCTION("""COMPUTED_VALUE"""),"いいえ") -> いいえ | X14: =IFERROR(__xludf.DUMMYFUNCTION("""COMPUTED_VALUE"""),"はい（日本的）") -> はい（日本的） | Y14: =IFERROR(__xludf.DUMMYFUNCTION("""COMPUTED_VALUE"""),5.0) -> 5 | Z14: =IFERROR(__xludf.DUMMYFUNCTION("""COMPUTED_VALUE"""),7.0) -> 7 | AA14: =IFERROR(__xludf.DUMMYFUNCTION("""COMPUTED_VALUE"""),5.0) -> 5 | AB14: =IFERROR(__xludf.DUMMYFUNCTION("""COMPUTED_VALUE"""),"いいえ") -> いいえ | AK14: gD6JBP1 | AL14: xXaRM7y | AM14: 46034.114 | AN14: 46-55 | AO14: Female | AP14: ¥12,000,000 or more | AQ14: Kanto | AR14: Daily | AS14: Drip | AU14: Rarely | AV14: Usucha | AW14: I drink sencha everyday | AX14: =IFERROR(__xludf.DUMMYFUNCTION("""COMPUTED_VALUE"""),"Energy boost/Caffeine, Taste/Flavor") -> Energy boost/Caffeine, Taste/Flavor | AZ14: =IFERROR(__xludf.DUMMYFUNCTION("""COMPUTED_VALUE"""),"") | BB14: Several times a week | BC14: To relax or take a break | BE14: Quality of drinks | BG14: No | BH14: Yes, Japanese | BI14: 5 | BJ14: 7 | BK14: 5 | BL14: No
A15: =IFERROR(__xludf.DUMMYFUNCTION("""COMPUTED_VALUE"""),"rjMkOgL") -> rjMkOgL | B15: =IFERROR(__xludf.DUMMYFUNCTION("""COMPUTED_VALUE"""),"aQYABpZ") -> aQYABpZ | C15: =IFERROR(__xludf.DUMMYFUNCTION("""COMPUTED_VALUE"""),46034.16165509259) -> 46034.162 | D15: =IFERROR(__xludf.DUMMYFUNCTION("""COMPUTED_VALUE"""),"36〜45歳") -> 36〜45歳 | E15: =IFERROR(__xludf.DUMMYFUNCTION("""COMPUTED_VALUE"""),"女性") -> 女性 | F15: =IFERROR(__xludf.DUMMYFUNCTION("""COMPUTED_VALUE"""),"1,200万円以上") -> 1,200万円以上 | G15: =IFERROR(__xludf.DUMMYFUNCTION("""COMPUTED_VALUE"""),"関東") -> 関東 | H15: =IFERROR(__xludf.DUMMYFUNCTION("""COMPUTED_VALUE"""),"週に1回") -> 週に1回 | I15: =IFERROR(__xludf.DUMMYFUNCTION("""COMPUTED_VALUE"""),"ラテ") -> ラテ | K15: =IFERROR(__xludf.DUMMYFUNCTION("""COMPUTED_VALUE"""),"ほとんど飲まない") -> ほとんど飲まない | L15: =IFERROR(__xludf.DUMMYFUNCTION("""COMPUTED_VALUE"""),"抹茶は飲まない") -> 抹茶は飲まない | N15: =IFERROR(__xludf.DUMMYFUNCTION("""COMPUTED_VALUE"""),"習慣") -> 習慣 | P15: =IFERROR(__xludf.DUMMYFUNCTION("""COMPUTED_VALUE"""),"カフェで") -> カフェで | R15: =IFERROR(__xludf.DUMMYFUNCTION("""COMPUTED_VALUE"""),"週に1回") -> 週に1回 | S15: =IFERROR(__xludf.DUMMYFUNCTION("""COMPUTED_VALUE"""),"休憩・リラックスするため") -> 休憩・リラックスするため | U15: =IFERROR(__xludf.DUMMYFUNCTION("""COMPUTED_VALUE"""),"飲み物の味・品質") -> 飲み物の味・品質 | W15: =IFERROR(__xludf.DUMMYFUNCTION("""COMPUTED_VALUE"""),"はい（西洋的）") -> はい（西洋的） | X15: =IFERROR(__xludf.DUMMYFUNCTION("""COMPUTED_VALUE"""),"はい（日本的）") -> はい（日本的） | Y15: =IFERROR(__xludf.DUMMYFUNCTION("""COMPUTED_VALUE"""),4.0) -> 4 | Z15: =IFERROR(__xludf.DUMMYFUNCTION("""COMPUTED_VALUE"""),7.0) -> 7 | AA15: =IFERROR(__xludf.DUMMYFUNCTION("""COMPUTED_VALUE"""),3.0) -> 3 | AB15: =IFERROR(__xludf.DUMMYFUNCTION("""COMPUTED_VALUE"""),"いいえ") -> いいえ | AK15: rjMkOgL | AL15: aQYABpZ | AM15: 46034.162 | AN15: 36-45 | AO15: Female | AP15: ¥12,000,000 or more | AQ15: Kanto | AR15: Once a week | AS15: Latte | AU15: Rarely | AV15: I don’t drink matcha | AX15: =IFERROR(__xludf.DUMMYFUNCTION("""COMPUTED_VALUE"""),"Routine/Ritual") -> Routine/Ritual | AZ15: =IFERROR(__xludf.DUMMYFUNCTION("""COMPUTED_VALUE"""),"At cafés") -> At cafés | BB15: Once a week | BC15: To relax or take a break | BE15: Quality of drinks | BG15: Yes, Western | BH15: Yes, Japanese | BI15: 4 | BJ15: 7 | BK15: 3 | BL15: No
A16: =IFERROR(__xludf.DUMMYFUNCTION("""COMPUTED_VALUE"""),"0QRD61Q") -> 0QRD61Q | B16: =IFERROR(__xludf.DUMMYFUNCTION("""COMPUTED_VALUE"""),"OD5b0zp") -> OD5b0zp | C16: =IFERROR(__xludf.DUMMYFUNCTION("""COMPUTED_VALUE"""),46034.174108796295) -> 46034.174 | D16: =IFERROR(__xludf.DUMMYFUNCTION("""COMPUTED_VALUE"""),"18〜25歳") -> 18〜25歳 | E16: =IFERROR(__xludf.DUMMYFUNCTION("""COMPUTED_VALUE"""),"女性") -> 女性 | F16: =IFERROR(__xludf.DUMMYFUNCTION("""COMPUTED_VALUE"""),"300万円未満") -> 300万円未満 | G16: =IFERROR(__xludf.DUMMYFUNCTION("""COMPUTED_VALUE"""),"中部") -> 中部 | H16: =IFERROR(__xludf.DUMMYFUNCTION("""COMPUTED_VALUE"""),"毎日") -> 毎日 | I16: =IFERROR(__xludf.DUMMYFUNCTION("""COMPUTED_VALUE"""),"プアオーバー（ハンドドリップ）") -> プアオーバー（ハンドドリップ） | K16: =IFERROR(__xludf.DUMMYFUNCTION("""COMPUTED_VALUE"""),"週に数回") -> 週に数回 | L16: =IFERROR(__xludf.DUMMYFUNCTION("""COMPUTED_VALUE"""),"抹茶ラテ") -> 抹茶ラテ | N16: =IFERROR(__xludf.DUMMYFUNCTION("""COMPUTED_VALUE"""),"その他：, 習慣") -> その他：, 習慣 | R16: =IFERROR(__xludf.DUMMYFUNCTION("""COMPUTED_VALUE"""),"月に数回") -> 月に数回 | S16: =IFERROR(__xludf.DUMMYFUNCTION("""COMPUTED_VALUE"""),"新しい飲み物を試すため") -> 新しい飲み物を試すため | U16: =IFERROR(__xludf.DUMMYFUNCTION("""COMPUTED_VALUE"""),"雰囲気・心地良さ") -> 雰囲気・心地良さ | W16: =IFERROR(__xludf.DUMMYFUNCTION("""COMPUTED_VALUE"""),"はい（グローバル）") -> はい（グローバル） | X16: =IFERROR(__xludf.DUMMYFUNCTION("""COMPUTED_VALUE"""),"はい（日本的）") -> はい（日本的） | Y16: =IFERROR(__xludf.DUMMYFUNCTION("""COMPUTED_VALUE"""),5.0) -> 5 | Z16: =IFERROR(__xludf.DUMMYFUNCTION("""COMPUTED_VALUE"""),4.0) -> 4 | AA16: =IFERROR(__xludf.DUMMYFUNCTION("""COMPUTED_VALUE"""),6.0) -> 6 | AB16: =IFERROR(__xludf.DUMMYFUNCTION("""COMPUTED_VALUE"""),"いいえ") -> いいえ | AK16: 0QRD61Q | AL16: OD5b0zp | AM16: 46034.174 | AN16: 18-25 | AO16: Female | AP16: Under ¥3,000,000 | AQ16: Chubu | AR16: Daily | AS16: Pour Over | AU16: Several times a week | AV16: Matcha Latte | AX16: =IFERROR(__xludf.DUMMYFUNCTION("""COMPUTED_VALUE"""),"Other:, Routine/Ritual") -> Other:, Routine/Ritual | AZ16: =IFERROR(__xludf.DUMMYFUNCTION("""COMPUTED_VALUE"""),"") | BB16: A few times a month | BC16: To try a new drink | BE16: Atmosphere | BG16: Yes, Global | BH16: Yes, Japanese | BI16: 5 | BJ16: 4 | BK16: 6 | BL16: No
A17: =IFERROR(__xludf.DUMMYFUNCTION("""COMPUTED_VALUE"""),"GxAQrlz") -> GxAQrlz | B17: =IFERROR(__xludf.DUMMYFUNCTION("""COMPUTED_VALUE"""),"q4AJOG9") -> q4AJOG9 | C17: =IFERROR(__xludf.DUMMYFUNCTION("""COMPUTED_VALUE"""),46034.18221064815) -> 46034.182 | D17: =IFERROR(__xludf.DUMMYFUNCTION("""COMPUTED_VALUE"""),"26〜35歳") -> 26〜35歳 | E17: =IFERROR(__xludf.DUMMYFUNCTION("""COMPUTED_VALUE"""),"女性") -> 女性 | F17: =IFERROR(__xludf.DUMMYFUNCTION("""COMPUTED_VALUE"""),"300万円未満") -> 300万円未満 | G17: =IFERROR(__xludf.DUMMYFUNCTION("""COMPUTED_VALUE"""),"関西") -> 関西 | H17: =IFERROR(__xludf.DUMMYFUNCTION("""COMPUTED_VALUE"""),"まったく飲まない") -> まったく飲まない | K17: =IFERROR(__xludf.DUMMYFUNCTION("""COMPUTED_VALUE"""),"週に数回") -> 週に数回 | L17: =IFERROR(__xludf.DUMMYFUNCTION("""COMPUTED_VALUE"""),"薄茶") -> 薄茶 | N17: =IFERROR(__xludf.DUMMYFUNCTION("""COMPUTED_VALUE"""),"社交的な場や雰囲気の考慮, 味・風味") -> 社交的な場や雰囲気の考慮, 味・風味 | P17: =IFERROR(__xludf.DUMMYFUNCTION("""COMPUTED_VALUE"""),"その他：") -> その他： | Q17: =IFERROR(__xludf.DUMMYFUNCTION("""COMPUTED_VALUE"""),"仕事") -> 仕事 | R17: =IFERROR(__xludf.DUMMYFUNCTION("""COMPUTED_VALUE"""),"月に数回") -> 月に数回 | S17: =IFERROR(__xludf.DUMMYFUNCTION("""COMPUTED_VALUE"""),"休憩・リラックスするため") -> 休憩・リラックスするため | U17: =IFERROR(__xludf.DUMMYFUNCTION("""COMPUTED_VALUE"""),"雰囲気・心地良さ") -> 雰囲気・心地良さ | W17: =IFERROR(__xludf.DUMMYFUNCTION("""COMPUTED_VALUE"""),"はい（グローバル）") -> はい（グローバル） | X17: =IFERROR(__xludf.DUMMYFUNCTION("""COMPUTED_VALUE"""),"はい（日本的）") -> はい（日本的） | Y17: =IFERROR(__xludf.DUMMYFUNCTION("""COMPUTED_VALUE"""),5.0) -> 5 | Z17: =IFERROR(__xludf.DUMMYFUNCTION("""COMPUTED_VALUE"""),7.0) -> 7 | AA17: =IFERROR(__xludf.DUMMYFUNCTION("""COMPUTED_VALUE"""),7.0) -> 7 | AB17: =IFERROR(__xludf.DUMMYFUNCTION("""COMPUTED_VALUE"""),"いいえ") -> いいえ | AK17: GxAQrlz | AL17: q4AJOG9 | AM17: 46034.182 | AN17: 26-35 | AO17: Female | AP17: Under ¥3,000,000 | AQ17: Kansai | AR17: Never | AU17: Several times a week | AV17: Usucha | AX17: =IFERROR(__xludf.DUMMYFUNCTION("""COMPUTED_VALUE"""),"Social atmosphere, Taste/Flavor") -> Social atmosphere, Taste/Flavor | AZ17: =IFERROR(__xludf.DUMMYFUNCTION("""COMPUTED_VALUE"""),"Other:") -> Other: | BA17: Work | BB17: A few times a month | BC17: To relax or take a break | BE17: Atmosphere | BG17: Yes, Global | BH17: Yes, Japanese | BI17: 5 | BJ17: 7 | BK17: 7 | BL17: No
A18: =IFERROR(__xludf.DUMMYFUNCTION("""COMPUTED_VALUE"""),"Y5lxOQ6") -> Y5lxOQ6 | B18: =IFERROR(__xludf.DUMMYFUNCTION("""COMPUTED_VALUE"""),"Y5WJrKW") -> Y5WJrKW | C18: =IFERROR(__xludf.DUMMYFUNCTION("""COMPUTED_VALUE"""),46034.18680555555) -> 46034.187 | D18: =IFERROR(__xludf.DUMMYFUNCTION("""COMPUTED_VALUE"""),"26〜35歳") -> 26〜35歳 | E18: =IFERROR(__xludf.DUMMYFUNCTION("""COMPUTED_VALUE"""),"男性") -> 男性 | F18: =IFERROR(__xludf.DUMMYFUNCTION("""COMPUTED_VALUE"""),"300万円〜599万9,999円") -> 300万円〜599万9,999円 | G18: =IFERROR(__xludf.DUMMYFUNCTION("""COMPUTED_VALUE"""),"関西") -> 関西 | H18: =IFERROR(__xludf.DUMMYFUNCTION("""COMPUTED_VALUE"""),"週に1回") -> 週に1回 | I18: =IFERROR(__xludf.DUMMYFUNCTION("""COMPUTED_VALUE"""),"ドリップコーヒー") -> ドリップコーヒー | K18: =IFERROR(__xludf.DUMMYFUNCTION("""COMPUTED_VALUE"""),"毎日") -> 毎日 | L18: =IFERROR(__xludf.DUMMYFUNCTION("""COMPUTED_VALUE"""),"薄茶") -> 薄茶 | N18: =IFERROR(__xludf.DUMMYFUNCTION("""COMPUTED_VALUE"""),"習慣, 味・風味") -> 習慣, 味・風味 | P18: =IFERROR(__xludf.DUMMYFUNCTION("""COMPUTED_VALUE"""),"その他：, 自宅で") -> その他：, 自宅で | R18: =IFERROR(__xludf.DUMMYFUNCTION("""COMPUTED_VALUE"""),"週に1回") -> 週に1回 | S18: =IFERROR(__xludf.DUMMYFUNCTION("""COMPUTED_VALUE"""),"休憩・リラックスするため") -> 休憩・リラックスするため | U18: =IFERROR(__xludf.DUMMYFUNCTION("""COMPUTED_VALUE"""),"サービス") -> サービス | W18: =IFERROR(__xludf.DUMMYFUNCTION("""COMPUTED_VALUE"""),"はい（グローバル）") -> はい（グローバル） | X18: =IFERROR(__xludf.DUMMYFUNCTION("""COMPUTED_VALUE"""),"はい（グローバル）") -> はい（グローバル） | Y18: =IFERROR(__xludf.DUMMYFUNCTION("""COMPUTED_VALUE"""),7.0) -> 7 | Z18: =IFERROR(__xludf.DUMMYFUNCTION("""COMPUTED_VALUE"""),7.0) -> 7 | AA18: =IFERROR(__xludf.DUMMYFUNCTION("""COMPUTED_VALUE"""),5.0) -> 5 | AB18: =IFERROR(__xludf.DUMMYFUNCTION("""COMPUTED_VALUE"""),"はい") -> はい | AK18: Y5lxOQ6 | AL18: Y5WJrKW | AM18: 46034.187 | AN18: 26-35 | AO18: Male | AP18: ¥3,000,000 – ¥5,999,999 | AQ18: Kansai | AR18: Once a week | AS18: Drip | AU18: Daily | AV18: Usucha | AX18: =IFERROR(__xludf.DUMMYFUNCTION("""COMPUTED_VALUE"""),"Routine/Ritual, Taste/Flavor") -> Routine/Ritual, Taste/Flavor | AZ18: =IFERROR(__xludf.DUMMYFUNCTION("""COMPUTED_VALUE"""),"Other:, At home") -> Other:, At home | BB18: Once a week | BC18: To relax or take a break | BE18: Service | BG18: Yes, Global | BH18: Yes, Global | BI18: 7 | BJ18: 7 | BK18: 5 | BL18: Yes
A19: =IFERROR(__xludf.DUMMYFUNCTION("""COMPUTED_VALUE"""),"Ek7NOBr") -> Ek7NOBr | B19: =IFERROR(__xludf.DUMMYFUNCTION("""COMPUTED_VALUE"""),"J9AeG1K") -> J9AeG1K | C19: =IFERROR(__xludf.DUMMYFUNCTION("""COMPUTED_VALUE"""),46034.28605324074) -> 46034.286 | D19: =IFERROR(__xludf.DUMMYFUNCTION("""COMPUTED_VALUE"""),"26〜35歳") -> 26〜35歳 | E19: =IFERROR(__xludf.DUMMYFUNCTION("""COMPUTED_VALUE"""),"男性") -> 男性 | F19: =IFERROR(__xludf.DUMMYFUNCTION("""COMPUTED_VALUE"""),"300万円〜599万9,999円") -> 300万円〜599万9,999円 | G19: =IFERROR(__xludf.DUMMYFUNCTION("""COMPUTED_VALUE"""),"九州") -> 九州 | H19: =IFERROR(__xludf.DUMMYFUNCTION("""COMPUTED_VALUE"""),"毎日") -> 毎日 | I19: =IFERROR(__xludf.DUMMYFUNCTION("""COMPUTED_VALUE"""),"ドリップコーヒー") -> ドリップコーヒー | K19: =IFERROR(__xludf.DUMMYFUNCTION("""COMPUTED_VALUE"""),"ほとんど飲まない") -> ほとんど飲まない | L19: =IFERROR(__xludf.DUMMYFUNCTION("""COMPUTED_VALUE"""),"濃茶") -> 濃茶 | N19: =IFERROR(__xludf.DUMMYFUNCTION("""COMPUTED_VALUE"""),"味・風味") -> 味・風味 | P19: =IFERROR(__xludf.DUMMYFUNCTION("""COMPUTED_VALUE"""),"自宅で, カフェで, コンビニ（セブンイレブン、ローソンなど）, 自動販売機") -> 自宅で, カフェで, コンビニ（セブンイレブン、ローソンなど）, 自動販売機 | R19: =IFERROR(__xludf.DUMMYFUNCTION("""COMPUTED_VALUE"""),"月に数回") -> 月に数回 | S19: =IFERROR(__xludf.DUMMYFUNCTION("""COMPUTED_VALUE"""),"休憩・リラックスするため") -> 休憩・リラックスするため | U19: =IFERROR(__xludf.DUMMYFUNCTION("""COMPUTED_VALUE"""),"飲み物の味・品質") -> 飲み物の味・品質 | W19: =IFERROR(__xludf.DUMMYFUNCTION("""COMPUTED_VALUE"""),"はい（グローバル）") -> はい（グローバル） | X19: =IFERROR(__xludf.DUMMYFUNCTION("""COMPUTED_VALUE"""),"はい（日本的）") -> はい（日本的） | Y19: =IFERROR(__xludf.DUMMYFUNCTION("""COMPUTED_VALUE"""),7.0) -> 7 | Z19: =IFERROR(__xludf.DUMMYFUNCTION("""COMPUTED_VALUE"""),7.0) -> 7 | AA19: =IFERROR(__xludf.DUMMYFUNCTION("""COMPUTED_VALUE"""),7.0) -> 7 | AB19: =IFERROR(__xludf.DUMMYFUNCTION("""COMPUTED_VALUE"""),"はい") -> はい | AK19: Ek7NOBr | AL19: J9AeG1K | AM19: 46034.286 | AN19: 26-35 | AO19: Male | AP19: ¥3,000,000 – ¥5,999,999 | AQ19: Kyushu | AR19: Daily | AS19: Drip | AU19: Rarely | AV19: Koicha | AX19: =IFERROR(__xludf.DUMMYFUNCTION("""COMPUTED_VALUE"""),"Taste/Flavor") -> Taste/Flavor | AZ19: =IFERROR(__xludf.DUMMYFUNCTION("""COMPUTED_VALUE"""),"At home, At cafés, From convenience stores (7-Eleven, Lawson, etc.), From vending machines") -> At home, At cafés, From convenience stores (7-Eleven, Lawson, etc.), From vending machines | BB19: A few times a month | BC19: To relax or take a break | BE19: Quality of drinks | BG19: Yes, Global | BH19: Yes, Japanese | BI19: 7 | BJ19: 7 | BK19: 7 | BL19: Yes
A20: =IFERROR(__xludf.DUMMYFUNCTION("""COMPUTED_VALUE"""),"eqWY140") -> eqWY140 | B20: =IFERROR(__xludf.DUMMYFUNCTION("""COMPUTED_VALUE"""),"vGyJ12X") -> vGyJ12X | C20: =IFERROR(__xludf.DUMMYFUNCTION("""COMPUTED_VALUE"""),46034.31005787037) -> 46034.31 | D20: =IFERROR(__xludf.DUMMYFUNCTION("""COMPUTED_VALUE"""),"65歳以上") -> 65歳以上 | E20: =IFERROR(__xludf.DUMMYFUNCTION("""COMPUTED_VALUE"""),"男性") -> 男性 | F20: =IFERROR(__xludf.DUMMYFUNCTION("""COMPUTED_VALUE"""),"1,200万円以上") -> 1,200万円以上 | G20: =IFERROR(__xludf.DUMMYFUNCTION("""COMPUTED_VALUE"""),"関東") -> 関東 | H20: =IFERROR(__xludf.DUMMYFUNCTION("""COMPUTED_VALUE"""),"週に1回") -> 週に1回 | I20: =IFERROR(__xludf.DUMMYFUNCTION("""COMPUTED_VALUE"""),"フレーバーコーヒー（モカ、バニラ、キャラメルなど）") -> フレーバーコーヒー（モカ、バニラ、キャラメルなど） | K20: =IFERROR(__xludf.DUMMYFUNCTION("""COMPUTED_VALUE"""),"週に1回") -> 週に1回 | L20: =IFERROR(__xludf.DUMMYFUNCTION("""COMPUTED_VALUE"""),"濃茶") -> 濃茶 | N20: =IFERROR(__xludf.DUMMYFUNCTION("""COMPUTED_VALUE"""),"健康面のメリット") -> 健康面のメリット | P20: =IFERROR(__xludf.DUMMYFUNCTION("""COMPUTED_VALUE"""),"自宅で") -> 自宅で | R20: =IFERROR(__xludf.DUMMYFUNCTION("""COMPUTED_VALUE"""),"ほとんど行かない") -> ほとんど行かない | S20: =IFERROR(__xludf.DUMMYFUNCTION("""COMPUTED_VALUE"""),"休憩・リラックスするため") -> 休憩・リラックスするため | U20: =IFERROR(__xludf.DUMMYFUNCTION("""COMPUTED_VALUE"""),"雰囲気・心地良さ") -> 雰囲気・心地良さ | W20: =IFERROR(__xludf.DUMMYFUNCTION("""COMPUTED_VALUE"""),"いいえ") -> いいえ | X20: =IFERROR(__xludf.DUMMYFUNCTION("""COMPUTED_VALUE"""),"はい（日本的）") -> はい（日本的） | Y20: =IFERROR(__xludf.DUMMYFUNCTION("""COMPUTED_VALUE"""),6.0) -> 6 | Z20: =IFERROR(__xludf.DUMMYFUNCTION("""COMPUTED_VALUE"""),7.0) -> 7 | AA20: =IFERROR(__xludf.DUMMYFUNCTION("""COMPUTED_VALUE"""),4.0) -> 4 | AB20: =IFERROR(__xludf.DUMMYFUNCTION("""COMPUTED_VALUE"""),"いいえ") -> いいえ | AK20: eqWY140 | AL20: vGyJ12X | AM20: 46034.31 | AN20: 65+ | AO20: Male | AP20: ¥12,000,000 or more | AQ20: Kanto | AR20: Once a week | AS20: Flavored coffee (mocha, vanilla, caramel, etc.) | AU20: Once a week | AV20: Koicha | AX20: =IFERROR(__xludf.DUMMYFUNCTION("""COMPUTED_VALUE"""),"Health benefits") -> Health benefits | AZ20: =IFERROR(__xludf.DUMMYFUNCTION("""COMPUTED_VALUE"""),"At home") -> At home | BB20: Rarely | BC20: To relax or take a break | BE20: Atmosphere | BG20: No | BH20: Yes, Japanese | BI20: 6 | BJ20: 7 | BK20: 4 | BL20: No
A21: =IFERROR(__xludf.DUMMYFUNCTION("""COMPUTED_VALUE"""),"lbkvb1W") -> lbkvb1W | B21: =IFERROR(__xludf.DUMMYFUNCTION("""COMPUTED_VALUE"""),"EkQZE4l") -> EkQZE4l | C21: =IFERROR(__xludf.DUMMYFUNCTION("""COMPUTED_VALUE"""),46034.315) -> 46034.315 | D21: =IFERROR(__xludf.DUMMYFUNCTION("""COMPUTED_VALUE"""),"26〜35歳") -> 26〜35歳 | E21: =IFERROR(__xludf.DUMMYFUNCTION("""COMPUTED_VALUE"""),"女性") -> 女性 | F21: =IFERROR(__xludf.DUMMYFUNCTION("""COMPUTED_VALUE"""),"600万円〜899万9,999円") -> 600万円〜899万9,999円 | G21: =IFERROR(__xludf.DUMMYFUNCTION("""COMPUTED_VALUE"""),"関東") -> 関東 | H21: =IFERROR(__xludf.DUMMYFUNCTION("""COMPUTED_VALUE"""),"毎日") -> 毎日 | I21: =IFERROR(__xludf.DUMMYFUNCTION("""COMPUTED_VALUE"""),"ドリップコーヒー") -> ドリップコーヒー | K21: =IFERROR(__xludf.DUMMYFUNCTION("""COMPUTED_VALUE"""),"ほとんど飲まない") -> ほとんど飲まない | L21: =IFERROR(__xludf.DUMMYFUNCTION("""COMPUTED_VALUE"""),"抹茶ラテ") -> 抹茶ラテ | N21: =IFERROR(__xludf.DUMMYFUNCTION("""COMPUTED_VALUE"""),"習慣, 味・風味") -> 習慣, 味・風味 | P21: =IFERROR(__xludf.DUMMYFUNCTION("""COMPUTED_VALUE"""),"自宅で, コンビニ（セブンイレブン、ローソンなど）") -> 自宅で, コンビニ（セブンイレブン、ローソンなど） | R21: =IFERROR(__xludf.DUMMYFUNCTION("""COMPUTED_VALUE"""),"月に数回") -> 月に数回 | S21: =IFERROR(__xludf.DUMMYFUNCTION("""COMPUTED_VALUE"""),"友人と会うため") -> 友人と会うため | U21: =IFERROR(__xludf.DUMMYFUNCTION("""COMPUTED_VALUE"""),"雰囲気・心地良さ") -> 雰囲気・心地良さ | W21: =IFERROR(__xludf.DUMMYFUNCTION("""COMPUTED_VALUE"""),"いいえ") -> いいえ | X21: =IFERROR(__xludf.DUMMYFUNCTION("""COMPUTED_VALUE"""),"いいえ") -> いいえ | Y21: =IFERROR(__xludf.DUMMYFUNCTION("""COMPUTED_VALUE"""),7.0) -> 7 | Z21: =IFERROR(__xludf.DUMMYFUNCTION("""COMPUTED_VALUE"""),4.0) -> 4 | AA21: =IFERROR(__xludf.DUMMYFUNCTION("""COMPUTED_VALUE"""),4.0) -> 4 | AB21: =IFERROR(__xludf.DUMMYFUNCTION("""COMPUTED_VALUE"""),"いいえ") -> いいえ | AK21: lbkvb1W | AL21: EkQZE4l | AM21: 46034.315 | AN21: 26-35 | AO21: Female | AP21: ¥6,000,000 – ¥8,999,999 | AQ21: Kanto | AR21: Daily | AS21: Drip | AU21: Rarely | AV21: Matcha Latte | AX21: =IFERROR(__xludf.DUMMYFUNCTION("""COMPUTED_VALUE"""),"Routine/Ritual, Taste/Flavor") -> Routine/Ritual, Taste/Flavor | AZ21: =IFERROR(__xludf.DUMMYFUNCTION("""COMPUTED_VALUE"""),"At home, From convenience stores (7-Eleven, Lawson, etc.)") -> At home, From convenience stores (7-Eleven, Lawson, etc.) | BB21: A few times a month | BC21: To meet friends | BE21: Atmosphere | BG21: No | BH21: No | BI21: 7 | BJ21: 4 | BK21: 4 | BL21: No
A22: =IFERROR(__xludf.DUMMYFUNCTION("""COMPUTED_VALUE"""),"68EP7gY") -> 68EP7gY | B22: =IFERROR(__xludf.DUMMYFUNCTION("""COMPUTED_VALUE"""),"2ENDrBg") -> 2ENDrBg | C22: =IFERROR(__xludf.DUMMYFUNCTION("""COMPUTED_VALUE"""),46034.46233796296) -> 46034.462 | D22: =IFERROR(__xludf.DUMMYFUNCTION("""COMPUTED_VALUE"""),"56〜65歳") -> 56〜65歳 | E22: =IFERROR(__xludf.DUMMYFUNCTION("""COMPUTED_VALUE"""),"男性") -> 男性 | F22: =IFERROR(__xludf.DUMMYFUNCTION("""COMPUTED_VALUE"""),"600万円〜899万9,999円") -> 600万円〜899万9,999円 | G22: =IFERROR(__xludf.DUMMYFUNCTION("""COMPUTED_VALUE"""),"関東") -> 関東 | H22: =IFERROR(__xludf.DUMMYFUNCTION("""COMPUTED_VALUE"""),"毎日") -> 毎日 | I22: =IFERROR(__xludf.DUMMYFUNCTION("""COMPUTED_VALUE"""),"ドリップコーヒー") -> ドリップコーヒー | K22: =IFERROR(__xludf.DUMMYFUNCTION("""COMPUTED_VALUE"""),"ほとんど飲まない") -> ほとんど飲まない | L22: =IFERROR(__xludf.DUMMYFUNCTION("""COMPUTED_VALUE"""),"抹茶ラテ") -> 抹茶ラテ | N22: =IFERROR(__xludf.DUMMYFUNCTION("""COMPUTED_VALUE"""),"味・風味, 社会的トレンドに同調・周囲の影響（周りの人がよく飲んでいるもの）") -> 味・風味, 社会的トレンドに同調・周囲の影響（周りの人がよく飲んでいるもの） | P22: =IFERROR(__xludf.DUMMYFUNCTION("""COMPUTED_VALUE"""),"コンビニ（セブンイレブン、ローソンなど）, その他：") -> コンビニ（セブンイレブン、ローソンなど）, その他： | Q22: =IFERROR(__xludf.DUMMYFUNCTION("""COMPUTED_VALUE"""),"オフィス") -> オフィス | R22: =IFERROR(__xludf.DUMMYFUNCTION("""COMPUTED_VALUE"""),"月に数回") -> 月に数回 | S22: =IFERROR(__xludf.DUMMYFUNCTION("""COMPUTED_VALUE"""),"勉強・仕事をするため") -> 勉強・仕事をするため | U22: =IFERROR(__xludf.DUMMYFUNCTION("""COMPUTED_VALUE"""),"雰囲気・心地良さ") -> 雰囲気・心地良さ | W22: =IFERROR(__xludf.DUMMYFUNCTION("""COMPUTED_VALUE"""),"はい（西洋的）") -> はい（西洋的） | X22: =IFERROR(__xludf.DUMMYFUNCTION("""COMPUTED_VALUE"""),"はい（日本的）") -> はい（日本的） | Y22: =IFERROR(__xludf.DUMMYFUNCTION("""COMPUTED_VALUE"""),7.0) -> 7 | Z22: =IFERROR(__xludf.DUMMYFUNCTION("""COMPUTED_VALUE"""),7.0) -> 7 | AA22: =IFERROR(__xludf.DUMMYFUNCTION("""COMPUTED_VALUE"""),2.0) -> 2 | AB22: =IFERROR(__xludf.DUMMYFUNCTION("""COMPUTED_VALUE"""),"いいえ") -> いいえ | AK22: 68EP7gY | AL22: 2ENDrBg | AM22: 46034.462 | AN22: 56-65 | AO22: Male | AP22: ¥6,000,000 – ¥8,999,999 | AQ22: Kanto | AR22: Daily | AS22: Drip | AU22: Rarely | AV22: Matcha Latte | AX22: =IFERROR(__xludf.DUMMYFUNCTION("""COMPUTED_VALUE"""),"Taste/Flavor, Social norms / influence (what people around me usually drink)") -> Taste/Flavor, Social norms / influence (what people around me usually drink) | AZ22: =IFERROR(__xludf.DUMMYFUNCTION("""COMPUTED_VALUE"""),"From convenience stores (7-Eleven, Lawson, etc.), Other:") -> From convenience stores (7-Eleven, Lawson, etc.), Other: | BA22: Office | BB22: A few times a month | BC22: To study/work | BE22: Atmosphere | BG22: Yes, Western | BH22: Yes, Japanese | BI22: 7 | BJ22: 7 | BK22: 2 | BL22: No
A23: =IFERROR(__xludf.DUMMYFUNCTION("""COMPUTED_VALUE"""),"9qjreME") -> 9qjreME | B23: =IFERROR(__xludf.DUMMYFUNCTION("""COMPUTED_VALUE"""),"2EN7klD") -> 2EN7klD | C23: =IFERROR(__xludf.DUMMYFUNCTION("""COMPUTED_VALUE"""),46034.64092592592) -> 46034.641 | D23: =IFERROR(__xludf.DUMMYFUNCTION("""COMPUTED_VALUE"""),"46〜55歳") -> 46〜55歳 | E23: =IFERROR(__xludf.DUMMYFUNCTION("""COMPUTED_VALUE"""),"男性") -> 男性 | F23: =IFERROR(__xludf.DUMMYFUNCTION("""COMPUTED_VALUE"""),"900万円〜1,199万9,999円") -> 900万円〜1,199万9,999円 | G23: =IFERROR(__xludf.DUMMYFUNCTION("""COMPUTED_VALUE"""),"関東") -> 関東 | H23: =IFERROR(__xludf.DUMMYFUNCTION("""COMPUTED_VALUE"""),"毎日") -> 毎日 | I23: =IFERROR(__xludf.DUMMYFUNCTION("""COMPUTED_VALUE"""),"ドリップコーヒー") -> ドリップコーヒー | K23: =IFERROR(__xludf.DUMMYFUNCTION("""COMPUTED_VALUE"""),"ほとんど飲まない") -> ほとんど飲まない | L23: =IFERROR(__xludf.DUMMYFUNCTION("""COMPUTED_VALUE"""),"抹茶ラテ") -> 抹茶ラテ | N23: =IFERROR(__xludf.DUMMYFUNCTION("""COMPUTED_VALUE"""),"味・風味, 価格") -> 味・風味, 価格 | P23: =IFERROR(__xludf.DUMMYFUNCTION("""COMPUTED_VALUE"""),"カフェで, 自宅で, コンビニ（セブンイレブン、ローソンなど）, 自動販売機") -> カフェで, 自宅で, コンビニ（セブンイレブン、ローソンなど）, 自動販売機 | R23: =IFERROR(__xludf.DUMMYFUNCTION("""COMPUTED_VALUE"""),"月に数回") -> 月に数回 | S23: =IFERROR(__xludf.DUMMYFUNCTION("""COMPUTED_VALUE"""),"勉強・仕事をするため") -> 勉強・仕事をするため | U23: =IFERROR(__xludf.DUMMYFUNCTION("""COMPUTED_VALUE"""),"雰囲気・心地良さ") -> 雰囲気・心地良さ | W23: =IFERROR(__xludf.DUMMYFUNCTION("""COMPUTED_VALUE"""),"はい（グローバル）") -> はい（グローバル） | X23: =IFERROR(__xludf.DUMMYFUNCTION("""COMPUTED_VALUE"""),"はい（日本的）") -> はい（日本的） | Y23: =IFERROR(__xludf.DUMMYFUNCTION("""COMPUTED_VALUE"""),7.0) -> 7 | Z23: =IFERROR(__xludf.DUMMYFUNCTION("""COMPUTED_VALUE"""),7.0) -> 7 | AA23: =IFERROR(__xludf.DUMMYFUNCTION("""COMPUTED_VALUE"""),4.0) -> 4 | AB23: =IFERROR(__xludf.DUMMYFUNCTION("""COMPUTED_VALUE"""),"いいえ") -> いいえ | AK23: 9qjreME | AL23: 2EN7klD | AM23: 46034.641 | AN23: 46-55 | AO23: Male | AP23: ¥9,000,000 – ¥11,999,999 | AQ23: Kanto | AR23: Daily | AS23: Drip | AU23: Rarely | AV23: Matcha Latte | AX23: =IFERROR(__xludf.DUMMYFUNCTION("""COMPUTED_VALUE"""),"Taste/Flavor, Price") -> Taste/Flavor, Price | AZ23: =IFERROR(__xludf.DUMMYFUNCTION("""COMPUTED_VALUE"""),"At cafés, At home, From convenience stores (7-Eleven, Lawson, etc.), From vending machines") -> At cafés, At home, From convenience stores (7-Eleven, Lawson, etc.), From vending machines | BB23: A few times a month | BC23: To study/work | BE23: Atmosphere | BG23: Yes, Global | BH23: Yes, Japanese | BI23: 7 | BJ23: 7 | BK23: 4 | BL23: No
A24: =IFERROR(__xludf.DUMMYFUNCTION("""COMPUTED_VALUE"""),"lbkZXPo") -> lbkZXPo | B24: =IFERROR(__xludf.DUMMYFUNCTION("""COMPUTED_VALUE"""),"vGyWA4D") -> vGyWA4D | C24: =IFERROR(__xludf.DUMMYFUNCTION("""COMPUTED_VALUE"""),46035.03644675926) -> 46035.036 | D24: =IFERROR(__xludf.DUMMYFUNCTION("""COMPUTED_VALUE"""),"46〜55歳") -> 46〜55歳 | E24: =IFERROR(__xludf.DUMMYFUNCTION("""COMPUTED_VALUE"""),"男性") -> 男性 | F24: =IFERROR(__xludf.DUMMYFUNCTION("""COMPUTED_VALUE"""),"900万円〜1,199万9,999円") -> 900万円〜1,199万9,999円 | G24: =IFERROR(__xludf.DUMMYFUNCTION("""COMPUTED_VALUE"""),"関東") -> 関東 | H24: =IFERROR(__xludf.DUMMYFUNCTION("""COMPUTED_VALUE"""),"毎日") -> 毎日 | I24: =IFERROR(__xludf.DUMMYFUNCTION("""COMPUTED_VALUE"""),"その他:") -> その他: | J24: =IFERROR(__xludf.DUMMYFUNCTION("""COMPUTED_VALUE"""),"缶コーヒー") -> 缶コーヒー | K24: =IFERROR(__xludf.DUMMYFUNCTION("""COMPUTED_VALUE"""),"ほとんど飲まない") -> ほとんど飲まない | L24: =IFERROR(__xludf.DUMMYFUNCTION("""COMPUTED_VALUE"""),"薄茶") -> 薄茶 | N24: =IFERROR(__xludf.DUMMYFUNCTION("""COMPUTED_VALUE"""),"その他：, 味・風味") -> その他：, 味・風味 | O24: =IFERROR(__xludf.DUMMYFUNCTION("""COMPUTED_VALUE"""),"手に入り易さ") -> 手に入り易さ | P24: =IFERROR(__xludf.DUMMYFUNCTION("""COMPUTED_VALUE"""),"カフェで, 自宅で, コンビニ（セブンイレブン、ローソンなど）, 自動販売機") -> カフェで, 自宅で, コンビニ（セブンイレブン、ローソンなど）, 自動販売機 | R24: =IFERROR(__xludf.DUMMYFUNCTION("""COMPUTED_VALUE"""),"月に数回") -> 月に数回 | S24: =IFERROR(__xludf.DUMMYFUNCTION("""COMPUTED_VALUE"""),"休憩・リラックスするため") -> 休憩・リラックスするため | U24: =IFERROR(__xludf.DUMMYFUNCTION("""COMPUTED_VALUE"""),"雰囲気・心地良さ") -> 雰囲気・心地良さ | W24: =IFERROR(__xludf.DUMMYFUNCTION("""COMPUTED_VALUE"""),"はい（西洋的）") -> はい（西洋的） | X24: =IFERROR(__xludf.DUMMYFUNCTION("""COMPUTED_VALUE"""),"はい（日本的）") -> はい（日本的） | Y24: =IFERROR(__xludf.DUMMYFUNCTION("""COMPUTED_VALUE"""),7.0) -> 7 | Z24: =IFERROR(__xludf.DUMMYFUNCTION("""COMPUTED_VALUE"""),7.0) -> 7 | AA24: =IFERROR(__xludf.DUMMYFUNCTION("""COMPUTED_VALUE"""),4.0) -> 4 | AB24: =IFERROR(__xludf.DUMMYFUNCTION("""COMPUTED_VALUE"""),"はい") -> はい | AK24: lbkZXPo | AL24: vGyWA4D | AM24: 46035.036 | AN24: 46-55 | AO24: Male | AP24: ¥9,000,000 – ¥11,999,999 | AQ24: Kanto | AR24: Daily | AS24: Other: | AT24: Canned Coffee | AU24: Rarely | AV24: Usucha | AX24: =IFERROR(__xludf.DUMMYFUNCTION("""COMPUTED_VALUE"""),"Other:, Taste/Flavor") -> Other:, Taste/Flavor | AY24: Ease of obtaining/availability | AZ24: =IFERROR(__xludf.DUMMYFUNCTION("""COMPUTED_VALUE"""),"At cafés, At home, From convenience stores (7-Eleven, Lawson, etc.), From vending machines") -> At cafés, At home, From convenience stores (7-Eleven, Lawson, etc.), From vending machines | BB24: A few times a month | BC24: To relax or take a break | BE24: Atmosphere | BG24: Yes, Western | BH24: Yes, Japanese | BI24: 7 | BJ24: 7 | BK24: 4 | BL24: Yes
A25: =IFERROR(__xludf.DUMMYFUNCTION("""COMPUTED_VALUE"""),"jaAYBoY") -> jaAYBoY | B25: =IFERROR(__xludf.DUMMYFUNCTION("""COMPUTED_VALUE"""),"lbd4vZp") -> lbd4vZp | C25: =IFERROR(__xludf.DUMMYFUNCTION("""COMPUTED_VALUE"""),46035.11938657407) -> 46035.119 | D25: =IFERROR(__xludf.DUMMYFUNCTION("""COMPUTED_VALUE"""),"18〜25歳") -> 18〜25歳 | E25: =IFERROR(__xludf.DUMMYFUNCTION("""COMPUTED_VALUE"""),"男性") -> 男性 | F25: =IFERROR(__xludf.DUMMYFUNCTION("""COMPUTED_VALUE"""),"300万円〜599万9,999円") -> 300万円〜599万9,999円 | G25: =IFERROR(__xludf.DUMMYFUNCTION("""COMPUTED_VALUE"""),"関西") -> 関西 | H25: =IFERROR(__xludf.DUMMYFUNCTION("""COMPUTED_VALUE"""),"毎日") -> 毎日 | I25: =IFERROR(__xludf.DUMMYFUNCTION("""COMPUTED_VALUE"""),"アメリカーノ") -> アメリカーノ | K25: =IFERROR(__xludf.DUMMYFUNCTION("""COMPUTED_VALUE"""),"ほとんど飲まない") -> ほとんど飲まない | L25: =IFERROR(__xludf.DUMMYFUNCTION("""COMPUTED_VALUE"""),"抹茶は飲まない") -> 抹茶は飲まない | N25: =IFERROR(__xludf.DUMMYFUNCTION("""COMPUTED_VALUE"""),"味・風味, 習慣") -> 味・風味, 習慣 | P25: =IFERROR(__xludf.DUMMYFUNCTION("""COMPUTED_VALUE"""),"カフェで, 自宅で, コンビニ（セブンイレブン、ローソンなど）") -> カフェで, 自宅で, コンビニ（セブンイレブン、ローソンなど） | R25: =IFERROR(__xludf.DUMMYFUNCTION("""COMPUTED_VALUE"""),"週に数回") -> 週に数回 | S25: =IFERROR(__xludf.DUMMYFUNCTION("""COMPUTED_VALUE"""),"習慣として") -> 習慣として | U25: =IFERROR(__xludf.DUMMYFUNCTION("""COMPUTED_VALUE"""),"雰囲気・心地良さ") -> 雰囲気・心地良さ | W25: =IFERROR(__xludf.DUMMYFUNCTION("""COMPUTED_VALUE"""),"はい（グローバル）") -> はい（グローバル） | X25: =IFERROR(__xludf.DUMMYFUNCTION("""COMPUTED_VALUE"""),"はい（日本的）") -> はい（日本的） | Y25: =IFERROR(__xludf.DUMMYFUNCTION("""COMPUTED_VALUE"""),7.0) -> 7 | Z25: =IFERROR(__xludf.DUMMYFUNCTION("""COMPUTED_VALUE"""),5.0) -> 5 | AA25: =IFERROR(__xludf.DUMMYFUNCTION("""COMPUTED_VALUE"""),7.0) -> 7 | AB25: =IFERROR(__xludf.DUMMYFUNCTION("""COMPUTED_VALUE"""),"はい") -> はい | AK25: jaAYBoY | AL25: lbd4vZp | AM25: 46035.119 | AN25: 18-25 | AO25: Male | AP25: ¥3,000,000 – ¥5,999,999 | AQ25: Kansai | AR25: Daily | AS25: Americano | AU25: Rarely | AV25: I don’t drink matcha | AX25: =IFERROR(__xludf.DUMMYFUNCTION("""COMPUTED_VALUE"""),"Taste/Flavor, Routine/Ritual") -> Taste/Flavor, Routine/Ritual | AZ25: =IFERROR(__xludf.DUMMYFUNCTION("""COMPUTED_VALUE"""),"At cafés, At home, From convenience stores (7-Eleven, Lawson, etc.)") -> At cafés, At home, From convenience stores (7-Eleven, Lawson, etc.) | BB25: Several times a week | BC25: Out of habit | BE25: Atmosphere | BG25: Yes, Global | BH25: Yes, Japanese | BI25: 7 | BJ25: 5 | BK25: 7 | BL25: Yes
A26: =IFERROR(__xludf.DUMMYFUNCTION("""COMPUTED_VALUE"""),"b5QyLD7") -> b5QyLD7 | B26: =IFERROR(__xludf.DUMMYFUNCTION("""COMPUTED_VALUE"""),"9qDrrr5") -> 9qDrrr5 | C26: =IFERROR(__xludf.DUMMYFUNCTION("""COMPUTED_VALUE"""),46035.13155092593) -> 46035.132 | D26: =IFERROR(__xludf.DUMMYFUNCTION("""COMPUTED_VALUE"""),"65歳以上") -> 65歳以上 | E26: =IFERROR(__xludf.DUMMYFUNCTION("""COMPUTED_VALUE"""),"男性") -> 男性 | F26: =IFERROR(__xludf.DUMMYFUNCTION("""COMPUTED_VALUE"""),"300万円〜599万9,999円") -> 300万円〜599万9,999円 | G26: =IFERROR(__xludf.DUMMYFUNCTION("""COMPUTED_VALUE"""),"関西") -> 関西 | H26: =IFERROR(__xludf.DUMMYFUNCTION("""COMPUTED_VALUE"""),"ほとんど飲まない") -> ほとんど飲まない | I26: =IFERROR(__xludf.DUMMYFUNCTION("""COMPUTED_VALUE"""),"ラテ") -> ラテ | K26: =IFERROR(__xludf.DUMMYFUNCTION("""COMPUTED_VALUE"""),"ほとんど飲まない") -> ほとんど飲まない | L26: =IFERROR(__xludf.DUMMYFUNCTION("""COMPUTED_VALUE"""),"抹茶は飲まない") -> 抹茶は飲まない | N26: =IFERROR(__xludf.DUMMYFUNCTION("""COMPUTED_VALUE"""),"習慣") -> 習慣 | R26: =IFERROR(__xludf.DUMMYFUNCTION("""COMPUTED_VALUE"""),"ほとんど行かない") -> ほとんど行かない | S26: =IFERROR(__xludf.DUMMYFUNCTION("""COMPUTED_VALUE"""),"友人と会うため") -> 友人と会うため | U26: =IFERROR(__xludf.DUMMYFUNCTION("""COMPUTED_VALUE"""),"飲み物の味・品質") -> 飲み物の味・品質 | W26: =IFERROR(__xludf.DUMMYFUNCTION("""COMPUTED_VALUE"""),"いいえ") -> いいえ | X26: =IFERROR(__xludf.DUMMYFUNCTION("""COMPUTED_VALUE"""),"はい（日本的）") -> はい（日本的） | Y26: =IFERROR(__xludf.DUMMYFUNCTION("""COMPUTED_VALUE"""),7.0) -> 7 | Z26: =IFERROR(__xludf.DUMMYFUNCTION("""COMPUTED_VALUE"""),7.0) -> 7 | AA26: =IFERROR(__xludf.DUMMYFUNCTION("""COMPUTED_VALUE"""),7.0) -> 7 | AB26: =IFERROR(__xludf.DUMMYFUNCTION("""COMPUTED_VALUE"""),"はい") -> はい | AK26: b5QyLD7 | AL26: 9qDrrr5 | AM26: 46035.132 | AN26: 65+ | AO26: Male | AP26: ¥3,000,000 – ¥5,999,999 | AQ26: Kansai | AR26: Rarely | AS26: Latte | AU26: Rarely | AV26: I don’t drink matcha | AX26: =IFERROR(__xludf.DUMMYFUNCTION("""COMPUTED_VALUE"""),"Routine/Ritual") -> Routine/Ritual | AZ26: =IFERROR(__xludf.DUMMYFUNCTION("""COMPUTED_VALUE"""),"") | BB26: Rarely | BC26: To meet friends | BE26: Quality of drinks | BG26: No | BH26: Yes, Japanese | BI26: 7 | BJ26: 7 | BK26: 7 | BL26: Yes
A27: =IFERROR(__xludf.DUMMYFUNCTION("""COMPUTED_VALUE"""),"b5QyGKL") -> b5QyGKL | B27: =IFERROR(__xludf.DUMMYFUNCTION("""COMPUTED_VALUE"""),"zxDbBE0") -> zxDbBE0 | C27: =IFERROR(__xludf.DUMMYFUNCTION("""COMPUTED_VALUE"""),46035.18347222222) -> 46035.183 | D27: =IFERROR(__xludf.DUMMYFUNCTION("""COMPUTED_VALUE"""),"46〜55歳") -> 46〜55歳 | E27: =IFERROR(__xludf.DUMMYFUNCTION("""COMPUTED_VALUE"""),"回答しない") -> 回答しない | F27: =IFERROR(__xludf.DUMMYFUNCTION("""COMPUTED_VALUE"""),"回答しない") -> 回答しない | G27: =IFERROR(__xludf.DUMMYFUNCTION("""COMPUTED_VALUE"""),"関東") -> 関東 | H27: =IFERROR(__xludf.DUMMYFUNCTION("""COMPUTED_VALUE"""),"毎日") -> 毎日 | I27: =IFERROR(__xludf.DUMMYFUNCTION("""COMPUTED_VALUE"""),"ドリップコーヒー") -> ドリップコーヒー | K27: =IFERROR(__xludf.DUMMYFUNCTION("""COMPUTED_VALUE"""),"ほとんど飲まない") -> ほとんど飲まない | L27: =IFERROR(__xludf.DUMMYFUNCTION("""COMPUTED_VALUE"""),"抹茶は飲まない") -> 抹茶は飲まない | N27: =IFERROR(__xludf.DUMMYFUNCTION("""COMPUTED_VALUE"""),"味・風味, 習慣") -> 味・風味, 習慣 | P27: =IFERROR(__xludf.DUMMYFUNCTION("""COMPUTED_VALUE"""),"自宅で") -> 自宅で | R27: =IFERROR(__xludf.DUMMYFUNCTION("""COMPUTED_VALUE"""),"月に数回") -> 月に数回 | S27: =IFERROR(__xludf.DUMMYFUNCTION("""COMPUTED_VALUE"""),"休憩・リラックスするため") -> 休憩・リラックスするため | U27: =IFERROR(__xludf.DUMMYFUNCTION("""COMPUTED_VALUE"""),"雰囲気・心地良さ") -> 雰囲気・心地良さ | W27: =IFERROR(__xludf.DUMMYFUNCTION("""COMPUTED_VALUE"""),"はい（西洋的）") -> はい（西洋的） | X27: =IFERROR(__xludf.DUMMYFUNCTION("""COMPUTED_VALUE"""),"はい（日本的）") -> はい（日本的） | Y27: =IFERROR(__xludf.DUMMYFUNCTION("""COMPUTED_VALUE"""),4.0) -> 4 | Z27: =IFERROR(__xludf.DUMMYFUNCTION("""COMPUTED_VALUE"""),6.0) -> 6 | AA27: =IFERROR(__xludf.DUMMYFUNCTION("""COMPUTED_VALUE"""),3.0) -> 3 | AB27: =IFERROR(__xludf.DUMMYFUNCTION("""COMPUTED_VALUE"""),"いいえ") -> いいえ | AK27: b5QyGKL | AL27: zxDbBE0 | AM27: 46035.183 | AN27: 46-55 | AO27: Prefer not to say | AP27: Prefer not to say | AQ27: Kanto | AR27: Daily | AS27: Drip | AU27: Rarely | AV27: I don’t drink matcha | AX27: =IFERROR(__xludf.DUMMYFUNCTION("""COMPUTED_VALUE"""),"Taste/Flavor, Routine/Ritual") -> Taste/Flavor, Routine/Ritual | AZ27: =IFERROR(__xludf.DUMMYFUNCTION("""COMPUTED_VALUE"""),"At home") -> At home | BB27: A few times a month | BC27: To relax or take a break | BE27: Atmosphere | BG27: Yes, Western | BH27: Yes, Japanese | BI27: 4 | BJ27: 6 | BK27: 3 | BL27: No
A28: =IFERROR(__xludf.DUMMYFUNCTION("""COMPUTED_VALUE"""),"RGy19Xj") -> RGy19Xj | B28: =IFERROR(__xludf.DUMMYFUNCTION("""COMPUTED_VALUE"""),"GxdkPlk") -> GxdkPlk | C28: =IFERROR(__xludf.DUMMYFUNCTION("""COMPUTED_VALUE"""),46035.467453703706) -> 46035.467 | D28: =IFERROR(__xludf.DUMMYFUNCTION("""COMPUTED_VALUE"""),"18〜25歳") -> 18〜25歳 | E28: =IFERROR(__xludf.DUMMYFUNCTION("""COMPUTED_VALUE"""),"女性") -> 女性 | F28: =IFERROR(__xludf.DUMMYFUNCTION("""COMPUTED_VALUE"""),"300万円〜599万9,999円") -> 300万円〜599万9,999円 | G28: =IFERROR(__xludf.DUMMYFUNCTION("""COMPUTED_VALUE"""),"関西") -> 関西 | H28: =IFERROR(__xludf.DUMMYFUNCTION("""COMPUTED_VALUE"""),"週に数回") -> 週に数回 | I28: =IFERROR(__xludf.DUMMYFUNCTION("""COMPUTED_VALUE"""),"ドリップコーヒー") -> ドリップコーヒー | K28: =IFERROR(__xludf.DUMMYFUNCTION("""COMPUTED_VALUE"""),"ほとんど飲まない") -> ほとんど飲まない | L28: =IFERROR(__xludf.DUMMYFUNCTION("""COMPUTED_VALUE"""),"抹茶ラテ") -> 抹茶ラテ | N28: =IFERROR(__xludf.DUMMYFUNCTION("""COMPUTED_VALUE"""),"味・風味, ブランド・イメージ") -> 味・風味, ブランド・イメージ | P28: =IFERROR(__xludf.DUMMYFUNCTION("""COMPUTED_VALUE"""),"カフェで") -> カフェで | R28: =IFERROR(__xludf.DUMMYFUNCTION("""COMPUTED_VALUE"""),"週に1回") -> 週に1回 | S28: =IFERROR(__xludf.DUMMYFUNCTION("""COMPUTED_VALUE"""),"休憩・リラックスするため") -> 休憩・リラックスするため | U28: =IFERROR(__xludf.DUMMYFUNCTION("""COMPUTED_VALUE"""),"雰囲気・心地良さ") -> 雰囲気・心地良さ | W28: =IFERROR(__xludf.DUMMYFUNCTION("""COMPUTED_VALUE"""),"はい（グローバル）") -> はい（グローバル） | X28: =IFERROR(__xludf.DUMMYFUNCTION("""COMPUTED_VALUE"""),"はい（日本的）") -> はい（日本的） | Y28: =IFERROR(__xludf.DUMMYFUNCTION("""COMPUTED_VALUE"""),5.0) -> 5 | Z28: =IFERROR(__xludf.DUMMYFUNCTION("""COMPUTED_VALUE"""),4.0) -> 4 | AA28: =IFERROR(__xludf.DUMMYFUNCTION("""COMPUTED_VALUE"""),2.0) -> 2 | AB28: =IFERROR(__xludf.DUMMYFUNCTION("""COMPUTED_VALUE"""),"はい") -> はい | AK28: RGy19Xj | AL28: GxdkPlk | AM28: 46035.467 | AN28: 18-25 | AO28: Female | AP28: ¥3,000,000 – ¥5,999,999 | AQ28: Kansai | AR28: Several times a week | AS28: Drip | AU28: Rarely | AV28: Matcha Latte | AX28: =IFERROR(__xludf.DUMMYFUNCTION("""COMPUTED_VALUE"""),"Taste/Flavor, Branding/Imagery") -> Taste/Flavor, Branding/Imagery | AZ28: =IFERROR(__xludf.DUMMYFUNCTION("""COMPUTED_VALUE"""),"At cafés") -> At cafés | BB28: Once a week | BC28: To relax or take a break | BE28: Atmosphere | BG28: Yes, Global | BH28: Yes, Japanese | BI28: 5 | BJ28: 4 | BK28: 2 | BL28: Yes
A29: =IFERROR(__xludf.DUMMYFUNCTION("""COMPUTED_VALUE"""),"QKlQZjp") -> QKlQZjp | B29: =IFERROR(__xludf.DUMMYFUNCTION("""COMPUTED_VALUE"""),"q4A7ZJg") -> q4A7ZJg | C29: =IFERROR(__xludf.DUMMYFUNCTION("""COMPUTED_VALUE"""),46036.10293981482) -> 46036.103 | D29: =IFERROR(__xludf.DUMMYFUNCTION("""COMPUTED_VALUE"""),"65歳以上") -> 65歳以上 | E29: =IFERROR(__xludf.DUMMYFUNCTION("""COMPUTED_VALUE"""),"男性") -> 男性 | F29: =IFERROR(__xludf.DUMMYFUNCTION("""COMPUTED_VALUE"""),"回答しない") -> 回答しない | G29: =IFERROR(__xludf.DUMMYFUNCTION("""COMPUTED_VALUE"""),"関東") -> 関東 | H29: =IFERROR(__xludf.DUMMYFUNCTION("""COMPUTED_VALUE"""),"毎日") -> 毎日 | I29: =IFERROR(__xludf.DUMMYFUNCTION("""COMPUTED_VALUE"""),"その他:") -> その他: | K29: =IFERROR(__xludf.DUMMYFUNCTION("""COMPUTED_VALUE"""),"ほとんど飲まない") -> ほとんど飲まない | L29: =IFERROR(__xludf.DUMMYFUNCTION("""COMPUTED_VALUE"""),"抹茶は飲まない") -> 抹茶は飲まない | N29: =IFERROR(__xludf.DUMMYFUNCTION("""COMPUTED_VALUE"""),"味・風味, 社交的な場や雰囲気の考慮") -> 味・風味, 社交的な場や雰囲気の考慮 | P29: =IFERROR(__xludf.DUMMYFUNCTION("""COMPUTED_VALUE"""),"自宅で") -> 自宅で | R29: =IFERROR(__xludf.DUMMYFUNCTION("""COMPUTED_VALUE"""),"月に数回") -> 月に数回 | S29: =IFERROR(__xludf.DUMMYFUNCTION("""COMPUTED_VALUE"""),"友人と会うため") -> 友人と会うため | U29: =IFERROR(__xludf.DUMMYFUNCTION("""COMPUTED_VALUE"""),"雰囲気・心地良さ") -> 雰囲気・心地良さ | W29: =IFERROR(__xludf.DUMMYFUNCTION("""COMPUTED_VALUE"""),"わからない") -> わからない | X29: =IFERROR(__xludf.DUMMYFUNCTION("""COMPUTED_VALUE"""),"わからない") -> わからない | Y29: =IFERROR(__xludf.DUMMYFUNCTION("""COMPUTED_VALUE"""),7.0) -> 7 | Z29: =IFERROR(__xludf.DUMMYFUNCTION("""COMPUTED_VALUE"""),7.0) -> 7 | AA29: =IFERROR(__xludf.DUMMYFUNCTION("""COMPUTED_VALUE"""),7.0) -> 7 | AB29: =IFERROR(__xludf.DUMMYFUNCTION("""COMPUTED_VALUE"""),"いいえ") -> いいえ | AK29: QKlQZjp | AL29: q4A7ZJg | AM29: 46036.103 | AN29: 65+ | AO29: Male | AP29: Prefer not to say | AQ29: Kanto | AR29: Daily | AS29: Other: | AU29: Rarely | AV29: I don’t drink matcha | AX29: =IFERROR(__xludf.DUMMYFUNCTION("""COMPUTED_VALUE"""),"Taste/Flavor, Social atmosphere") -> Taste/Flavor, Social atmosphere | AZ29: =IFERROR(__xludf.DUMMYFUNCTION("""COMPUTED_VALUE"""),"At home") -> At home | BB29: A few times a month | BC29: To meet friends | BE29: Atmosphere | BG29: Unsure | BH29: Unsure | BI29: 7 | BJ29: 7 | BK29: 7 | BL29: No
A30: =IFERROR(__xludf.DUMMYFUNCTION("""COMPUTED_VALUE"""),"PdJxOqV") -> PdJxOqV | B30: =IFERROR(__xludf.DUMMYFUNCTION("""COMPUTED_VALUE"""),"RG56DO4") -> RG56DO4 | C30: =IFERROR(__xludf.DUMMYFUNCTION("""COMPUTED_VALUE"""),46036.150034722225) -> 46036.15 | D30: =IFERROR(__xludf.DUMMYFUNCTION("""COMPUTED_VALUE"""),"18〜25歳") -> 18〜25歳 | E30: =IFERROR(__xludf.DUMMYFUNCTION("""COMPUTED_VALUE"""),"女性") -> 女性 | F30: =IFERROR(__xludf.DUMMYFUNCTION("""COMPUTED_VALUE"""),"回答しない") -> 回答しない | G30: =IFERROR(__xludf.DUMMYFUNCTION("""COMPUTED_VALUE"""),"関西") -> 関西 | H30: =IFERROR(__xludf.DUMMYFUNCTION("""COMPUTED_VALUE"""),"週に数回") -> 週に数回 | I30: =IFERROR(__xludf.DUMMYFUNCTION("""COMPUTED_VALUE"""),"ドリップコーヒー") -> ドリップコーヒー | K30: =IFERROR(__xludf.DUMMYFUNCTION("""COMPUTED_VALUE"""),"週に数回") -> 週に数回 | L30: =IFERROR(__xludf.DUMMYFUNCTION("""COMPUTED_VALUE"""),"薄茶") -> 薄茶 | N30: =IFERROR(__xludf.DUMMYFUNCTION("""COMPUTED_VALUE"""),"味・風味, 習慣") -> 味・風味, 習慣 | R30: =IFERROR(__xludf.DUMMYFUNCTION("""COMPUTED_VALUE"""),"月に数回") -> 月に数回 | S30: =IFERROR(__xludf.DUMMYFUNCTION("""COMPUTED_VALUE"""),"休憩・リラックスするため") -> 休憩・リラックスするため | U30: =IFERROR(__xludf.DUMMYFUNCTION("""COMPUTED_VALUE"""),"雰囲気・心地良さ") -> 雰囲気・心地良さ | W30: =IFERROR(__xludf.DUMMYFUNCTION("""COMPUTED_VALUE"""),"はい（グローバル）") -> はい（グローバル） | X30: =IFERROR(__xludf.DUMMYFUNCTION("""COMPUTED_VALUE"""),"はい（日本的）") -> はい（日本的） | Y30: =IFERROR(__xludf.DUMMYFUNCTION("""COMPUTED_VALUE"""),7.0) -> 7 | Z30: =IFERROR(__xludf.DUMMYFUNCTION("""COMPUTED_VALUE"""),7.0) -> 7 | AA30: =IFERROR(__xludf.DUMMYFUNCTION("""COMPUTED_VALUE"""),5.0) -> 5 | AB30: =IFERROR(__xludf.DUMMYFUNCTION("""COMPUTED_VALUE"""),"いいえ") -> いいえ | AK30: PdJxOqV | AL30: RG56DO4 | AM30: 46036.15 | AN30: 18-25 | AO30: Female | AP30: Prefer not to say | AQ30: Kansai | AR30: Several times a week | AS30: Drip | AU30: Several times a week | AV30: Usucha | AX30: =IFERROR(__xludf.DUMMYFUNCTION("""COMPUTED_VALUE"""),"Taste/Flavor, Routine/Ritual") -> Taste/Flavor, Routine/Ritual | AZ30: =IFERROR(__xludf.DUMMYFUNCTION("""COMPUTED_VALUE"""),"") | BB30: A few times a month | BC30: To relax or take a break | BE30: Atmosphere | BG30: Yes, Global | BH30: Yes, Japanese | BI30: 7 | BJ30: 7 | BK30: 5 | BL30: No
A31: =IFERROR(__xludf.DUMMYFUNCTION("""COMPUTED_VALUE"""),"Np1jb7p") -> Np1jb7p | B31: =IFERROR(__xludf.DUMMYFUNCTION("""COMPUTED_VALUE"""),"81QgeBY") -> 81QgeBY | C31: =IFERROR(__xludf.DUMMYFUNCTION("""COMPUTED_VALUE"""),46036.19474537037) -> 46036.195 | D31: =IFERROR(__xludf.DUMMYFUNCTION("""COMPUTED_VALUE"""),"36〜45歳") -> 36〜45歳 | E31: =IFERROR(__xludf.DUMMYFUNCTION("""COMPUTED_VALUE"""),"女性") -> 女性 | F31: =IFERROR(__xludf.DUMMYFUNCTION("""COMPUTED_VALUE"""),"300万円〜599万9,999円") -> 300万円〜599万9,999円 | G31: =IFERROR(__xludf.DUMMYFUNCTION("""COMPUTED_VALUE"""),"関西") -> 関西 | H31: =IFERROR(__xludf.DUMMYFUNCTION("""COMPUTED_VALUE"""),"毎日") -> 毎日 | I31: =IFERROR(__xludf.DUMMYFUNCTION("""COMPUTED_VALUE"""),"ドリップコーヒー") -> ドリップコーヒー | K31: =IFERROR(__xludf.DUMMYFUNCTION("""COMPUTED_VALUE"""),"ほとんど飲まない") -> ほとんど飲まない | L31: =IFERROR(__xludf.DUMMYFUNCTION("""COMPUTED_VALUE"""),"抹茶は飲まない") -> 抹茶は飲まない | N31: =IFERROR(__xludf.DUMMYFUNCTION("""COMPUTED_VALUE"""),"味・風味") -> 味・風味 | P31: =IFERROR(__xludf.DUMMYFUNCTION("""COMPUTED_VALUE"""),"自宅で") -> 自宅で | R31: =IFERROR(__xludf.DUMMYFUNCTION("""COMPUTED_VALUE"""),"毎日") -> 毎日 | S31: =IFERROR(__xludf.DUMMYFUNCTION("""COMPUTED_VALUE"""),"休憩・リラックスするため") -> 休憩・リラックスするため | U31: =IFERROR(__xludf.DUMMYFUNCTION("""COMPUTED_VALUE"""),"雰囲気・心地良さ") -> 雰囲気・心地良さ | W31: =IFERROR(__xludf.DUMMYFUNCTION("""COMPUTED_VALUE"""),"はい（グローバル）") -> はい（グローバル） | X31: =IFERROR(__xludf.DUMMYFUNCTION("""COMPUTED_VALUE"""),"はい（日本的）") -> はい（日本的） | Y31: =IFERROR(__xludf.DUMMYFUNCTION("""COMPUTED_VALUE"""),7.0) -> 7 | Z31: =IFERROR(__xludf.DUMMYFUNCTION("""COMPUTED_VALUE"""),1.0) -> 1 | AA31: =IFERROR(__xludf.DUMMYFUNCTION("""COMPUTED_VALUE"""),5.0) -> 5 | AB31: =IFERROR(__xludf.DUMMYFUNCTION("""COMPUTED_VALUE"""),"いいえ") -> いいえ | AK31: Np1jb7p | AL31: 81QgeBY | AM31: 46036.195 | AN31: 36-45 | AO31: Female | AP31: ¥3,000,000 – ¥5,999,999 | AQ31: Kansai | AR31: Daily | AS31: Drip | AU31: Rarely | AV31: I don’t drink matcha | AX31: =IFERROR(__xludf.DUMMYFUNCTION("""COMPUTED_VALUE"""),"Taste/Flavor") -> Taste/Flavor | AZ31: =IFERROR(__xludf.DUMMYFUNCTION("""COMPUTED_VALUE"""),"At home") -> At home | BB31: Daily | BC31: To relax or take a break | BE31: Atmosphere | BG31: Yes, Global | BH31: Yes, Japanese | BI31: 7 | BJ31: 1 | BK31: 5 | BL31: No
A32: =IFERROR(__xludf.DUMMYFUNCTION("""COMPUTED_VALUE"""),"pb2DOGb") -> pb2DOGb | B32: =IFERROR(__xludf.DUMMYFUNCTION("""COMPUTED_VALUE"""),"XxWp9kV") -> XxWp9kV | C32: =IFERROR(__xludf.DUMMYFUNCTION("""COMPUTED_VALUE"""),46038.00806712963) -> 46038.008 | D32: =IFERROR(__xludf.DUMMYFUNCTION("""COMPUTED_VALUE"""),"46〜55歳") -> 46〜55歳 | E32: =IFERROR(__xludf.DUMMYFUNCTION("""COMPUTED_VALUE"""),"女性") -> 女性 | F32: =IFERROR(__xludf.DUMMYFUNCTION("""COMPUTED_VALUE"""),"300万円〜599万9,999円") -> 300万円〜599万9,999円 | G32: =IFERROR(__xludf.DUMMYFUNCTION("""COMPUTED_VALUE"""),"関西") -> 関西 | H32: =IFERROR(__xludf.DUMMYFUNCTION("""COMPUTED_VALUE"""),"週に数回") -> 週に数回 | I32: =IFERROR(__xludf.DUMMYFUNCTION("""COMPUTED_VALUE"""),"ラテ") -> ラテ | K32: =IFERROR(__xludf.DUMMYFUNCTION("""COMPUTED_VALUE"""),"ほとんど飲まない") -> ほとんど飲まない | L32: =IFERROR(__xludf.DUMMYFUNCTION("""COMPUTED_VALUE"""),"抹茶ラテ") -> 抹茶ラテ | N32: =IFERROR(__xludf.DUMMYFUNCTION("""COMPUTED_VALUE"""),"習慣, 味・風味") -> 習慣, 味・風味 | P32: =IFERROR(__xludf.DUMMYFUNCTION("""COMPUTED_VALUE"""),"自宅で, カフェで") -> 自宅で, カフェで | R32: =IFERROR(__xludf.DUMMYFUNCTION("""COMPUTED_VALUE"""),"月に数回") -> 月に数回 | S32: =IFERROR(__xludf.DUMMYFUNCTION("""COMPUTED_VALUE"""),"友人と会うため") -> 友人と会うため | U32: =IFERROR(__xludf.DUMMYFUNCTION("""COMPUTED_VALUE"""),"飲み物の味・品質") -> 飲み物の味・品質 | W32: =IFERROR(__xludf.DUMMYFUNCTION("""COMPUTED_VALUE"""),"いいえ") -> いいえ | X32: =IFERROR(__xludf.DUMMYFUNCTION("""COMPUTED_VALUE"""),"はい（日本的）") -> はい（日本的） | Y32: =IFERROR(__xludf.DUMMYFUNCTION("""COMPUTED_VALUE"""),7.0) -> 7 | Z32: =IFERROR(__xludf.DUMMYFUNCTION("""COMPUTED_VALUE"""),7.0) -> 7 | AA32: =IFERROR(__xludf.DUMMYFUNCTION("""COMPUTED_VALUE"""),5.0) -> 5 | AB32: =IFERROR(__xludf.DUMMYFUNCTION("""COMPUTED_VALUE"""),"いいえ") -> いいえ | AK32: pb2DOGb | AL32: XxWp9kV | AM32: 46038.008 | AN32: 46-55 | AO32: Female | AP32: ¥3,000,000 – ¥5,999,999 | AQ32: Kansai | AR32: Several times a week | AS32: Latte | AU32: Rarely | AV32: Matcha Latte | AX32: =IFERROR(__xludf.DUMMYFUNCTION("""COMPUTED_VALUE"""),"Routine/Ritual, Taste/Flavor") -> Routine/Ritual, Taste/Flavor | AZ32: =IFERROR(__xludf.DUMMYFUNCTION("""COMPUTED_VALUE"""),"At home, At cafés") -> At home, At cafés | BB32: A few times a month | BC32: To meet friends | BE32: Quality of drinks | BG32: No | BH32: Yes, Japanese | BI32: 7 | BJ32: 7 | BK32: 5 | BL32: No
A33: =IFERROR(__xludf.DUMMYFUNCTION("""COMPUTED_VALUE"""),"EkOLgBr") -> EkOLgBr | B33: =IFERROR(__xludf.DUMMYFUNCTION("""COMPUTED_VALUE"""),"J9ANZQz") -> J9ANZQz | C33: =IFERROR(__xludf.DUMMYFUNCTION("""COMPUTED_VALUE"""),46039.07131944445) -> 46039.071 | D33: =IFERROR(__xludf.DUMMYFUNCTION("""COMPUTED_VALUE"""),"26〜35歳") -> 26〜35歳 | E33: =IFERROR(__xludf.DUMMYFUNCTION("""COMPUTED_VALUE"""),"女性") -> 女性 | F33: =IFERROR(__xludf.DUMMYFUNCTION("""COMPUTED_VALUE"""),"300万円未満") -> 300万円未満 | G33: =IFERROR(__xludf.DUMMYFUNCTION("""COMPUTED_VALUE"""),"関西") -> 関西 | H33: =IFERROR(__xludf.DUMMYFUNCTION("""COMPUTED_VALUE"""),"毎日") -> 毎日 | I33: =IFERROR(__xludf.DUMMYFUNCTION("""COMPUTED_VALUE"""),"プアオーバー（ハンドドリップ）") -> プアオーバー（ハンドドリップ） | K33: =IFERROR(__xludf.DUMMYFUNCTION("""COMPUTED_VALUE"""),"まったく飲まない") -> まったく飲まない | N33: =IFERROR(__xludf.DUMMYFUNCTION("""COMPUTED_VALUE"""),"味・風味") -> 味・風味 | P33: =IFERROR(__xludf.DUMMYFUNCTION("""COMPUTED_VALUE"""),"カフェで") -> カフェで | R33: =IFERROR(__xludf.DUMMYFUNCTION("""COMPUTED_VALUE"""),"週に数回") -> 週に数回 | S33: =IFERROR(__xludf.DUMMYFUNCTION("""COMPUTED_VALUE"""),"習慣として") -> 習慣として | U33: =IFERROR(__xludf.DUMMYFUNCTION("""COMPUTED_VALUE"""),"雰囲気・心地良さ") -> 雰囲気・心地良さ | W33: =IFERROR(__xludf.DUMMYFUNCTION("""COMPUTED_VALUE"""),"はい（グローバル）") -> はい（グローバル） | X33: =IFERROR(__xludf.DUMMYFUNCTION("""COMPUTED_VALUE"""),"はい（日本的）") -> はい（日本的） | Y33: =IFERROR(__xludf.DUMMYFUNCTION("""COMPUTED_VALUE"""),5.0) -> 5 | Z33: =IFERROR(__xludf.DUMMYFUNCTION("""COMPUTED_VALUE"""),4.0) -> 4 | AA33: =IFERROR(__xludf.DUMMYFUNCTION("""COMPUTED_VALUE"""),4.0) -> 4 | AB33: =IFERROR(__xludf.DUMMYFUNCTION("""COMPUTED_VALUE"""),"いいえ") -> いいえ | AK33: EkOLgBr | AL33: J9ANZQz | AM33: 46039.071 | AN33: 26-35 | AO33: Female | AP33: Under ¥3,000,000 | AQ33: Kansai | AR33: Daily | AS33: Pour Over | AU33: Never | AX33: =IFERROR(__xludf.DUMMYFUNCTION("""COMPUTED_VALUE"""),"Taste/Flavor") -> Taste/Flavor | AZ33: =IFERROR(__xludf.DUMMYFUNCTION("""COMPUTED_VALUE"""),"At cafés") -> At cafés | BB33: Several times a week | BC33: Out of habit | BE33: Atmosphere | BG33: Yes, Global | BH33: Yes, Japanese | BI33: 5 | BJ33: 4 | BK33: 4 | BL33: No
A34: =IFERROR(__xludf.DUMMYFUNCTION("""COMPUTED_VALUE"""),"Y5AYV0N") -> Y5AYV0N | B34: =IFERROR(__xludf.DUMMYFUNCTION("""COMPUTED_VALUE"""),"44xWaRo") -> 44xWaRo | C34: =IFERROR(__xludf.DUMMYFUNCTION("""COMPUTED_VALUE"""),46039.22078703704) -> 46039.221 | D34: =IFERROR(__xludf.DUMMYFUNCTION("""COMPUTED_VALUE"""),"56〜65歳") -> 56〜65歳 | E34: =IFERROR(__xludf.DUMMYFUNCTION("""COMPUTED_VALUE"""),"男性") -> 男性 | F34: =IFERROR(__xludf.DUMMYFUNCTION("""COMPUTED_VALUE"""),"900万円〜1,199万9,999円") -> 900万円〜1,199万9,999円 | G34: =IFERROR(__xludf.DUMMYFUNCTION("""COMPUTED_VALUE"""),"北海道") -> 北海道 | H34: =IFERROR(__xludf.DUMMYFUNCTION("""COMPUTED_VALUE"""),"毎日") -> 毎日 | I34: =IFERROR(__xludf.DUMMYFUNCTION("""COMPUTED_VALUE"""),"ドリップコーヒー") -> ドリップコーヒー | K34: =IFERROR(__xludf.DUMMYFUNCTION("""COMPUTED_VALUE"""),"毎日") -> 毎日 | L34: =IFERROR(__xludf.DUMMYFUNCTION("""COMPUTED_VALUE"""),"薄茶") -> 薄茶 | N34: =IFERROR(__xludf.DUMMYFUNCTION("""COMPUTED_VALUE"""),"社交的な場や雰囲気の考慮") -> 社交的な場や雰囲気の考慮 | P34: =IFERROR(__xludf.DUMMYFUNCTION("""COMPUTED_VALUE"""),"カフェで") -> カフェで | R34: =IFERROR(__xludf.DUMMYFUNCTION("""COMPUTED_VALUE"""),"毎日") -> 毎日 | S34: =IFERROR(__xludf.DUMMYFUNCTION("""COMPUTED_VALUE"""),"休憩・リラックスするため") -> 休憩・リラックスするため | U34: =IFERROR(__xludf.DUMMYFUNCTION("""COMPUTED_VALUE"""),"雰囲気・心地良さ") -> 雰囲気・心地良さ | W34: =IFERROR(__xludf.DUMMYFUNCTION("""COMPUTED_VALUE"""),"はい（西洋的）") -> はい（西洋的） | X34: =IFERROR(__xludf.DUMMYFUNCTION("""COMPUTED_VALUE"""),"はい（日本的）") -> はい（日本的） | Y34: =IFERROR(__xludf.DUMMYFUNCTION("""COMPUTED_VALUE"""),7.0) -> 7 | Z34: =IFERROR(__xludf.DUMMYFUNCTION("""COMPUTED_VALUE"""),7.0) -> 7 | AA34: =IFERROR(__xludf.DUMMYFUNCTION("""COMPUTED_VALUE"""),7.0) -> 7 | AB34: =IFERROR(__xludf.DUMMYFUNCTION("""COMPUTED_VALUE"""),"いいえ") -> いいえ | AK34: Y5AYV0N | AL34: 44xWaRo | AM34: 46039.221 | AN34: 56-65 | AO34: Male | AP34: ¥9,000,000 – ¥11,999,999 | AQ34: Hokkaido | AR34: Daily | AS34: Drip | AU34: Daily | AV34: Usucha | AX34: =IFERROR(__xludf.DUMMYFUNCTION("""COMPUTED_VALUE"""),"Social atmosphere") -> Social atmosphere | AZ34: =IFERROR(__xludf.DUMMYFUNCTION("""COMPUTED_VALUE"""),"At cafés") -> At cafés | BB34: Daily | BC34: To relax or take a break | BE34: Atmosphere | BG34: Yes, Western | BH34: Yes, Japanese | BI34: 7 | BJ34: 7 | BK34: 7 | BL34: No
A35: =IFERROR(__xludf.DUMMYFUNCTION("""COMPUTED_VALUE"""),"yPaokO6") -> yPaokO6 | B35: =IFERROR(__xludf.DUMMYFUNCTION("""COMPUTED_VALUE"""),"Meb1MBp") -> Meb1MBp | C35: =IFERROR(__xludf.DUMMYFUNCTION("""COMPUTED_VALUE"""),46040.28325231482) -> 46040.283 | D35: =IFERROR(__xludf.DUMMYFUNCTION("""COMPUTED_VALUE"""),"36〜45歳") -> 36〜45歳 | E35: =IFERROR(__xludf.DUMMYFUNCTION("""COMPUTED_VALUE"""),"男性") -> 男性 | F35: =IFERROR(__xludf.DUMMYFUNCTION("""COMPUTED_VALUE"""),"300万円〜599万9,999円") -> 300万円〜599万9,999円 | G35: =IFERROR(__xludf.DUMMYFUNCTION("""COMPUTED_VALUE"""),"北海道") -> 北海道 | H35: =IFERROR(__xludf.DUMMYFUNCTION("""COMPUTED_VALUE"""),"毎日") -> 毎日 | I35: =IFERROR(__xludf.DUMMYFUNCTION("""COMPUTED_VALUE"""),"プアオーバー（ハンドドリップ）") -> プアオーバー（ハンドドリップ） | K35: =IFERROR(__xludf.DUMMYFUNCTION("""COMPUTED_VALUE"""),"ほとんど飲まない") -> ほとんど飲まない | L35: =IFERROR(__xludf.DUMMYFUNCTION("""COMPUTED_VALUE"""),"抹茶ラテ") -> 抹茶ラテ | N35: =IFERROR(__xludf.DUMMYFUNCTION("""COMPUTED_VALUE"""),"味・風味, 価格") -> 味・風味, 価格 | P35: =IFERROR(__xludf.DUMMYFUNCTION("""COMPUTED_VALUE"""),"カフェで") -> カフェで | R35: =IFERROR(__xludf.DUMMYFUNCTION("""COMPUTED_VALUE"""),"週に数回") -> 週に数回 | S35: =IFERROR(__xludf.DUMMYFUNCTION("""COMPUTED_VALUE"""),"休憩・リラックスするため") -> 休憩・リラックスするため | U35: =IFERROR(__xludf.DUMMYFUNCTION("""COMPUTED_VALUE"""),"雰囲気・心地良さ") -> 雰囲気・心地良さ | W35: =IFERROR(__xludf.DUMMYFUNCTION("""COMPUTED_VALUE"""),"はい（日本的）") -> はい（日本的） | X35: =IFERROR(__xludf.DUMMYFUNCTION("""COMPUTED_VALUE"""),"はい（日本的）") -> はい（日本的） | Y35: =IFERROR(__xludf.DUMMYFUNCTION("""COMPUTED_VALUE"""),7.0) -> 7 | Z35: =IFERROR(__xludf.DUMMYFUNCTION("""COMPUTED_VALUE"""),6.0) -> 6 | AA35: =IFERROR(__xludf.DUMMYFUNCTION("""COMPUTED_VALUE"""),7.0) -> 7 | AB35: =IFERROR(__xludf.DUMMYFUNCTION("""COMPUTED_VALUE"""),"いいえ") -> いいえ | AK35: yPaokO6 | AL35: Meb1MBp | AM35: 46040.283 | AN35: 36-45 | AO35: Male | AP35: ¥3,000,000 – ¥5,999,999 | AQ35: Hokkaido | AR35: Daily | AS35: Pour Over | AU35: Rarely | AV35: Matcha Latte | AX35: =IFERROR(__xludf.DUMMYFUNCTION("""COMPUTED_VALUE"""),"Taste/Flavor, Price") -> Taste/Flavor, Price | AZ35: =IFERROR(__xludf.DUMMYFUNCTION("""COMPUTED_VALUE"""),"At cafés") -> At cafés | BB35: Several times a week | BC35: To relax or take a break | BE35: Atmosphere | BG35: Yes, Japanese | BH35: Yes, Japanese | BI35: 7 | BJ35: 6 | BK35: 7 | BL35: No
A36: =IFERROR(__xludf.DUMMYFUNCTION("""COMPUTED_VALUE"""),"rjZqzzM") -> rjZqzzM | B36: =IFERROR(__xludf.DUMMYFUNCTION("""COMPUTED_VALUE"""),"Np6lJxO") -> Np6lJxO | C36: =IFERROR(__xludf.DUMMYFUNCTION("""COMPUTED_VALUE"""),46041.00724537037) -> 46041.007 | D36: =IFERROR(__xludf.DUMMYFUNCTION("""COMPUTED_VALUE"""),"36〜45歳") -> 36〜45歳 | E36: =IFERROR(__xludf.DUMMYFUNCTION("""COMPUTED_VALUE"""),"女性") -> 女性 | F36: =IFERROR(__xludf.DUMMYFUNCTION("""COMPUTED_VALUE"""),"回答しない") -> 回答しない | G36: =IFERROR(__xludf.DUMMYFUNCTION("""COMPUTED_VALUE"""),"関西") -> 関西 | H36: =IFERROR(__xludf.DUMMYFUNCTION("""COMPUTED_VALUE"""),"毎日") -> 毎日 | I36: =IFERROR(__xludf.DUMMYFUNCTION("""COMPUTED_VALUE"""),"プアオーバー（ハンドドリップ）") -> プアオーバー（ハンドドリップ） | K36: =IFERROR(__xludf.DUMMYFUNCTION("""COMPUTED_VALUE"""),"まったく飲まない") -> まったく飲まない | P36: =IFERROR(__xludf.DUMMYFUNCTION("""COMPUTED_VALUE"""),"カフェで") -> カフェで | R36: =IFERROR(__xludf.DUMMYFUNCTION("""COMPUTED_VALUE"""),"月に数回") -> 月に数回 | S36: =IFERROR(__xludf.DUMMYFUNCTION("""COMPUTED_VALUE"""),"友人と会うため") -> 友人と会うため | U36: =IFERROR(__xludf.DUMMYFUNCTION("""COMPUTED_VALUE"""),"飲み物の味・品質") -> 飲み物の味・品質 | W36: =IFERROR(__xludf.DUMMYFUNCTION("""COMPUTED_VALUE"""),"わからない") -> わからない | X36: =IFERROR(__xludf.DUMMYFUNCTION("""COMPUTED_VALUE"""),"はい（日本的）") -> はい（日本的） | Y36: =IFERROR(__xludf.DUMMYFUNCTION("""COMPUTED_VALUE"""),7.0) -> 7 | Z36: =IFERROR(__xludf.DUMMYFUNCTION("""COMPUTED_VALUE"""),7.0) -> 7 | AA36: =IFERROR(__xludf.DUMMYFUNCTION("""COMPUTED_VALUE"""),3.0) -> 3 | AB36: =IFERROR(__xludf.DUMMYFUNCTION("""COMPUTED_VALUE"""),"いいえ") -> いいえ | AK36: rjZqzzM | AL36: Np6lJxO | AM36: 46041.007 | AN36: 36-45 | AO36: Female | AP36: Prefer not to say | AQ36: Kansai | AR36: Daily | AS36: Pour Over | AU36: Never | AX36: =IFERROR(__xludf.DUMMYFUNCTION("""COMPUTED_VALUE"""),"") | AZ36: =IFERROR(__xludf.DUMMYFUNCTION("""COMPUTED_VALUE"""),"At cafés") -> At cafés | BB36: A few times a month | BC36: To meet friends | BE36: Quality of drinks | BG36: Unsure | BH36: Yes, Japanese | BI36: 7 | BJ36: 7 | BK36: 3 | BL36: No
A37: =IFERROR(__xludf.DUMMYFUNCTION("""COMPUTED_VALUE"""),"2E6gLL9") -> 2E6gLL9 | B37: =IFERROR(__xludf.DUMMYFUNCTION("""COMPUTED_VALUE"""),"WON8qMj") -> WON8qMj | C37: =IFERROR(__xludf.DUMMYFUNCTION("""COMPUTED_VALUE"""),46041.56443287037) -> 46041.564 | D37: =IFERROR(__xludf.DUMMYFUNCTION("""COMPUTED_VALUE"""),"36〜45歳") -> 36〜45歳 | E37: =IFERROR(__xludf.DUMMYFUNCTION("""COMPUTED_VALUE"""),"女性") -> 女性 | F37: =IFERROR(__xludf.DUMMYFUNCTION("""COMPUTED_VALUE"""),"600万円〜899万9,999円") -> 600万円〜899万9,999円 | G37: =IFERROR(__xludf.DUMMYFUNCTION("""COMPUTED_VALUE"""),"北海道") -> 北海道 | H37: =IFERROR(__xludf.DUMMYFUNCTION("""COMPUTED_VALUE"""),"毎日") -> 毎日 | I37: =IFERROR(__xludf.DUMMYFUNCTION("""COMPUTED_VALUE"""),"ドリップコーヒー") -> ドリップコーヒー | K37: =IFERROR(__xludf.DUMMYFUNCTION("""COMPUTED_VALUE"""),"ほとんど飲まない") -> ほとんど飲まない | L37: =IFERROR(__xludf.DUMMYFUNCTION("""COMPUTED_VALUE"""),"薄茶") -> 薄茶 | N37: =IFERROR(__xludf.DUMMYFUNCTION("""COMPUTED_VALUE"""),"健康面のメリット") -> 健康面のメリット | P37: =IFERROR(__xludf.DUMMYFUNCTION("""COMPUTED_VALUE"""),"自宅で") -> 自宅で | R37: =IFERROR(__xludf.DUMMYFUNCTION("""COMPUTED_VALUE"""),"月に数回") -> 月に数回 | S37: =IFERROR(__xludf.DUMMYFUNCTION("""COMPUTED_VALUE"""),"休憩・リラックスするため") -> 休憩・リラックスするため | U37: =IFERROR(__xludf.DUMMYFUNCTION("""COMPUTED_VALUE"""),"飲み物の味・品質") -> 飲み物の味・品質 | W37: =IFERROR(__xludf.DUMMYFUNCTION("""COMPUTED_VALUE"""),"はい（グローバル）") -> はい（グローバル） | X37: =IFERROR(__xludf.DUMMYFUNCTION("""COMPUTED_VALUE"""),"はい（日本的）") -> はい（日本的） | Y37: =IFERROR(__xludf.DUMMYFUNCTION("""COMPUTED_VALUE"""),6.0) -> 6 | Z37: =IFERROR(__xludf.DUMMYFUNCTION("""COMPUTED_VALUE"""),6.0) -> 6 | AA37: =IFERROR(__xludf.DUMMYFUNCTION("""COMPUTED_VALUE"""),6.0) -> 6 | AB37: =IFERROR(__xludf.DUMMYFUNCTION("""COMPUTED_VALUE"""),"はい") -> はい | AK37: 2E6gLL9 | AL37: WON8qMj | AM37: 46041.564 | AN37: 36-45 | AO37: Female | AP37: ¥6,000,000 – ¥8,999,999 | AQ37: Hokkaido | AR37: Daily | AS37: Drip | AU37: Rarely | AV37: Usucha | AX37: =IFERROR(__xludf.DUMMYFUNCTION("""COMPUTED_VALUE"""),"Health benefits") -> Health benefits | AZ37: =IFERROR(__xludf.DUMMYFUNCTION("""COMPUTED_VALUE"""),"At home") -> At home | BB37: A few times a month | BC37: To relax or take a break | BE37: Quality of drinks | BG37: Yes, Global | BH37: Yes, Japanese | BI37: 6 | BJ37: 6 | BK37: 6 | BL37: Yes
A38: =IFERROR(__xludf.DUMMYFUNCTION("""COMPUTED_VALUE"""),"LZ22L4G") -> LZ22L4G | B38: =IFERROR(__xludf.DUMMYFUNCTION("""COMPUTED_VALUE"""),"pbKL1Gy") -> pbKL1Gy | C38: =IFERROR(__xludf.DUMMYFUNCTION("""COMPUTED_VALUE"""),46042.46795138889) -> 46042.468 | D38: =IFERROR(__xludf.DUMMYFUNCTION("""COMPUTED_VALUE"""),"18〜25歳") -> 18〜25歳 | E38: =IFERROR(__xludf.DUMMYFUNCTION("""COMPUTED_VALUE"""),"男性") -> 男性 | F38: =IFERROR(__xludf.DUMMYFUNCTION("""COMPUTED_VALUE"""),"300万円〜599万9,999円") -> 300万円〜599万9,999円 | G38: =IFERROR(__xludf.DUMMYFUNCTION("""COMPUTED_VALUE"""),"東北") -> 東北 | H38: =IFERROR(__xludf.DUMMYFUNCTION("""COMPUTED_VALUE"""),"毎日") -> 毎日 | I38: =IFERROR(__xludf.DUMMYFUNCTION("""COMPUTED_VALUE"""),"プアオーバー（ハンドドリップ）") -> プアオーバー（ハンドドリップ） | K38: =IFERROR(__xludf.DUMMYFUNCTION("""COMPUTED_VALUE"""),"ほとんど飲まない") -> ほとんど飲まない | L38: =IFERROR(__xludf.DUMMYFUNCTION("""COMPUTED_VALUE"""),"薄茶") -> 薄茶 | N38: =IFERROR(__xludf.DUMMYFUNCTION("""COMPUTED_VALUE"""),"習慣") -> 習慣 | P38: =IFERROR(__xludf.DUMMYFUNCTION("""COMPUTED_VALUE"""),"カフェで") -> カフェで | R38: =IFERROR(__xludf.DUMMYFUNCTION("""COMPUTED_VALUE"""),"週に数回") -> 週に数回 | S38: =IFERROR(__xludf.DUMMYFUNCTION("""COMPUTED_VALUE"""),"休憩・リラックスするため") -> 休憩・リラックスするため | U38: =IFERROR(__xludf.DUMMYFUNCTION("""COMPUTED_VALUE"""),"サービス") -> サービス | W38: =IFERROR(__xludf.DUMMYFUNCTION("""COMPUTED_VALUE"""),"はい（グローバル）") -> はい（グローバル） | X38: =IFERROR(__xludf.DUMMYFUNCTION("""COMPUTED_VALUE"""),"はい（日本的）") -> はい（日本的） | Y38: =IFERROR(__xludf.DUMMYFUNCTION("""COMPUTED_VALUE"""),7.0) -> 7 | Z38: =IFERROR(__xludf.DUMMYFUNCTION("""COMPUTED_VALUE"""),7.0) -> 7 | AA38: =IFERROR(__xludf.DUMMYFUNCTION("""COMPUTED_VALUE"""),7.0) -> 7 | AB38: =IFERROR(__xludf.DUMMYFUNCTION("""COMPUTED_VALUE"""),"いいえ") -> いいえ | AK38: LZ22L4G | AL38: pbKL1Gy | AM38: 46042.468 | AN38: 18-25 | AO38: Male | AP38: ¥3,000,000 – ¥5,999,999 | AQ38: Tohoku | AR38: Daily | AS38: Pour Over | AU38: Rarely | AV38: Usucha | AX38: =IFERROR(__xludf.DUMMYFUNCTION("""COMPUTED_VALUE"""),"Routine/Ritual") -> Routine/Ritual | AZ38: =IFERROR(__xludf.DUMMYFUNCTION("""COMPUTED_VALUE"""),"At cafés") -> At cafés | BB38: Several times a week | BC38: To relax or take a break | BE38: Service | BG38: Yes, Global | BH38: Yes, Japanese | BI38: 7 | BJ38: 7 | BK38: 7 | BL38: No
A39: =IFERROR(__xludf.DUMMYFUNCTION("""COMPUTED_VALUE"""),"rj4laqL") -> rj4laqL | B39: =IFERROR(__xludf.DUMMYFUNCTION("""COMPUTED_VALUE"""),"Np6dba0") -> Np6dba0 | C39: =IFERROR(__xludf.DUMMYFUNCTION("""COMPUTED_VALUE"""),46045.29539351852) -> 46045.295 | D39: =IFERROR(__xludf.DUMMYFUNCTION("""COMPUTED_VALUE"""),"18〜25歳") -> 18〜25歳 | E39: =IFERROR(__xludf.DUMMYFUNCTION("""COMPUTED_VALUE"""),"男性") -> 男性 | F39: =IFERROR(__xludf.DUMMYFUNCTION("""COMPUTED_VALUE"""),"300万円〜599万9,999円") -> 300万円〜599万9,999円 | G39: =IFERROR(__xludf.DUMMYFUNCTION("""COMPUTED_VALUE"""),"関東") -> 関東 | H39: =IFERROR(__xludf.DUMMYFUNCTION("""COMPUTED_VALUE"""),"毎日") -> 毎日 | I39: =IFERROR(__xludf.DUMMYFUNCTION("""COMPUTED_VALUE"""),"プアオーバー（ハンドドリップ）") -> プアオーバー（ハンドドリップ） | K39: =IFERROR(__xludf.DUMMYFUNCTION("""COMPUTED_VALUE"""),"ほとんど飲まない") -> ほとんど飲まない | L39: =IFERROR(__xludf.DUMMYFUNCTION("""COMPUTED_VALUE"""),"薄茶") -> 薄茶 | N39: =IFERROR(__xludf.DUMMYFUNCTION("""COMPUTED_VALUE"""),"習慣") -> 習慣 | P39: =IFERROR(__xludf.DUMMYFUNCTION("""COMPUTED_VALUE"""),"その他：") -> その他： | Q39: =IFERROR(__xludf.DUMMYFUNCTION("""COMPUTED_VALUE"""),"職場") -> 職場 | R39: =IFERROR(__xludf.DUMMYFUNCTION("""COMPUTED_VALUE"""),"月に数回") -> 月に数回 | S39: =IFERROR(__xludf.DUMMYFUNCTION("""COMPUTED_VALUE"""),"新しい飲み物を試すため") -> 新しい飲み物を試すため | U39: =IFERROR(__xludf.DUMMYFUNCTION("""COMPUTED_VALUE"""),"雰囲気・心地良さ") -> 雰囲気・心地良さ | W39: =IFERROR(__xludf.DUMMYFUNCTION("""COMPUTED_VALUE"""),"はい（グローバル）") -> はい（グローバル） | X39: =IFERROR(__xludf.DUMMYFUNCTION("""COMPUTED_VALUE"""),"はい（グローバル）") -> はい（グローバル） | Y39: =IFERROR(__xludf.DUMMYFUNCTION("""COMPUTED_VALUE"""),6.0) -> 6 | Z39: =IFERROR(__xludf.DUMMYFUNCTION("""COMPUTED_VALUE"""),2.0) -> 2 | AB39: =IFERROR(__xludf.DUMMYFUNCTION("""COMPUTED_VALUE"""),"はい") -> はい | AK39: rj4laqL | AL39: Np6dba0 | AM39: 46045.295 | AN39: 18-25 | AO39: Male | AP39: ¥3,000,000 – ¥5,999,999 | AQ39: Kanto | AR39: Daily | AS39: Pour Over | AU39: Rarely | AV39: Usucha | AX39: =IFERROR(__xludf.DUMMYFUNCTION("""COMPUTED_VALUE"""),"Routine/Ritual") -> Routine/Ritual | AZ39: =IFERROR(__xludf.DUMMYFUNCTION("""COMPUTED_VALUE"""),"Other:") -> Other: | BA39: Workplace | BB39: A few times a month | BC39: To try a new drink | BE39: Atmosphere | BG39: Yes, Global | BH39: Yes, Global | BI39: 6 | BJ39: 2 | BL39: Yes
A40: =IFERROR(__xludf.DUMMYFUNCTION("""COMPUTED_VALUE"""),"VLeljXE") -> VLeljXE | B40: =IFERROR(__xludf.DUMMYFUNCTION("""COMPUTED_VALUE"""),"xXpzMVk") -> xXpzMVk | C40: =IFERROR(__xludf.DUMMYFUNCTION("""COMPUTED_VALUE"""),46045.45578703703) -> 46045.456 | D40: =IFERROR(__xludf.DUMMYFUNCTION("""COMPUTED_VALUE"""),"26〜35歳") -> 26〜35歳 | E40: =IFERROR(__xludf.DUMMYFUNCTION("""COMPUTED_VALUE"""),"男性") -> 男性 | F40: =IFERROR(__xludf.DUMMYFUNCTION("""COMPUTED_VALUE"""),"1,200万円以上") -> 1,200万円以上 | G40: =IFERROR(__xludf.DUMMYFUNCTION("""COMPUTED_VALUE"""),"関東") -> 関東 | H40: =IFERROR(__xludf.DUMMYFUNCTION("""COMPUTED_VALUE"""),"毎日") -> 毎日 | I40: =IFERROR(__xludf.DUMMYFUNCTION("""COMPUTED_VALUE"""),"ドリップコーヒー") -> ドリップコーヒー | K40: =IFERROR(__xludf.DUMMYFUNCTION("""COMPUTED_VALUE"""),"週に数回") -> 週に数回 | L40: =IFERROR(__xludf.DUMMYFUNCTION("""COMPUTED_VALUE"""),"抹茶ラテ") -> 抹茶ラテ | N40: =IFERROR(__xludf.DUMMYFUNCTION("""COMPUTED_VALUE"""),"習慣") -> 習慣 | P40: =IFERROR(__xludf.DUMMYFUNCTION("""COMPUTED_VALUE"""),"自宅で, カフェで, コンビニ（セブンイレブン、ローソンなど）, 自動販売機") -> 自宅で, カフェで, コンビニ（セブンイレブン、ローソンなど）, 自動販売機 | R40: =IFERROR(__xludf.DUMMYFUNCTION("""COMPUTED_VALUE"""),"週に数回") -> 週に数回 | S40: =IFERROR(__xludf.DUMMYFUNCTION("""COMPUTED_VALUE"""),"習慣として") -> 習慣として | U40: =IFERROR(__xludf.DUMMYFUNCTION("""COMPUTED_VALUE"""),"その他：") -> その他： | W40: =IFERROR(__xludf.DUMMYFUNCTION("""COMPUTED_VALUE"""),"はい（グローバル）") -> はい（グローバル） | X40: =IFERROR(__xludf.DUMMYFUNCTION("""COMPUTED_VALUE"""),"はい（日本的）") -> はい（日本的） | Y40: =IFERROR(__xludf.DUMMYFUNCTION("""COMPUTED_VALUE"""),7.0) -> 7 | Z40: =IFERROR(__xludf.DUMMYFUNCTION("""COMPUTED_VALUE"""),7.0) -> 7 | AA40: =IFERROR(__xludf.DUMMYFUNCTION("""COMPUTED_VALUE"""),7.0) -> 7 | AB40: =IFERROR(__xludf.DUMMYFUNCTION("""COMPUTED_VALUE"""),"はい") -> はい | AK40: VLeljXE | AL40: xXpzMVk | AM40: 46045.456 | AN40: 26-35 | AO40: Male | AP40: ¥12,000,000 or more | AQ40: Kanto | AR40: Daily | AS40: Drip | AU40: Several times a week | AV40: Matcha Latte | AX40: =IFERROR(__xludf.DUMMYFUNCTION("""COMPUTED_VALUE"""),"Routine/Ritual") -> Routine/Ritual | AZ40: =IFERROR(__xludf.DUMMYFUNCTION("""COMPUTED_VALUE"""),"At home, At cafés, From convenience stores (7-Eleven, Lawson, etc.), From vending machines") -> At home, At cafés, From convenience stores (7-Eleven, Lawson, etc.), From vending machines | BB40: Several times a week | BC40: Out of habit | BE40: Other: | BG40: Yes, Global | BH40: Yes, Japanese | BI40: 7 | BJ40: 7 | BK40: 7 | BL40: Yes
A41: =IFERROR(__xludf.DUMMYFUNCTION("""COMPUTED_VALUE"""),"aQLx2aE") -> aQLx2aE | B41: =IFERROR(__xludf.DUMMYFUNCTION("""COMPUTED_VALUE"""),"WONqRGN") -> WONqRGN | C41: =IFERROR(__xludf.DUMMYFUNCTION("""COMPUTED_VALUE"""),46045.46512731481) -> 46045.465 | D41: =IFERROR(__xludf.DUMMYFUNCTION("""COMPUTED_VALUE"""),"18〜25歳") -> 18〜25歳 | E41: =IFERROR(__xludf.DUMMYFUNCTION("""COMPUTED_VALUE"""),"女性") -> 女性 | F41: =IFERROR(__xludf.DUMMYFUNCTION("""COMPUTED_VALUE"""),"300万円未満") -> 300万円未満 | G41: =IFERROR(__xludf.DUMMYFUNCTION("""COMPUTED_VALUE"""),"関東") -> 関東 | H41: =IFERROR(__xludf.DUMMYFUNCTION("""COMPUTED_VALUE"""),"週に数回") -> 週に数回 | I41: =IFERROR(__xludf.DUMMYFUNCTION("""COMPUTED_VALUE"""),"プアオーバー（ハンドドリップ）") -> プアオーバー（ハンドドリップ） | K41: =IFERROR(__xludf.DUMMYFUNCTION("""COMPUTED_VALUE"""),"週に1回") -> 週に1回 | L41: =IFERROR(__xludf.DUMMYFUNCTION("""COMPUTED_VALUE"""),"抹茶ラテ") -> 抹茶ラテ | N41: =IFERROR(__xludf.DUMMYFUNCTION("""COMPUTED_VALUE"""),"味・風味, エナジー／カフェイン") -> 味・風味, エナジー／カフェイン | P41: =IFERROR(__xludf.DUMMYFUNCTION("""COMPUTED_VALUE"""),"カフェで, 自宅で, コンビニ（セブンイレブン、ローソンなど）") -> カフェで, 自宅で, コンビニ（セブンイレブン、ローソンなど） | R41: =IFERROR(__xludf.DUMMYFUNCTION("""COMPUTED_VALUE"""),"週に1回") -> 週に1回 | S41: =IFERROR(__xludf.DUMMYFUNCTION("""COMPUTED_VALUE"""),"習慣として") -> 習慣として | U41: =IFERROR(__xludf.DUMMYFUNCTION("""COMPUTED_VALUE"""),"サービス") -> サービス | W41: =IFERROR(__xludf.DUMMYFUNCTION("""COMPUTED_VALUE"""),"はい（グローバル）") -> はい（グローバル） | X41: =IFERROR(__xludf.DUMMYFUNCTION("""COMPUTED_VALUE"""),"はい（日本的）") -> はい（日本的） | Y41: =IFERROR(__xludf.DUMMYFUNCTION("""COMPUTED_VALUE"""),5.0) -> 5 | Z41: =IFERROR(__xludf.DUMMYFUNCTION("""COMPUTED_VALUE"""),7.0) -> 7 | AA41: =IFERROR(__xludf.DUMMYFUNCTION("""COMPUTED_VALUE"""),6.0) -> 6 | AB41: =IFERROR(__xludf.DUMMYFUNCTION("""COMPUTED_VALUE"""),"いいえ") -> いいえ | AK41: aQLx2aE | AL41: WONqRGN | AM41: 46045.465 | AN41: 18-25 | AO41: Female | AP41: Under ¥3,000,000 | AQ41: Kanto | AR41: Several times a week | AS41: Pour Over | AU41: Once a week | AV41: Matcha Latte | AX41: =IFERROR(__xludf.DUMMYFUNCTION("""COMPUTED_VALUE"""),"Taste/Flavor, Energy boost/Caffeine") -> Taste/Flavor, Energy boost/Caffeine | AZ41: =IFERROR(__xludf.DUMMYFUNCTION("""COMPUTED_VALUE"""),"At cafés, At home, From convenience stores (7-Eleven, Lawson, etc.)") -> At cafés, At home, From convenience stores (7-Eleven, Lawson, etc.) | BB41: Once a week | BC41: Out of habit | BE41: Service | BG41: Yes, Global | BH41: Yes, Japanese | BI41: 5 | BJ41: 7 | BK41: 6 | BL41: No
A42: =IFERROR(__xludf.DUMMYFUNCTION("""COMPUTED_VALUE"""),"Bzy1jOR") -> Bzy1jOR | B42: =IFERROR(__xludf.DUMMYFUNCTION("""COMPUTED_VALUE"""),"zxqdr2g") -> zxqdr2g | C42: =IFERROR(__xludf.DUMMYFUNCTION("""COMPUTED_VALUE"""),46045.51131944444) -> 46045.511 | D42: =IFERROR(__xludf.DUMMYFUNCTION("""COMPUTED_VALUE"""),"36〜45歳") -> 36〜45歳 | E42: =IFERROR(__xludf.DUMMYFUNCTION("""COMPUTED_VALUE"""),"女性") -> 女性 | F42: =IFERROR(__xludf.DUMMYFUNCTION("""COMPUTED_VALUE"""),"300万円未満") -> 300万円未満 | G42: =IFERROR(__xludf.DUMMYFUNCTION("""COMPUTED_VALUE"""),"関東") -> 関東 | H42: =IFERROR(__xludf.DUMMYFUNCTION("""COMPUTED_VALUE"""),"毎日") -> 毎日 | I42: =IFERROR(__xludf.DUMMYFUNCTION("""COMPUTED_VALUE"""),"プアオーバー（ハンドドリップ）") -> プアオーバー（ハンドドリップ） | K42: =IFERROR(__xludf.DUMMYFUNCTION("""COMPUTED_VALUE"""),"ほとんど飲まない") -> ほとんど飲まない | L42: =IFERROR(__xludf.DUMMYFUNCTION("""COMPUTED_VALUE"""),"薄茶") -> 薄茶 | N42: =IFERROR(__xludf.DUMMYFUNCTION("""COMPUTED_VALUE"""),"習慣, その他：") -> 習慣, その他： | P42: =IFERROR(__xludf.DUMMYFUNCTION("""COMPUTED_VALUE"""),"カフェで, その他：") -> カフェで, その他： | S42: =IFERROR(__xludf.DUMMYFUNCTION("""COMPUTED_VALUE"""),"休憩・リラックスするため") -> 休憩・リラックスするため | U42: =IFERROR(__xludf.DUMMYFUNCTION("""COMPUTED_VALUE"""),"飲み物の味・品質") -> 飲み物の味・品質 | W42: =IFERROR(__xludf.DUMMYFUNCTION("""COMPUTED_VALUE"""),"はい（グローバル）") -> はい（グローバル） | X42: =IFERROR(__xludf.DUMMYFUNCTION("""COMPUTED_VALUE"""),"はい（日本的）") -> はい（日本的） | Y42: =IFERROR(__xludf.DUMMYFUNCTION("""COMPUTED_VALUE"""),7.0) -> 7 | Z42: =IFERROR(__xludf.DUMMYFUNCTION("""COMPUTED_VALUE"""),7.0) -> 7 | AA42: =IFERROR(__xludf.DUMMYFUNCTION("""COMPUTED_VALUE"""),5.0) -> 5 | AB42: =IFERROR(__xludf.DUMMYFUNCTION("""COMPUTED_VALUE"""),"いいえ") -> いいえ | AK42: Bzy1jOR | AL42: zxqdr2g | AM42: 46045.511 | AN42: 36-45 | AO42: Female | AP42: Under ¥3,000,000 | AQ42: Kanto | AR42: Daily | AS42: Pour Over | AU42: Rarely | AV42: Usucha | AX42: =IFERROR(__xludf.DUMMYFUNCTION("""COMPUTED_VALUE"""),"Routine/Ritual, Other:") -> Routine/Ritual, Other: | AZ42: =IFERROR(__xludf.DUMMYFUNCTION("""COMPUTED_VALUE"""),"At cafés, Other:") -> At cafés, Other: | BC42: To relax or take a break | BE42: Quality of drinks | BG42: Yes, Global | BH42: Yes, Japanese | BI42: 7 | BJ42: 7 | BK42: 5 | BL42: No
A43: =IFERROR(__xludf.DUMMYFUNCTION("""COMPUTED_VALUE"""),"yPQEMog") -> yPQEMog | B43: =IFERROR(__xludf.DUMMYFUNCTION("""COMPUTED_VALUE"""),"448EV9X") -> 448EV9X | C43: =IFERROR(__xludf.DUMMYFUNCTION("""COMPUTED_VALUE"""),46046.104837962965) -> 46046.105 | D43: =IFERROR(__xludf.DUMMYFUNCTION("""COMPUTED_VALUE"""),"18〜25歳") -> 18〜25歳 | E43: =IFERROR(__xludf.DUMMYFUNCTION("""COMPUTED_VALUE"""),"女性") -> 女性 | F43: =IFERROR(__xludf.DUMMYFUNCTION("""COMPUTED_VALUE"""),"回答しない") -> 回答しない | G43: =IFERROR(__xludf.DUMMYFUNCTION("""COMPUTED_VALUE"""),"関東") -> 関東 | H43: =IFERROR(__xludf.DUMMYFUNCTION("""COMPUTED_VALUE"""),"毎日") -> 毎日 | I43: =IFERROR(__xludf.DUMMYFUNCTION("""COMPUTED_VALUE"""),"アメリカーノ") -> アメリカーノ | K43: =IFERROR(__xludf.DUMMYFUNCTION("""COMPUTED_VALUE"""),"ほとんど飲まない") -> ほとんど飲まない | L43: =IFERROR(__xludf.DUMMYFUNCTION("""COMPUTED_VALUE"""),"抹茶ラテ") -> 抹茶ラテ | N43: =IFERROR(__xludf.DUMMYFUNCTION("""COMPUTED_VALUE"""),"味・風味, エナジー／カフェイン") -> 味・風味, エナジー／カフェイン | P43: =IFERROR(__xludf.DUMMYFUNCTION("""COMPUTED_VALUE"""),"カフェで") -> カフェで | R43: =IFERROR(__xludf.DUMMYFUNCTION("""COMPUTED_VALUE"""),"毎日") -> 毎日 | S43: =IFERROR(__xludf.DUMMYFUNCTION("""COMPUTED_VALUE"""),"習慣として") -> 習慣として | U43: =IFERROR(__xludf.DUMMYFUNCTION("""COMPUTED_VALUE"""),"雰囲気・心地良さ") -> 雰囲気・心地良さ | W43: =IFERROR(__xludf.DUMMYFUNCTION("""COMPUTED_VALUE"""),"いいえ") -> いいえ | X43: =IFERROR(__xludf.DUMMYFUNCTION("""COMPUTED_VALUE"""),"はい（日本的）") -> はい（日本的） | Y43: =IFERROR(__xludf.DUMMYFUNCTION("""COMPUTED_VALUE"""),6.0) -> 6 | Z43: =IFERROR(__xludf.DUMMYFUNCTION("""COMPUTED_VALUE"""),6.0) -> 6 | AA43: =IFERROR(__xludf.DUMMYFUNCTION("""COMPUTED_VALUE"""),7.0) -> 7 | AB43: =IFERROR(__xludf.DUMMYFUNCTION("""COMPUTED_VALUE"""),"いいえ") -> いいえ | AK43: yPQEMog | AL43: 448EV9X | AM43: 46046.105 | AN43: 18-25 | AO43: Female | AP43: Prefer not to say | AQ43: Kanto | AR43: Daily | AS43: Americano | AU43: Rarely | AV43: Matcha Latte | AX43: =IFERROR(__xludf.DUMMYFUNCTION("""COMPUTED_VALUE"""),"Taste/Flavor, Energy boost/Caffeine") -> Taste/Flavor, Energy boost/Caffeine | AZ43: =IFERROR(__xludf.DUMMYFUNCTION("""COMPUTED_VALUE"""),"At cafés") -> At cafés | BB43: Daily | BC43: Out of habit | BE43: Atmosphere | BG43: No | BH43: Yes, Japanese | BI43: 6 | BJ43: 6 | BK43: 7 | BL43: No
A44: =IFERROR(__xludf.DUMMYFUNCTION("""COMPUTED_VALUE"""),"xXqPPd9") -> xXqPPd9 | B44: =IFERROR(__xludf.DUMMYFUNCTION("""COMPUTED_VALUE"""),"2EeZ8Ej") -> 2EeZ8Ej | C44: =IFERROR(__xludf.DUMMYFUNCTION("""COMPUTED_VALUE"""),46046.181608796294) -> 46046.182 | D44: =IFERROR(__xludf.DUMMYFUNCTION("""COMPUTED_VALUE"""),"18〜25歳") -> 18〜25歳 | E44: =IFERROR(__xludf.DUMMYFUNCTION("""COMPUTED_VALUE"""),"男性") -> 男性 | F44: =IFERROR(__xludf.DUMMYFUNCTION("""COMPUTED_VALUE"""),"600万円〜899万9,999円") -> 600万円〜899万9,999円 | G44: =IFERROR(__xludf.DUMMYFUNCTION("""COMPUTED_VALUE"""),"関東") -> 関東 | H44: =IFERROR(__xludf.DUMMYFUNCTION("""COMPUTED_VALUE"""),"週に数回") -> 週に数回 | I44: =IFERROR(__xludf.DUMMYFUNCTION("""COMPUTED_VALUE"""),"プアオーバー（ハンドドリップ）") -> プアオーバー（ハンドドリップ） | K44: =IFERROR(__xludf.DUMMYFUNCTION("""COMPUTED_VALUE"""),"ほとんど飲まない") -> ほとんど飲まない | N44: =IFERROR(__xludf.DUMMYFUNCTION("""COMPUTED_VALUE"""),"味・風味, 社交的な場や雰囲気の考慮") -> 味・風味, 社交的な場や雰囲気の考慮 | P44: =IFERROR(__xludf.DUMMYFUNCTION("""COMPUTED_VALUE"""),"自宅で, カフェで") -> 自宅で, カフェで | R44: =IFERROR(__xludf.DUMMYFUNCTION("""COMPUTED_VALUE"""),"週に数回") -> 週に数回 | S44: =IFERROR(__xludf.DUMMYFUNCTION("""COMPUTED_VALUE"""),"勉強・仕事をするため") -> 勉強・仕事をするため | U44: =IFERROR(__xludf.DUMMYFUNCTION("""COMPUTED_VALUE"""),"雰囲気・心地良さ") -> 雰囲気・心地良さ | W44: =IFERROR(__xludf.DUMMYFUNCTION("""COMPUTED_VALUE"""),"いいえ") -> いいえ | X44: =IFERROR(__xludf.DUMMYFUNCTION("""COMPUTED_VALUE"""),"はい（日本的）") -> はい（日本的） | Y44: =IFERROR(__xludf.DUMMYFUNCTION("""COMPUTED_VALUE"""),6.0) -> 6 | Z44: =IFERROR(__xludf.DUMMYFUNCTION("""COMPUTED_VALUE"""),6.0) -> 6 | AA44: =IFERROR(__xludf.DUMMYFUNCTION("""COMPUTED_VALUE"""),7.0) -> 7 | AB44: =IFERROR(__xludf.DUMMYFUNCTION("""COMPUTED_VALUE"""),"いいえ") -> いいえ | AK44: xXqPPd9 | AL44: 2EeZ8Ej | AM44: 46046.182 | AN44: 18-25 | AO44: Male | AP44: ¥6,000,000 – ¥8,999,999 | AQ44: Kanto | AR44: Several times a week | AS44: Pour Over | AU44: Rarely | AX44: =IFERROR(__xludf.DUMMYFUNCTION("""COMPUTED_VALUE"""),"Taste/Flavor, Social atmosphere") -> Taste/Flavor, Social atmosphere | AZ44: =IFERROR(__xludf.DUMMYFUNCTION("""COMPUTED_VALUE"""),"At home, At cafés") -> At home, At cafés | BB44: Several times a week | BC44: To study/work | BE44: Atmosphere | BG44: No | BH44: Yes, Japanese | BI44: 6 | BJ44: 6 | BK44: 7 | BL44: No
A45: =IFERROR(__xludf.DUMMYFUNCTION("""COMPUTED_VALUE"""),"QKZxNdp") -> QKZxNdp | B45: =IFERROR(__xludf.DUMMYFUNCTION("""COMPUTED_VALUE"""),"RG0lj0d") -> RG0lj0d | C45: =IFERROR(__xludf.DUMMYFUNCTION("""COMPUTED_VALUE"""),46046.659050925926) -> 46046.659 | D45: =IFERROR(__xludf.DUMMYFUNCTION("""COMPUTED_VALUE"""),"26〜35歳") -> 26〜35歳 | E45: =IFERROR(__xludf.DUMMYFUNCTION("""COMPUTED_VALUE"""),"男性") -> 男性 | F45: =IFERROR(__xludf.DUMMYFUNCTION("""COMPUTED_VALUE"""),"300万円〜599万9,999円") -> 300万円〜599万9,999円 | G45: =IFERROR(__xludf.DUMMYFUNCTION("""COMPUTED_VALUE"""),"関東") -> 関東 | H45: =IFERROR(__xludf.DUMMYFUNCTION("""COMPUTED_VALUE"""),"ほとんど飲まない") -> ほとんど飲まない | I45: =IFERROR(__xludf.DUMMYFUNCTION("""COMPUTED_VALUE"""),"コーヒーは飲まない") -> コーヒーは飲まない | K45: =IFERROR(__xludf.DUMMYFUNCTION("""COMPUTED_VALUE"""),"週に数回") -> 週に数回 | L45: =IFERROR(__xludf.DUMMYFUNCTION("""COMPUTED_VALUE"""),"抹茶ラテ") -> 抹茶ラテ | N45: =IFERROR(__xludf.DUMMYFUNCTION("""COMPUTED_VALUE"""),"味・風味, 新しいものを試したい") -> 味・風味, 新しいものを試したい | P45: =IFERROR(__xludf.DUMMYFUNCTION("""COMPUTED_VALUE"""),"カフェで") -> カフェで | R45: =IFERROR(__xludf.DUMMYFUNCTION("""COMPUTED_VALUE"""),"月に数回") -> 月に数回 | S45: =IFERROR(__xludf.DUMMYFUNCTION("""COMPUTED_VALUE"""),"友人と会うため") -> 友人と会うため | U45: =IFERROR(__xludf.DUMMYFUNCTION("""COMPUTED_VALUE"""),"雰囲気・心地良さ") -> 雰囲気・心地良さ | W45: =IFERROR(__xludf.DUMMYFUNCTION("""COMPUTED_VALUE"""),"わからない") -> わからない | X45: =IFERROR(__xludf.DUMMYFUNCTION("""COMPUTED_VALUE"""),"はい（日本的）") -> はい（日本的） | Y45: =IFERROR(__xludf.DUMMYFUNCTION("""COMPUTED_VALUE"""),0.0) -> 0 | Z45: =IFERROR(__xludf.DUMMYFUNCTION("""COMPUTED_VALUE"""),7.0) -> 7 | AA45: =IFERROR(__xludf.DUMMYFUNCTION("""COMPUTED_VALUE"""),6.0) -> 6 | AB45: =IFERROR(__xludf.DUMMYFUNCTION("""COMPUTED_VALUE"""),"いいえ") -> いいえ | AK45: QKZxNdp | AL45: RG0lj0d | AM45: 46046.659 | AN45: 26-35 | AO45: Male | AP45: ¥3,000,000 – ¥5,999,999 | AQ45: Kanto | AR45: Rarely | AS45: I don't drink coffee | AU45: Several times a week | AV45: Matcha Latte | AX45: =IFERROR(__xludf.DUMMYFUNCTION("""COMPUTED_VALUE"""),"Taste/Flavor, To try new things") -> Taste/Flavor, To try new things | AZ45: =IFERROR(__xludf.DUMMYFUNCTION("""COMPUTED_VALUE"""),"At cafés") -> At cafés | BB45: A few times a month | BC45: To meet friends | BE45: Atmosphere | BG45: Unsure | BH45: Yes, Japanese | BI45: 0 | BJ45: 7 | BK45: 6 | BL45: No
A46: =IFERROR(__xludf.DUMMYFUNCTION("""COMPUTED_VALUE"""),"LZrOWjz") -> LZrOWjz | B46: =IFERROR(__xludf.DUMMYFUNCTION("""COMPUTED_VALUE"""),"RG0QBEK") -> RG0QBEK | C46: =IFERROR(__xludf.DUMMYFUNCTION("""COMPUTED_VALUE"""),46047.76725694445) -> 46047.767 | D46: =IFERROR(__xludf.DUMMYFUNCTION("""COMPUTED_VALUE"""),"46〜55歳") -> 46〜55歳 | E46: =IFERROR(__xludf.DUMMYFUNCTION("""COMPUTED_VALUE"""),"女性") -> 女性 | F46: =IFERROR(__xludf.DUMMYFUNCTION("""COMPUTED_VALUE"""),"回答しない") -> 回答しない | G46: =IFERROR(__xludf.DUMMYFUNCTION("""COMPUTED_VALUE"""),"日本には住んでいない") -> 日本には住んでいない | H46: =IFERROR(__xludf.DUMMYFUNCTION("""COMPUTED_VALUE"""),"毎日") -> 毎日 | I46: =IFERROR(__xludf.DUMMYFUNCTION("""COMPUTED_VALUE"""),"ドリップコーヒー") -> ドリップコーヒー | K46: =IFERROR(__xludf.DUMMYFUNCTION("""COMPUTED_VALUE"""),"まったく飲まない") -> まったく飲まない | N46: =IFERROR(__xludf.DUMMYFUNCTION("""COMPUTED_VALUE"""),"習慣, 価格") -> 習慣, 価格 | R46: =IFERROR(__xludf.DUMMYFUNCTION("""COMPUTED_VALUE"""),"ほとんど行かない") -> ほとんど行かない | W46: =IFERROR(__xludf.DUMMYFUNCTION("""COMPUTED_VALUE"""),"いいえ") -> いいえ | X46: =IFERROR(__xludf.DUMMYFUNCTION("""COMPUTED_VALUE"""),"はい（日本的）") -> はい（日本的） | AK46: LZrOWjz | AL46: RG0QBEK | AM46: 46047.767 | AN46: 46-55 | AO46: Female | AP46: Prefer not to say | AQ46: I do not live in Japan | AR46: Daily | AS46: Drip | AU46: Never | AX46: =IFERROR(__xludf.DUMMYFUNCTION("""COMPUTED_VALUE"""),"Routine/Ritual, Price") -> Routine/Ritual, Price | AZ46: =IFERROR(__xludf.DUMMYFUNCTION("""COMPUTED_VALUE"""),"") | BB46: Rarely | BG46: No | BH46: Yes, Japanese
A47: =IFERROR(__xludf.DUMMYFUNCTION("""COMPUTED_VALUE"""),"dWMpYWq") -> dWMpYWq | B47: =IFERROR(__xludf.DUMMYFUNCTION("""COMPUTED_VALUE"""),"eq6gKzq") -> eq6gKzq | C47: =IFERROR(__xludf.DUMMYFUNCTION("""COMPUTED_VALUE"""),46048.39412037037) -> 46048.394 | D47: =IFERROR(__xludf.DUMMYFUNCTION("""COMPUTED_VALUE"""),"56〜65歳") -> 56〜65歳 | E47: =IFERROR(__xludf.DUMMYFUNCTION("""COMPUTED_VALUE"""),"男性") -> 男性 | F47: =IFERROR(__xludf.DUMMYFUNCTION("""COMPUTED_VALUE"""),"900万円〜1,199万9,999円") -> 900万円〜1,199万9,999円 | G47: =IFERROR(__xludf.DUMMYFUNCTION("""COMPUTED_VALUE"""),"関東") -> 関東 | H47: =IFERROR(__xludf.DUMMYFUNCTION("""COMPUTED_VALUE"""),"毎日") -> 毎日 | I47: =IFERROR(__xludf.DUMMYFUNCTION("""COMPUTED_VALUE"""),"その他:") -> その他: | J47: =IFERROR(__xludf.DUMMYFUNCTION("""COMPUTED_VALUE"""),"Iインスタントコーヒー") -> Iインスタントコーヒー | K47: =IFERROR(__xludf.DUMMYFUNCTION("""COMPUTED_VALUE"""),"ほとんど飲まない") -> ほとんど飲まない | L47: =IFERROR(__xludf.DUMMYFUNCTION("""COMPUTED_VALUE"""),"その他：") -> その他： | M47: =IFERROR(__xludf.DUMMYFUNCTION("""COMPUTED_VALUE"""),"1年に数回スターバックスで抹茶ラテ") -> 1年に数回スターバックスで抹茶ラテ | N47: =IFERROR(__xludf.DUMMYFUNCTION("""COMPUTED_VALUE"""),"社交的な場や雰囲気の考慮") -> 社交的な場や雰囲気の考慮 | P47: =IFERROR(__xludf.DUMMYFUNCTION("""COMPUTED_VALUE"""),"自宅で") -> 自宅で | Q47: =IFERROR(__xludf.DUMMYFUNCTION("""COMPUTED_VALUE"""),"カフェ") -> カフェ | R47: =IFERROR(__xludf.DUMMYFUNCTION("""COMPUTED_VALUE"""),"月に数回") -> 月に数回 | S47: =IFERROR(__xludf.DUMMYFUNCTION("""COMPUTED_VALUE"""),"休憩・リラックスするため") -> 休憩・リラックスするため | U47: =IFERROR(__xludf.DUMMYFUNCTION("""COMPUTED_VALUE"""),"雰囲気・心地良さ") -> 雰囲気・心地良さ | W47: =IFERROR(__xludf.DUMMYFUNCTION("""COMPUTED_VALUE"""),"いいえ") -> いいえ | X47: =IFERROR(__xludf.DUMMYFUNCTION("""COMPUTED_VALUE"""),"はい（日本的）") -> はい（日本的） | Y47: =IFERROR(__xludf.DUMMYFUNCTION("""COMPUTED_VALUE"""),7.0) -> 7 | Z47: =IFERROR(__xludf.DUMMYFUNCTION("""COMPUTED_VALUE"""),7.0) -> 7 | AA47: =IFERROR(__xludf.DUMMYFUNCTION("""COMPUTED_VALUE"""),7.0) -> 7 | AB47: =IFERROR(__xludf.DUMMYFUNCTION("""COMPUTED_VALUE"""),"いいえ") -> いいえ | AK47: dWMpYWq | AL47: eq6gKzq | AM47: 46048.394 | AN47: 56-65 | AO47: Male | AP47: ¥9,000,000 – ¥11,999,999 | AQ47: Kanto | AR47: Daily | AS47: Other: | AT47: Instant Coffee | AU47: Rarely | AV47: Other: | AW47: I have a matcha latte at Starbucks a few times a year. | AX47: =IFERROR(__xludf.DUMMYFUNCTION("""COMPUTED_VALUE"""),"Social atmosphere") -> Social atmosphere | AZ47: =IFERROR(__xludf.DUMMYFUNCTION("""COMPUTED_VALUE"""),"At home") -> At home | BA47: Cafe | BB47: A few times a month | BC47: To relax or take a break | BE47: Atmosphere | BG47: No | BH47: Yes, Japanese | BI47: 7 | BJ47: 7 | BK47: 7 | BL47: No
A48: =IFERROR(__xludf.DUMMYFUNCTION("""COMPUTED_VALUE"""),"OD2gPRA") -> OD2gPRA | B48: =IFERROR(__xludf.DUMMYFUNCTION("""COMPUTED_VALUE"""),"kdy8J4J") -> kdy8J4J | C48: =IFERROR(__xludf.DUMMYFUNCTION("""COMPUTED_VALUE"""),46048.40122685185) -> 46048.401 | D48: =IFERROR(__xludf.DUMMYFUNCTION("""COMPUTED_VALUE"""),"46〜55歳") -> 46〜55歳 | E48: =IFERROR(__xludf.DUMMYFUNCTION("""COMPUTED_VALUE"""),"女性") -> 女性 | F48: =IFERROR(__xludf.DUMMYFUNCTION("""COMPUTED_VALUE"""),"900万円〜1,199万9,999円") -> 900万円〜1,199万9,999円 | G48: =IFERROR(__xludf.DUMMYFUNCTION("""COMPUTED_VALUE"""),"関東") -> 関東 | H48: =IFERROR(__xludf.DUMMYFUNCTION("""COMPUTED_VALUE"""),"毎日") -> 毎日 | I48: =IFERROR(__xludf.DUMMYFUNCTION("""COMPUTED_VALUE"""),"ラテ") -> ラテ | K48: =IFERROR(__xludf.DUMMYFUNCTION("""COMPUTED_VALUE"""),"ほとんど飲まない") -> ほとんど飲まない | L48: =IFERROR(__xludf.DUMMYFUNCTION("""COMPUTED_VALUE"""),"薄茶") -> 薄茶 | N48: =IFERROR(__xludf.DUMMYFUNCTION("""COMPUTED_VALUE"""),"味・風味, 習慣") -> 味・風味, 習慣 | P48: =IFERROR(__xludf.DUMMYFUNCTION("""COMPUTED_VALUE"""),"自宅で, コンビニ（セブンイレブン、ローソンなど）, カフェで") -> 自宅で, コンビニ（セブンイレブン、ローソンなど）, カフェで | R48: =IFERROR(__xludf.DUMMYFUNCTION("""COMPUTED_VALUE"""),"ほとんど行かない") -> ほとんど行かない | S48: =IFERROR(__xludf.DUMMYFUNCTION("""COMPUTED_VALUE"""),"休憩・リラックスするため") -> 休憩・リラックスするため | U48: =IFERROR(__xludf.DUMMYFUNCTION("""COMPUTED_VALUE"""),"雰囲気・心地良さ") -> 雰囲気・心地良さ | W48: =IFERROR(__xludf.DUMMYFUNCTION("""COMPUTED_VALUE"""),"いいえ") -> いいえ | X48: =IFERROR(__xludf.DUMMYFUNCTION("""COMPUTED_VALUE"""),"はい（日本的）") -> はい（日本的） | Y48: =IFERROR(__xludf.DUMMYFUNCTION("""COMPUTED_VALUE"""),6.0) -> 6 | Z48: =IFERROR(__xludf.DUMMYFUNCTION("""COMPUTED_VALUE"""),7.0) -> 7 | AA48: =IFERROR(__xludf.DUMMYFUNCTION("""COMPUTED_VALUE"""),7.0) -> 7 | AB48: =IFERROR(__xludf.DUMMYFUNCTION("""COMPUTED_VALUE"""),"いいえ") -> いいえ | AK48: OD2gPRA | AL48: kdy8J4J | AM48: 46048.401 | AN48: 46-55 | AO48: Female | AP48: ¥9,000,000 – ¥11,999,999 | AQ48: Kanto | AR48: Daily | AS48: Latte | AU48: Rarely | AV48: Usucha | AX48: =IFERROR(__xludf.DUMMYFUNCTION("""COMPUTED_VALUE"""),"Taste/Flavor, Routine/Ritual") -> Taste/Flavor, Routine/Ritual | AZ48: =IFERROR(__xludf.DUMMYFUNCTION("""COMPUTED_VALUE"""),"At home, From convenience stores (7-Eleven, Lawson, etc.), At cafés") -> At home, From convenience stores (7-Eleven, Lawson, etc.), At cafés | BB48: Rarely | BC48: To relax or take a break | BE48: Atmosphere | BG48: No | BH48: Yes, Japanese | BI48: 6 | BJ48: 7 | BK48: 7 | BL48: No
A49: =IFERROR(__xludf.DUMMYFUNCTION("""COMPUTED_VALUE"""),"eqJOWJo") -> eqJOWJo | B49: =IFERROR(__xludf.DUMMYFUNCTION("""COMPUTED_VALUE"""),"eq6VvEk") -> eq6VvEk | C49: =IFERROR(__xludf.DUMMYFUNCTION("""COMPUTED_VALUE"""),46049.31818287037) -> 46049.318 | D49: =IFERROR(__xludf.DUMMYFUNCTION("""COMPUTED_VALUE"""),"56〜65歳") -> 56〜65歳 | E49: =IFERROR(__xludf.DUMMYFUNCTION("""COMPUTED_VALUE"""),"女性") -> 女性 | F49: =IFERROR(__xludf.DUMMYFUNCTION("""COMPUTED_VALUE"""),"300万円〜599万9,999円") -> 300万円〜599万9,999円 | G49: =IFERROR(__xludf.DUMMYFUNCTION("""COMPUTED_VALUE"""),"関西") -> 関西 | H49: =IFERROR(__xludf.DUMMYFUNCTION("""COMPUTED_VALUE"""),"毎日") -> 毎日 | I49: =IFERROR(__xludf.DUMMYFUNCTION("""COMPUTED_VALUE"""),"ドリップコーヒー") -> ドリップコーヒー | K49: =IFERROR(__xludf.DUMMYFUNCTION("""COMPUTED_VALUE"""),"ほとんど飲まない") -> ほとんど飲まない | L49: =IFERROR(__xludf.DUMMYFUNCTION("""COMPUTED_VALUE"""),"その他：") -> その他： | M49: =IFERROR(__xludf.DUMMYFUNCTION("""COMPUTED_VALUE"""),"緑茶は食事でのむ") -> 緑茶は食事でのむ | N49: =IFERROR(__xludf.DUMMYFUNCTION("""COMPUTED_VALUE"""),"味・風味, 習慣") -> 味・風味, 習慣 | P49: =IFERROR(__xludf.DUMMYFUNCTION("""COMPUTED_VALUE"""),"カフェで, 自宅で") -> カフェで, 自宅で | R49: =IFERROR(__xludf.DUMMYFUNCTION("""COMPUTED_VALUE"""),"週に数回") -> 週に数回 | S49: =IFERROR(__xludf.DUMMYFUNCTION("""COMPUTED_VALUE"""),"休憩・リラックスするため") -> 休憩・リラックスするため | U49: =IFERROR(__xludf.DUMMYFUNCTION("""COMPUTED_VALUE"""),"雰囲気・心地良さ") -> 雰囲気・心地良さ | W49: =IFERROR(__xludf.DUMMYFUNCTION("""COMPUTED_VALUE"""),"いいえ") -> いいえ | X49: =IFERROR(__xludf.DUMMYFUNCTION("""COMPUTED_VALUE"""),"はい（日本的）") -> はい（日本的） | Y49: =IFERROR(__xludf.DUMMYFUNCTION("""COMPUTED_VALUE"""),4.0) -> 4 | Z49: =IFERROR(__xludf.DUMMYFUNCTION("""COMPUTED_VALUE"""),6.0) -> 6 | AA49: =IFERROR(__xludf.DUMMYFUNCTION("""COMPUTED_VALUE"""),5.0) -> 5 | AB49: =IFERROR(__xludf.DUMMYFUNCTION("""COMPUTED_VALUE"""),"いいえ") -> いいえ | AK49: eqJOWJo | AL49: eq6VvEk | AM49: 46049.318 | AN49: 56-65 | AO49: Female | AP49: ¥3,000,000 – ¥5,999,999 | AQ49: Kansai | AR49: Daily | AS49: Drip | AU49: Rarely | AV49: Other: | AW49: I drink green tea with meals. | AX49: =IFERROR(__xludf.DUMMYFUNCTION("""COMPUTED_VALUE"""),"Taste/Flavor, Routine/Ritual") -> Taste/Flavor, Routine/Ritual | AZ49: =IFERROR(__xludf.DUMMYFUNCTION("""COMPUTED_VALUE"""),"At cafés, At home") -> At cafés, At home | BB49: Several times a week | BC49: To relax or take a break | BE49: Atmosphere | BG49: No | BH49: Yes, Japanese | BI49: 4 | BJ49: 6 | BK49: 5 | BL49: No
A50: =IFERROR(__xludf.DUMMYFUNCTION("""COMPUTED_VALUE"""),"kd2VEeR") -> kd2VEeR | B50: =IFERROR(__xludf.DUMMYFUNCTION("""COMPUTED_VALUE"""),"xXdo7k9") -> xXdo7k9 | C50: =IFERROR(__xludf.DUMMYFUNCTION("""COMPUTED_VALUE"""),46057.57728009259) -> 46057.577 | D50: =IFERROR(__xludf.DUMMYFUNCTION("""COMPUTED_VALUE"""),"26〜35歳") -> 26〜35歳 | E50: =IFERROR(__xludf.DUMMYFUNCTION("""COMPUTED_VALUE"""),"男性") -> 男性 | F50: =IFERROR(__xludf.DUMMYFUNCTION("""COMPUTED_VALUE"""),"600万円〜899万9,999円") -> 600万円〜899万9,999円 | G50: =IFERROR(__xludf.DUMMYFUNCTION("""COMPUTED_VALUE"""),"関東") -> 関東 | H50: =IFERROR(__xludf.DUMMYFUNCTION("""COMPUTED_VALUE"""),"週に数回") -> 週に数回 | I50: =IFERROR(__xludf.DUMMYFUNCTION("""COMPUTED_VALUE"""),"ラテ") -> ラテ | K50: =IFERROR(__xludf.DUMMYFUNCTION("""COMPUTED_VALUE"""),"週に1回") -> 週に1回 | L50: =IFERROR(__xludf.DUMMYFUNCTION("""COMPUTED_VALUE"""),"抹茶は飲まない") -> 抹茶は飲まない | N50: =IFERROR(__xludf.DUMMYFUNCTION("""COMPUTED_VALUE"""),"ブランド・イメージ, 味・風味") -> ブランド・イメージ, 味・風味 | P50: =IFERROR(__xludf.DUMMYFUNCTION("""COMPUTED_VALUE"""),"カフェで") -> カフェで | R50: =IFERROR(__xludf.DUMMYFUNCTION("""COMPUTED_VALUE"""),"週に数回") -> 週に数回 | S50: =IFERROR(__xludf.DUMMYFUNCTION("""COMPUTED_VALUE"""),"勉強・仕事をするため") -> 勉強・仕事をするため | U50: =IFERROR(__xludf.DUMMYFUNCTION("""COMPUTED_VALUE"""),"雰囲気・心地良さ") -> 雰囲気・心地良さ | W50: =IFERROR(__xludf.DUMMYFUNCTION("""COMPUTED_VALUE"""),"はい（グローバル）") -> はい（グローバル） | X50: =IFERROR(__xludf.DUMMYFUNCTION("""COMPUTED_VALUE"""),"はい（グローバル）") -> はい（グローバル） | Y50: =IFERROR(__xludf.DUMMYFUNCTION("""COMPUTED_VALUE"""),6.0) -> 6 | Z50: =IFERROR(__xludf.DUMMYFUNCTION("""COMPUTED_VALUE"""),6.0) -> 6 | AA50: =IFERROR(__xludf.DUMMYFUNCTION("""COMPUTED_VALUE"""),3.0) -> 3 | AB50: =IFERROR(__xludf.DUMMYFUNCTION("""COMPUTED_VALUE"""),"いいえ") -> いいえ | AK50: kd2VEeR | AL50: xXdo7k9 | AM50: 46057.577 | AN50: 26-35 | AO50: Male | AP50: ¥6,000,000 – ¥8,999,999 | AQ50: Kanto | AR50: Several times a week | AS50: Latte | AU50: Once a week | AV50: I don’t drink matcha | AX50: =IFERROR(__xludf.DUMMYFUNCTION("""COMPUTED_VALUE"""),"Branding/Imagery, Taste/Flavor") -> Branding/Imagery, Taste/Flavor | AZ50: =IFERROR(__xludf.DUMMYFUNCTION("""COMPUTED_VALUE"""),"At cafés") -> At cafés | BB50: Several times a week | BC50: To study/work | BE50: Atmosphere | BG50: Yes, Global | BH50: Yes, Global | BI50: 6 | BJ50: 6 | BK50: 3 | BL50: No
A51: =IFERROR(__xludf.DUMMYFUNCTION("""COMPUTED_VALUE"""),"rjXV585") -> rjXV585 | B51: =IFERROR(__xludf.DUMMYFUNCTION("""COMPUTED_VALUE"""),"kdYoB5e") -> kdYoB5e | C51: =IFERROR(__xludf.DUMMYFUNCTION("""COMPUTED_VALUE"""),46060.13034722222) -> 46060.13 | D51: =IFERROR(__xludf.DUMMYFUNCTION("""COMPUTED_VALUE"""),"36〜45歳") -> 36〜45歳 | E51: =IFERROR(__xludf.DUMMYFUNCTION("""COMPUTED_VALUE"""),"女性") -> 女性 | F51: =IFERROR(__xludf.DUMMYFUNCTION("""COMPUTED_VALUE"""),"600万円〜899万9,999円") -> 600万円〜899万9,999円 | G51: =IFERROR(__xludf.DUMMYFUNCTION("""COMPUTED_VALUE"""),"関西") -> 関西 | H51: =IFERROR(__xludf.DUMMYFUNCTION("""COMPUTED_VALUE"""),"週に数回") -> 週に数回 | I51: =IFERROR(__xludf.DUMMYFUNCTION("""COMPUTED_VALUE"""),"ドリップコーヒー") -> ドリップコーヒー | K51: =IFERROR(__xludf.DUMMYFUNCTION("""COMPUTED_VALUE"""),"ほとんど飲まない") -> ほとんど飲まない | L51: =IFERROR(__xludf.DUMMYFUNCTION("""COMPUTED_VALUE"""),"抹茶ラテ") -> 抹茶ラテ | N51: =IFERROR(__xludf.DUMMYFUNCTION("""COMPUTED_VALUE"""),"その他：, 味・風味") -> その他：, 味・風味 | O51: =IFERROR(__xludf.DUMMYFUNCTION("""COMPUTED_VALUE"""),"気分によって変えます") -> 気分によって変えます | P51: =IFERROR(__xludf.DUMMYFUNCTION("""COMPUTED_VALUE"""),"自宅で, コンビニ（セブンイレブン、ローソンなど）") -> 自宅で, コンビニ（セブンイレブン、ローソンなど） | R51: =IFERROR(__xludf.DUMMYFUNCTION("""COMPUTED_VALUE"""),"月に数回") -> 月に数回 | S51: =IFERROR(__xludf.DUMMYFUNCTION("""COMPUTED_VALUE"""),"勉強・仕事をするため") -> 勉強・仕事をするため | U51: =IFERROR(__xludf.DUMMYFUNCTION("""COMPUTED_VALUE"""),"雰囲気・心地良さ") -> 雰囲気・心地良さ | W51: =IFERROR(__xludf.DUMMYFUNCTION("""COMPUTED_VALUE"""),"はい（グローバル）") -> はい（グローバル） | X51: =IFERROR(__xludf.DUMMYFUNCTION("""COMPUTED_VALUE"""),"はい（日本的）") -> はい（日本的） | Y51: =IFERROR(__xludf.DUMMYFUNCTION("""COMPUTED_VALUE"""),5.0) -> 5 | Z51: =IFERROR(__xludf.DUMMYFUNCTION("""COMPUTED_VALUE"""),5.0) -> 5 | AA51: =IFERROR(__xludf.DUMMYFUNCTION("""COMPUTED_VALUE"""),5.0) -> 5 | AB51: =IFERROR(__xludf.DUMMYFUNCTION("""COMPUTED_VALUE"""),"いいえ") -> いいえ | AK51: rjXV585 | AL51: kdYoB5e | AM51: 46060.13 | AN51: 36-45 | AO51: Female | AP51: ¥6,000,000 – ¥8,999,999 | AQ51: Kansai | AR51: Several times a week | AS51: Drip | AU51: Rarely | AV51: Matcha Latte | AX51: =IFERROR(__xludf.DUMMYFUNCTION("""COMPUTED_VALUE"""),"Other:, Taste/Flavor") -> Other:, Taste/Flavor | AY51: I change it depending on my mood. | AZ51: =IFERROR(__xludf.DUMMYFUNCTION("""COMPUTED_VALUE"""),"At home, From convenience stores (7-Eleven, Lawson, etc.)") -> At home, From convenience stores (7-Eleven, Lawson, etc.) | BB51: A few times a month | BC51: To study/work | BE51: Atmosphere | BG51: Yes, Global | BH51: Yes, Japanese | BI51: 5 | BJ51: 5 | BK51: 5 | BL51: No
A52: =IFERROR(__xludf.DUMMYFUNCTION("""COMPUTED_VALUE"""),"9qe69rG") -> 9qe69rG | B52: =IFERROR(__xludf.DUMMYFUNCTION("""COMPUTED_VALUE"""),"gD52JXN") -> gD52JXN | C52: =IFERROR(__xludf.DUMMYFUNCTION("""COMPUTED_VALUE"""),46061.1175) -> 46061.118 | D52: =IFERROR(__xludf.DUMMYFUNCTION("""COMPUTED_VALUE"""),"65歳以上") -> 65歳以上 | E52: =IFERROR(__xludf.DUMMYFUNCTION("""COMPUTED_VALUE"""),"男性") -> 男性 | F52: =IFERROR(__xludf.DUMMYFUNCTION("""COMPUTED_VALUE"""),"300万円〜599万9,999円") -> 300万円〜599万9,999円 | G52: =IFERROR(__xludf.DUMMYFUNCTION("""COMPUTED_VALUE"""),"関西") -> 関西 | H52: =IFERROR(__xludf.DUMMYFUNCTION("""COMPUTED_VALUE"""),"毎日") -> 毎日 | I52: =IFERROR(__xludf.DUMMYFUNCTION("""COMPUTED_VALUE"""),"ドリップコーヒー") -> ドリップコーヒー | K52: =IFERROR(__xludf.DUMMYFUNCTION("""COMPUTED_VALUE"""),"ほとんど飲まない") -> ほとんど飲まない | L52: =IFERROR(__xludf.DUMMYFUNCTION("""COMPUTED_VALUE"""),"その他：") -> その他： | M52: =IFERROR(__xludf.DUMMYFUNCTION("""COMPUTED_VALUE"""),"煎茶") -> 煎茶 | N52: =IFERROR(__xludf.DUMMYFUNCTION("""COMPUTED_VALUE"""),"習慣, ブランド・イメージ") -> 習慣, ブランド・イメージ | P52: =IFERROR(__xludf.DUMMYFUNCTION("""COMPUTED_VALUE"""),"自宅で") -> 自宅で | R52: =IFERROR(__xludf.DUMMYFUNCTION("""COMPUTED_VALUE"""),"ほとんど行かない") -> ほとんど行かない | S52: =IFERROR(__xludf.DUMMYFUNCTION("""COMPUTED_VALUE"""),"その他：") -> その他： | T52: =IFERROR(__xludf.DUMMYFUNCTION("""COMPUTED_VALUE"""),"久ししぶりに外出したとき") -> 久ししぶりに外出したとき | V52: =IFERROR(__xludf.DUMMYFUNCTION("""COMPUTED_VALUE"""),"アメリカにいた時 よく飲んだので") -> アメリカにいた時 よく飲んだので | W52: =IFERROR(__xludf.DUMMYFUNCTION("""COMPUTED_VALUE"""),"はい（西洋的）") -> はい（西洋的） | X52: =IFERROR(__xludf.DUMMYFUNCTION("""COMPUTED_VALUE"""),"はい（日本的）") -> はい（日本的） | Y52: =IFERROR(__xludf.DUMMYFUNCTION("""COMPUTED_VALUE"""),5.0) -> 5 | Z52: =IFERROR(__xludf.DUMMYFUNCTION("""COMPUTED_VALUE"""),6.0) -> 6 | AA52: =IFERROR(__xludf.DUMMYFUNCTION("""COMPUTED_VALUE"""),2.0) -> 2 | AB52: =IFERROR(__xludf.DUMMYFUNCTION("""COMPUTED_VALUE"""),"いいえ") -> いいえ | AK52: 9qe69rG | AL52: gD52JXN | AM52: 46061.118 | AN52: 65+ | AO52: Male | AP52: ¥3,000,000 – ¥5,999,999 | AQ52: Kansai | AR52: Daily | AS52: Drip | AU52: Rarely | AV52: Other: | AW52: Sencha | AX52: =IFERROR(__xludf.DUMMYFUNCTION("""COMPUTED_VALUE"""),"Routine/Ritual, Branding/Imagery") -> Routine/Ritual, Branding/Imagery | AZ52: =IFERROR(__xludf.DUMMYFUNCTION("""COMPUTED_VALUE"""),"At home") -> At home | BB52: Rarely | BC52: Other: | BD52: When I went out after a long time. | BF52: Because I drank it often when I was in the U.S. | BG52: Yes, Western | BH52: Yes, Japanese | BI52: 5 | BJ52: 6 | BK52: 2 | BL52: No
A53: =IFERROR(__xludf.DUMMYFUNCTION("""COMPUTED_VALUE"""),"dW7kDgN") -> dW7kDgN | B53: =IFERROR(__xludf.DUMMYFUNCTION("""COMPUTED_VALUE"""),"5Bd6vqb") -> 5Bd6vqb | C53: =IFERROR(__xludf.DUMMYFUNCTION("""COMPUTED_VALUE"""),46062.14965277778) -> 46062.15 | D53: =IFERROR(__xludf.DUMMYFUNCTION("""COMPUTED_VALUE"""),"36〜45歳") -> 36〜45歳 | E53: =IFERROR(__xludf.DUMMYFUNCTION("""COMPUTED_VALUE"""),"女性") -> 女性 | F53: =IFERROR(__xludf.DUMMYFUNCTION("""COMPUTED_VALUE"""),"600万円〜899万9,999円") -> 600万円〜899万9,999円 | G53: =IFERROR(__xludf.DUMMYFUNCTION("""COMPUTED_VALUE"""),"関東") -> 関東 | H53: =IFERROR(__xludf.DUMMYFUNCTION("""COMPUTED_VALUE"""),"週に数回") -> 週に数回 | I53: =IFERROR(__xludf.DUMMYFUNCTION("""COMPUTED_VALUE"""),"ラテ") -> ラテ | K53: =IFERROR(__xludf.DUMMYFUNCTION("""COMPUTED_VALUE"""),"ほとんど飲まない") -> ほとんど飲まない | L53: =IFERROR(__xludf.DUMMYFUNCTION("""COMPUTED_VALUE"""),"抹茶ラテ") -> 抹茶ラテ | N53: =IFERROR(__xludf.DUMMYFUNCTION("""COMPUTED_VALUE"""),"味・風味, 価格") -> 味・風味, 価格 | P53: =IFERROR(__xludf.DUMMYFUNCTION("""COMPUTED_VALUE"""),"カフェで, その他：") -> カフェで, その他： | Q53: =IFERROR(__xludf.DUMMYFUNCTION("""COMPUTED_VALUE"""),"抹茶はイベントで飲むくらい") -> 抹茶はイベントで飲むくらい | R53: =IFERROR(__xludf.DUMMYFUNCTION("""COMPUTED_VALUE"""),"週に1回") -> 週に1回 | S53: =IFERROR(__xludf.DUMMYFUNCTION("""COMPUTED_VALUE"""),"その他：") -> その他： | T53: =IFERROR(__xludf.DUMMYFUNCTION("""COMPUTED_VALUE"""),"待ち時間") -> 待ち時間 | U53: =IFERROR(__xludf.DUMMYFUNCTION("""COMPUTED_VALUE"""),"雰囲気・心地良さ") -> 雰囲気・心地良さ | W53: =IFERROR(__xludf.DUMMYFUNCTION("""COMPUTED_VALUE"""),"いいえ") -> いいえ | X53: =IFERROR(__xludf.DUMMYFUNCTION("""COMPUTED_VALUE"""),"はい（日本的）") -> はい（日本的） | Y53: =IFERROR(__xludf.DUMMYFUNCTION("""COMPUTED_VALUE"""),4.0) -> 4 | Z53: =IFERROR(__xludf.DUMMYFUNCTION("""COMPUTED_VALUE"""),7.0) -> 7 | AA53: =IFERROR(__xludf.DUMMYFUNCTION("""COMPUTED_VALUE"""),5.0) -> 5 | AB53: =IFERROR(__xludf.DUMMYFUNCTION("""COMPUTED_VALUE"""),"いいえ") -> いいえ | AK53: dW7kDgN | AL53: 5Bd6vqb | AM53: 46062.15 | AN53: 36-45 | AO53: Female | AP53: ¥6,000,000 – ¥8,999,999 | AQ53: Kanto | AR53: Several times a week | AS53: Latte | AU53: Rarely | AV53: Matcha Latte | AX53: =IFERROR(__xludf.DUMMYFUNCTION("""COMPUTED_VALUE"""),"Taste/Flavor, Price") -> Taste/Flavor, Price | AZ53: =IFERROR(__xludf.DUMMYFUNCTION("""COMPUTED_VALUE"""),"At cafés, Other:") -> At cafés, Other: | BA53: I only drink matcha at events | BB53: Once a week | BC53: Other: | BD53: Waiting time | BE53: Atmosphere | BG53: No | BH53: Yes, Japanese | BI53: 4 | BJ53: 7 | BK53: 5 | BL53: No
A54: =IFERROR(__xludf.DUMMYFUNCTION("""COMPUTED_VALUE"""),"9qeoEKV") -> 9qeoEKV | B54: =IFERROR(__xludf.DUMMYFUNCTION("""COMPUTED_VALUE"""),"pbLjWk1") -> pbLjWk1 | C54: =IFERROR(__xludf.DUMMYFUNCTION("""COMPUTED_VALUE"""),46062.150925925926) -> 46062.151 | D54: =IFERROR(__xludf.DUMMYFUNCTION("""COMPUTED_VALUE"""),"46〜55歳") -> 46〜55歳 | E54: =IFERROR(__xludf.DUMMYFUNCTION("""COMPUTED_VALUE"""),"女性") -> 女性 | F54: =IFERROR(__xludf.DUMMYFUNCTION("""COMPUTED_VALUE"""),"1,200万円以上") -> 1,200万円以上 | G54: =IFERROR(__xludf.DUMMYFUNCTION("""COMPUTED_VALUE"""),"関東") -> 関東 | H54: =IFERROR(__xludf.DUMMYFUNCTION("""COMPUTED_VALUE"""),"週に数回") -> 週に数回 | I54: =IFERROR(__xludf.DUMMYFUNCTION("""COMPUTED_VALUE"""),"ラテ") -> ラテ | K54: =IFERROR(__xludf.DUMMYFUNCTION("""COMPUTED_VALUE"""),"ほとんど飲まない") -> ほとんど飲まない | L54: =IFERROR(__xludf.DUMMYFUNCTION("""COMPUTED_VALUE"""),"濃茶") -> 濃茶 | N54: =IFERROR(__xludf.DUMMYFUNCTION("""COMPUTED_VALUE"""),"味・風味") -> 味・風味 | P54: =IFERROR(__xludf.DUMMYFUNCTION("""COMPUTED_VALUE"""),"自宅で, カフェで, コンビニ（セブンイレブン、ローソンなど）") -> 自宅で, カフェで, コンビニ（セブンイレブン、ローソンなど） | R54: =IFERROR(__xludf.DUMMYFUNCTION("""COMPUTED_VALUE"""),"月に数回") -> 月に数回 | S54: =IFERROR(__xludf.DUMMYFUNCTION("""COMPUTED_VALUE"""),"勉強・仕事をするため") -> 勉強・仕事をするため | U54: =IFERROR(__xludf.DUMMYFUNCTION("""COMPUTED_VALUE"""),"雰囲気・心地良さ") -> 雰囲気・心地良さ | W54: =IFERROR(__xludf.DUMMYFUNCTION("""COMPUTED_VALUE"""),"わからない") -> わからない | X54: =IFERROR(__xludf.DUMMYFUNCTION("""COMPUTED_VALUE"""),"はい（日本的）") -> はい（日本的） | Y54: =IFERROR(__xludf.DUMMYFUNCTION("""COMPUTED_VALUE"""),7.0) -> 7 | Z54: =IFERROR(__xludf.DUMMYFUNCTION("""COMPUTED_VALUE"""),5.0) -> 5 | AA54: =IFERROR(__xludf.DUMMYFUNCTION("""COMPUTED_VALUE"""),5.0) -> 5 | AB54: =IFERROR(__xludf.DUMMYFUNCTION("""COMPUTED_VALUE"""),"いいえ") -> いいえ | AK54: 9qeoEKV | AL54: pbLjWk1 | AM54: 46062.151 | AN54: 46-55 | AO54: Female | AP54: ¥12,000,000 or more | AQ54: Kanto | AR54: Several times a week | AS54: Latte | AU54: Rarely | AV54: Koicha | AX54: =IFERROR(__xludf.DUMMYFUNCTION("""COMPUTED_VALUE"""),"Taste/Flavor") -> Taste/Flavor | AZ54: =IFERROR(__xludf.DUMMYFUNCTION("""COMPUTED_VALUE"""),"At home, At cafés, From convenience stores (7-Eleven, Lawson, etc.)") -> At home, At cafés, From convenience stores (7-Eleven, Lawson, etc.) | BB54: A few times a month | BC54: To study/work | BE54: Atmosphere | BG54: Unsure | BH54: Yes, Japanese | BI54: 7 | BJ54: 5 | BK54: 5 | BL54: No
A55: =IFERROR(__xludf.DUMMYFUNCTION("""COMPUTED_VALUE"""),"2E2Dxjp") -> 2E2Dxjp | B55: =IFERROR(__xludf.DUMMYFUNCTION("""COMPUTED_VALUE"""),"rjlNLpR") -> rjlNLpR | C55: =IFERROR(__xludf.DUMMYFUNCTION("""COMPUTED_VALUE"""),46062.15195601852) -> 46062.152 | D55: =IFERROR(__xludf.DUMMYFUNCTION("""COMPUTED_VALUE"""),"18〜25歳") -> 18〜25歳 | E55: =IFERROR(__xludf.DUMMYFUNCTION("""COMPUTED_VALUE"""),"男性") -> 男性 | F55: =IFERROR(__xludf.DUMMYFUNCTION("""COMPUTED_VALUE"""),"1,200万円以上") -> 1,200万円以上 | G55: =IFERROR(__xludf.DUMMYFUNCTION("""COMPUTED_VALUE"""),"関東") -> 関東 | H55: =IFERROR(__xludf.DUMMYFUNCTION("""COMPUTED_VALUE"""),"週に数回") -> 週に数回 | I55: =IFERROR(__xludf.DUMMYFUNCTION("""COMPUTED_VALUE"""),"その他:") -> その他: | J55: =IFERROR(__xludf.DUMMYFUNCTION("""COMPUTED_VALUE"""),"bottled") -> bottled | K55: =IFERROR(__xludf.DUMMYFUNCTION("""COMPUTED_VALUE"""),"まったく飲まない") -> まったく飲まない | N55: =IFERROR(__xludf.DUMMYFUNCTION("""COMPUTED_VALUE"""),"その他：") -> その他： | O55: =IFERROR(__xludf.DUMMYFUNCTION("""COMPUTED_VALUE"""),"availability") -> availability | P55: =IFERROR(__xludf.DUMMYFUNCTION("""COMPUTED_VALUE"""),"コンビニ（セブンイレブン、ローソンなど）") -> コンビニ（セブンイレブン、ローソンなど） | R55: =IFERROR(__xludf.DUMMYFUNCTION("""COMPUTED_VALUE"""),"月に数回") -> 月に数回 | S55: =IFERROR(__xludf.DUMMYFUNCTION("""COMPUTED_VALUE"""),"友人と会うため") -> 友人と会うため | U55: =IFERROR(__xludf.DUMMYFUNCTION("""COMPUTED_VALUE"""),"雰囲気・心地良さ") -> 雰囲気・心地良さ | W55: =IFERROR(__xludf.DUMMYFUNCTION("""COMPUTED_VALUE"""),"いいえ") -> いいえ | X55: =IFERROR(__xludf.DUMMYFUNCTION("""COMPUTED_VALUE"""),"はい（日本的）") -> はい（日本的） | Y55: =IFERROR(__xludf.DUMMYFUNCTION("""COMPUTED_VALUE"""),5.0) -> 5 | Z55: =IFERROR(__xludf.DUMMYFUNCTION("""COMPUTED_VALUE"""),6.0) -> 6 | AA55: =IFERROR(__xludf.DUMMYFUNCTION("""COMPUTED_VALUE"""),7.0) -> 7 | AB55: =IFERROR(__xludf.DUMMYFUNCTION("""COMPUTED_VALUE"""),"いいえ") -> いいえ | AK55: 2E2Dxjp | AL55: rjlNLpR | AM55: 46062.152 | AN55: 18-25 | AO55: Male | AP55: ¥12,000,000 or more | AQ55: Kanto | AR55: Several times a week | AS55: Other: | AT55: Bottled | AU55: Never | AX55: =IFERROR(__xludf.DUMMYFUNCTION("""COMPUTED_VALUE"""),"Other:") -> Other: | AY55: Availability | AZ55: =IFERROR(__xludf.DUMMYFUNCTION("""COMPUTED_VALUE"""),"From convenience stores (7-Eleven, Lawson, etc.)") -> From convenience stores (7-Eleven, Lawson, etc.) | BB55: A few times a month | BC55: To meet friends | BE55: Atmosphere | BG55: No | BH55: Yes, Japanese | BI55: 5 | BJ55: 6 | BK55: 7 | BL55: No
A56: =IFERROR(__xludf.DUMMYFUNCTION("""COMPUTED_VALUE"""),"VLr41e6") -> VLr41e6 | B56: =IFERROR(__xludf.DUMMYFUNCTION("""COMPUTED_VALUE"""),"xXdkPVk") -> xXdkPVk | C56: =IFERROR(__xludf.DUMMYFUNCTION("""COMPUTED_VALUE"""),46062.15582175926) -> 46062.156 | D56: =IFERROR(__xludf.DUMMYFUNCTION("""COMPUTED_VALUE"""),"36〜45歳") -> 36〜45歳 | E56: =IFERROR(__xludf.DUMMYFUNCTION("""COMPUTED_VALUE"""),"男性") -> 男性 | F56: =IFERROR(__xludf.DUMMYFUNCTION("""COMPUTED_VALUE"""),"1,200万円以上") -> 1,200万円以上 | G56: =IFERROR(__xludf.DUMMYFUNCTION("""COMPUTED_VALUE"""),"関西") -> 関西 | H56: =IFERROR(__xludf.DUMMYFUNCTION("""COMPUTED_VALUE"""),"毎日") -> 毎日 | I56: =IFERROR(__xludf.DUMMYFUNCTION("""COMPUTED_VALUE"""),"ドリップコーヒー") -> ドリップコーヒー | K56: =IFERROR(__xludf.DUMMYFUNCTION("""COMPUTED_VALUE"""),"まったく飲まない") -> まったく飲まない | N56: =IFERROR(__xludf.DUMMYFUNCTION("""COMPUTED_VALUE"""),"エナジー／カフェイン, 味・風味") -> エナジー／カフェイン, 味・風味 | P56: =IFERROR(__xludf.DUMMYFUNCTION("""COMPUTED_VALUE"""),"コンビニ（セブンイレブン、ローソンなど）, 自宅で, カフェで") -> コンビニ（セブンイレブン、ローソンなど）, 自宅で, カフェで | R56: =IFERROR(__xludf.DUMMYFUNCTION("""COMPUTED_VALUE"""),"週に1回") -> 週に1回 | S56: =IFERROR(__xludf.DUMMYFUNCTION("""COMPUTED_VALUE"""),"勉強・仕事をするため") -> 勉強・仕事をするため | U56: =IFERROR(__xludf.DUMMYFUNCTION("""COMPUTED_VALUE"""),"雰囲気・心地良さ") -> 雰囲気・心地良さ | W56: =IFERROR(__xludf.DUMMYFUNCTION("""COMPUTED_VALUE"""),"はい（グローバル）") -> はい（グローバル） | X56: =IFERROR(__xludf.DUMMYFUNCTION("""COMPUTED_VALUE"""),"はい（日本的）") -> はい（日本的） | Y56: =IFERROR(__xludf.DUMMYFUNCTION("""COMPUTED_VALUE"""),6.0) -> 6 | Z56: =IFERROR(__xludf.DUMMYFUNCTION("""COMPUTED_VALUE"""),4.0) -> 4 | AA56: =IFERROR(__xludf.DUMMYFUNCTION("""COMPUTED_VALUE"""),7.0) -> 7 | AB56: =IFERROR(__xludf.DUMMYFUNCTION("""COMPUTED_VALUE"""),"いいえ") -> いいえ | AK56: VLr41e6 | AL56: xXdkPVk | AM56: 46062.156 | AN56: 36-45 | AO56: Male | AP56: ¥12,000,000 or more | AQ56: Kansai | AR56: Daily | AS56: Drip | AU56: Never | AX56: =IFERROR(__xludf.DUMMYFUNCTION("""COMPUTED_VALUE"""),"Energy boost/Caffeine, Taste/Flavor") -> Energy boost/Caffeine, Taste/Flavor | AZ56: =IFERROR(__xludf.DUMMYFUNCTION("""COMPUTED_VALUE"""),"From convenience stores (7-Eleven, Lawson, etc.), At home, At cafés") -> From convenience stores (7-Eleven, Lawson, etc.), At home, At cafés | BB56: Once a week | BC56: To study/work | BE56: Atmosphere | BG56: Yes, Global | BH56: Yes, Japanese | BI56: 6 | BJ56: 4 | BK56: 7 | BL56: No
A57: =IFERROR(__xludf.DUMMYFUNCTION("""COMPUTED_VALUE"""),"QKGO82Y") -> QKGO82Y | B57: =IFERROR(__xludf.DUMMYFUNCTION("""COMPUTED_VALUE"""),"2E4qJge") -> 2E4qJge | C57: =IFERROR(__xludf.DUMMYFUNCTION("""COMPUTED_VALUE"""),46062.16138888889) -> 46062.161 | D57: =IFERROR(__xludf.DUMMYFUNCTION("""COMPUTED_VALUE"""),"36〜45歳") -> 36〜45歳 | E57: =IFERROR(__xludf.DUMMYFUNCTION("""COMPUTED_VALUE"""),"男性") -> 男性 | F57: =IFERROR(__xludf.DUMMYFUNCTION("""COMPUTED_VALUE"""),"1,200万円以上") -> 1,200万円以上 | G57: =IFERROR(__xludf.DUMMYFUNCTION("""COMPUTED_VALUE"""),"関東") -> 関東 | H57: =IFERROR(__xludf.DUMMYFUNCTION("""COMPUTED_VALUE"""),"毎日") -> 毎日 | I57: =IFERROR(__xludf.DUMMYFUNCTION("""COMPUTED_VALUE"""),"ドリップコーヒー") -> ドリップコーヒー | K57: =IFERROR(__xludf.DUMMYFUNCTION("""COMPUTED_VALUE"""),"まったく飲まない") -> まったく飲まない | N57: =IFERROR(__xludf.DUMMYFUNCTION("""COMPUTED_VALUE"""),"味・風味") -> 味・風味 | P57: =IFERROR(__xludf.DUMMYFUNCTION("""COMPUTED_VALUE"""),"自宅で, コンビニ（セブンイレブン、ローソンなど）") -> 自宅で, コンビニ（セブンイレブン、ローソンなど） | R57: =IFERROR(__xludf.DUMMYFUNCTION("""COMPUTED_VALUE"""),"ほとんど行かない") -> ほとんど行かない | S57: =IFERROR(__xludf.DUMMYFUNCTION("""COMPUTED_VALUE"""),"友人と会うため") -> 友人と会うため | U57: =IFERROR(__xludf.DUMMYFUNCTION("""COMPUTED_VALUE"""),"雰囲気・心地良さ") -> 雰囲気・心地良さ | W57: =IFERROR(__xludf.DUMMYFUNCTION("""COMPUTED_VALUE"""),"いいえ") -> いいえ | X57: =IFERROR(__xludf.DUMMYFUNCTION("""COMPUTED_VALUE"""),"はい（日本的）") -> はい（日本的） | Y57: =IFERROR(__xludf.DUMMYFUNCTION("""COMPUTED_VALUE"""),5.0) -> 5 | Z57: =IFERROR(__xludf.DUMMYFUNCTION("""COMPUTED_VALUE"""),7.0) -> 7 | AA57: =IFERROR(__xludf.DUMMYFUNCTION("""COMPUTED_VALUE"""),2.0) -> 2 | AB57: =IFERROR(__xludf.DUMMYFUNCTION("""COMPUTED_VALUE"""),"いいえ") -> いいえ | AK57: QKGO82Y | AL57: 2E4qJge | AM57: 46062.161 | AN57: 36-45 | AO57: Male | AP57: ¥12,000,000 or more | AQ57: Kanto | AR57: Daily | AS57: Drip | AU57: Never | AX57: =IFERROR(__xludf.DUMMYFUNCTION("""COMPUTED_VALUE"""),"Taste/Flavor") -> Taste/Flavor | AZ57: =IFERROR(__xludf.DUMMYFUNCTION("""COMPUTED_VALUE"""),"At home, From convenience stores (7-Eleven, Lawson, etc.)") -> At home, From convenience stores (7-Eleven, Lawson, etc.) | BB57: Rarely | BC57: To meet friends | BE57: Atmosphere | BG57: No | BH57: Yes, Japanese | BI57: 5 | BJ57: 7 | BK57: 2 | BL57: No
A58: =IFERROR(__xludf.DUMMYFUNCTION("""COMPUTED_VALUE"""),"D4LZPPp") -> D4LZPPp | B58: =IFERROR(__xludf.DUMMYFUNCTION("""COMPUTED_VALUE"""),"ODApo5k") -> ODApo5k | C58: =IFERROR(__xludf.DUMMYFUNCTION("""COMPUTED_VALUE"""),46062.21375) -> 46062.214 | D58: =IFERROR(__xludf.DUMMYFUNCTION("""COMPUTED_VALUE"""),"26〜35歳") -> 26〜35歳 | E58: =IFERROR(__xludf.DUMMYFUNCTION("""COMPUTED_VALUE"""),"男性") -> 男性 | F58: =IFERROR(__xludf.DUMMYFUNCTION("""COMPUTED_VALUE"""),"300万円〜599万9,999円") -> 300万円〜599万9,999円 | G58: =IFERROR(__xludf.DUMMYFUNCTION("""COMPUTED_VALUE"""),"関東") -> 関東 | H58: =IFERROR(__xludf.DUMMYFUNCTION("""COMPUTED_VALUE"""),"毎日") -> 毎日 | I58: =IFERROR(__xludf.DUMMYFUNCTION("""COMPUTED_VALUE"""),"ドリップコーヒー") -> ドリップコーヒー | K58: =IFERROR(__xludf.DUMMYFUNCTION("""COMPUTED_VALUE"""),"まったく飲まない") -> まったく飲まない | N58: =IFERROR(__xludf.DUMMYFUNCTION("""COMPUTED_VALUE"""),"習慣") -> 習慣 | P58: =IFERROR(__xludf.DUMMYFUNCTION("""COMPUTED_VALUE"""),"自宅で") -> 自宅で | R58: =IFERROR(__xludf.DUMMYFUNCTION("""COMPUTED_VALUE"""),"月に数回") -> 月に数回 | S58: =IFERROR(__xludf.DUMMYFUNCTION("""COMPUTED_VALUE"""),"勉強・仕事をするため") -> 勉強・仕事をするため | U58: =IFERROR(__xludf.DUMMYFUNCTION("""COMPUTED_VALUE"""),"雰囲気・心地良さ") -> 雰囲気・心地良さ | W58: =IFERROR(__xludf.DUMMYFUNCTION("""COMPUTED_VALUE"""),"いいえ") -> いいえ | X58: =IFERROR(__xludf.DUMMYFUNCTION("""COMPUTED_VALUE"""),"はい（日本的）") -> はい（日本的） | Y58: =IFERROR(__xludf.DUMMYFUNCTION("""COMPUTED_VALUE"""),6.0) -> 6 | Z58: =IFERROR(__xludf.DUMMYFUNCTION("""COMPUTED_VALUE"""),6.0) -> 6 | AA58: =IFERROR(__xludf.DUMMYFUNCTION("""COMPUTED_VALUE"""),4.0) -> 4 | AB58: =IFERROR(__xludf.DUMMYFUNCTION("""COMPUTED_VALUE"""),"いいえ") -> いいえ | AK58: D4LZPPp | AL58: ODApo5k | AM58: 46062.214 | AN58: 26-35 | AO58: Male | AP58: ¥3,000,000 – ¥5,999,999 | AQ58: Kanto | AR58: Daily | AS58: Drip | AU58: Never | AX58: =IFERROR(__xludf.DUMMYFUNCTION("""COMPUTED_VALUE"""),"Routine/Ritual") -> Routine/Ritual | AZ58: =IFERROR(__xludf.DUMMYFUNCTION("""COMPUTED_VALUE"""),"At home") -> At home | BB58: A few times a month | BC58: To study/work | BE58: Atmosphere | BG58: No | BH58: Yes, Japanese | BI58: 6 | BJ58: 6 | BK58: 4 | BL58: No
A59: =IFERROR(__xludf.DUMMYFUNCTION("""COMPUTED_VALUE"""),"obJkr8X") -> obJkr8X | B59: =IFERROR(__xludf.DUMMYFUNCTION("""COMPUTED_VALUE"""),"gD5yxa1") -> gD5yxa1 | C59: =IFERROR(__xludf.DUMMYFUNCTION("""COMPUTED_VALUE"""),46062.278819444444) -> 46062.279 | D59: =IFERROR(__xludf.DUMMYFUNCTION("""COMPUTED_VALUE"""),"26〜35歳") -> 26〜35歳 | E59: =IFERROR(__xludf.DUMMYFUNCTION("""COMPUTED_VALUE"""),"男性") -> 男性 | F59: =IFERROR(__xludf.DUMMYFUNCTION("""COMPUTED_VALUE"""),"900万円〜1,199万9,999円") -> 900万円〜1,199万9,999円 | G59: =IFERROR(__xludf.DUMMYFUNCTION("""COMPUTED_VALUE"""),"関東") -> 関東 | H59: =IFERROR(__xludf.DUMMYFUNCTION("""COMPUTED_VALUE"""),"週に1回") -> 週に1回 | I59: =IFERROR(__xludf.DUMMYFUNCTION("""COMPUTED_VALUE"""),"ラテ") -> ラテ | K59: =IFERROR(__xludf.DUMMYFUNCTION("""COMPUTED_VALUE"""),"週に1回") -> 週に1回 | L59: =IFERROR(__xludf.DUMMYFUNCTION("""COMPUTED_VALUE"""),"薄茶") -> 薄茶 | N59: =IFERROR(__xludf.DUMMYFUNCTION("""COMPUTED_VALUE"""),"習慣, 味・風味") -> 習慣, 味・風味 | P59: =IFERROR(__xludf.DUMMYFUNCTION("""COMPUTED_VALUE"""),"自宅で, コンビニ（セブンイレブン、ローソンなど）") -> 自宅で, コンビニ（セブンイレブン、ローソンなど） | R59: =IFERROR(__xludf.DUMMYFUNCTION("""COMPUTED_VALUE"""),"月に数回") -> 月に数回 | S59: =IFERROR(__xludf.DUMMYFUNCTION("""COMPUTED_VALUE"""),"その他：") -> その他： | T59: =IFERROR(__xludf.DUMMYFUNCTION("""COMPUTED_VALUE"""),"次の予定までの時間調整のため") -> 次の予定までの時間調整のため | U59: =IFERROR(__xludf.DUMMYFUNCTION("""COMPUTED_VALUE"""),"雰囲気・心地良さ") -> 雰囲気・心地良さ | W59: =IFERROR(__xludf.DUMMYFUNCTION("""COMPUTED_VALUE"""),"いいえ") -> いいえ | X59: =IFERROR(__xludf.DUMMYFUNCTION("""COMPUTED_VALUE"""),"はい（日本的）") -> はい（日本的） | Y59: =IFERROR(__xludf.DUMMYFUNCTION("""COMPUTED_VALUE"""),3.0) -> 3 | Z59: =IFERROR(__xludf.DUMMYFUNCTION("""COMPUTED_VALUE"""),6.0) -> 6 | AA59: =IFERROR(__xludf.DUMMYFUNCTION("""COMPUTED_VALUE"""),2.0) -> 2 | AB59: =IFERROR(__xludf.DUMMYFUNCTION("""COMPUTED_VALUE"""),"はい") -> はい | AK59: obJkr8X | AL59: gD5yxa1 | AM59: 46062.279 | AN59: 26-35 | AO59: Male | AP59: ¥9,000,000 – ¥11,999,999 | AQ59: Kanto | AR59: Once a week | AS59: Latte | AU59: Once a week | AV59: Usucha | AX59: =IFERROR(__xludf.DUMMYFUNCTION("""COMPUTED_VALUE"""),"Routine/Ritual, Taste/Flavor") -> Routine/Ritual, Taste/Flavor | AZ59: =IFERROR(__xludf.DUMMYFUNCTION("""COMPUTED_VALUE"""),"At home, From convenience stores (7-Eleven, Lawson, etc.)") -> At home, From convenience stores (7-Eleven, Lawson, etc.) | BB59: A few times a month | BC59: Other: | BD59: To kill time until my next appointment | BE59: Atmosphere | BG59: No | BH59: Yes, Japanese | BI59: 3 | BJ59: 6 | BK59: 2 | BL59: Yes
A60: =IFERROR(__xludf.DUMMYFUNCTION("""COMPUTED_VALUE"""),"rjXvy2L") -> rjXvy2L | B60: =IFERROR(__xludf.DUMMYFUNCTION("""COMPUTED_VALUE"""),"9qdLg2Q") -> 9qdLg2Q | C60: =IFERROR(__xludf.DUMMYFUNCTION("""COMPUTED_VALUE"""),46062.281539351854) -> 46062.282 | D60: =IFERROR(__xludf.DUMMYFUNCTION("""COMPUTED_VALUE"""),"46〜55歳") -> 46〜55歳 | E60: =IFERROR(__xludf.DUMMYFUNCTION("""COMPUTED_VALUE"""),"女性") -> 女性 | F60: =IFERROR(__xludf.DUMMYFUNCTION("""COMPUTED_VALUE"""),"1,200万円以上") -> 1,200万円以上 | G60: =IFERROR(__xludf.DUMMYFUNCTION("""COMPUTED_VALUE"""),"関東") -> 関東 | H60: =IFERROR(__xludf.DUMMYFUNCTION("""COMPUTED_VALUE"""),"毎日") -> 毎日 | I60: =IFERROR(__xludf.DUMMYFUNCTION("""COMPUTED_VALUE"""),"ドリップコーヒー") -> ドリップコーヒー | K60: =IFERROR(__xludf.DUMMYFUNCTION("""COMPUTED_VALUE"""),"ほとんど飲まない") -> ほとんど飲まない | L60: =IFERROR(__xludf.DUMMYFUNCTION("""COMPUTED_VALUE"""),"抹茶は飲まない") -> 抹茶は飲まない | N60: =IFERROR(__xludf.DUMMYFUNCTION("""COMPUTED_VALUE"""),"味・風味, 社交的な場や雰囲気の考慮") -> 味・風味, 社交的な場や雰囲気の考慮 | P60: =IFERROR(__xludf.DUMMYFUNCTION("""COMPUTED_VALUE"""),"自宅で, カフェで, コンビニ（セブンイレブン、ローソンなど）") -> 自宅で, カフェで, コンビニ（セブンイレブン、ローソンなど） | R60: =IFERROR(__xludf.DUMMYFUNCTION("""COMPUTED_VALUE"""),"月に数回") -> 月に数回 | S60: =IFERROR(__xludf.DUMMYFUNCTION("""COMPUTED_VALUE"""),"友人と会うため") -> 友人と会うため | U60: =IFERROR(__xludf.DUMMYFUNCTION("""COMPUTED_VALUE"""),"雰囲気・心地良さ") -> 雰囲気・心地良さ | W60: =IFERROR(__xludf.DUMMYFUNCTION("""COMPUTED_VALUE"""),"いいえ") -> いいえ | X60: =IFERROR(__xludf.DUMMYFUNCTION("""COMPUTED_VALUE"""),"はい（日本的）") -> はい（日本的） | Y60: =IFERROR(__xludf.DUMMYFUNCTION("""COMPUTED_VALUE"""),6.0) -> 6 | Z60: =IFERROR(__xludf.DUMMYFUNCTION("""COMPUTED_VALUE"""),6.0) -> 6 | AA60: =IFERROR(__xludf.DUMMYFUNCTION("""COMPUTED_VALUE"""),3.0) -> 3 | AB60: =IFERROR(__xludf.DUMMYFUNCTION("""COMPUTED_VALUE"""),"いいえ") -> いいえ | AK60: rjXvy2L | AL60: 9qdLg2Q | AM60: 46062.282 | AN60: 46-55 | AO60: Female | AP60: ¥12,000,000 or more | AQ60: Kanto | AR60: Daily | AS60: Drip | AU60: Rarely | AV60: I don’t drink matcha | AX60: =IFERROR(__xludf.DUMMYFUNCTION("""COMPUTED_VALUE"""),"Taste/Flavor, Social atmosphere") -> Taste/Flavor, Social atmosphere | AZ60: =IFERROR(__xludf.DUMMYFUNCTION("""COMPUTED_VALUE"""),"At home, At cafés, From convenience stores (7-Eleven, Lawson, etc.)") -> At home, At cafés, From convenience stores (7-Eleven, Lawson, etc.) | BB60: A few times a month | BC60: To meet friends | BE60: Atmosphere | BG60: No | BH60: Yes, Japanese | BI60: 6 | BJ60: 6 | BK60: 3 | BL60: No
A61: =IFERROR(__xludf.DUMMYFUNCTION("""COMPUTED_VALUE"""),"0Q4a71P") -> 0Q4a71P | B61: =IFERROR(__xludf.DUMMYFUNCTION("""COMPUTED_VALUE"""),"obArZ1x") -> obArZ1x | C61: =IFERROR(__xludf.DUMMYFUNCTION("""COMPUTED_VALUE"""),46062.29765046296) -> 46062.298 | D61: =IFERROR(__xludf.DUMMYFUNCTION("""COMPUTED_VALUE"""),"36〜45歳") -> 36〜45歳 | E61: =IFERROR(__xludf.DUMMYFUNCTION("""COMPUTED_VALUE"""),"男性") -> 男性 | F61: =IFERROR(__xludf.DUMMYFUNCTION("""COMPUTED_VALUE"""),"1,200万円以上") -> 1,200万円以上 | G61: =IFERROR(__xludf.DUMMYFUNCTION("""COMPUTED_VALUE"""),"関東") -> 関東 | H61: =IFERROR(__xludf.DUMMYFUNCTION("""COMPUTED_VALUE"""),"毎日") -> 毎日 | I61: =IFERROR(__xludf.DUMMYFUNCTION("""COMPUTED_VALUE"""),"ドリップコーヒー") -> ドリップコーヒー | K61: =IFERROR(__xludf.DUMMYFUNCTION("""COMPUTED_VALUE"""),"まったく飲まない") -> まったく飲まない | N61: =IFERROR(__xludf.DUMMYFUNCTION("""COMPUTED_VALUE"""),"習慣, エナジー／カフェイン") -> 習慣, エナジー／カフェイン | O61: =IFERROR(__xludf.DUMMYFUNCTION("""COMPUTED_VALUE"""),"抹茶は作り方が分かりません。") -> 抹茶は作り方が分かりません。 | P61: =IFERROR(__xludf.DUMMYFUNCTION("""COMPUTED_VALUE"""),"自宅で") -> 自宅で | R61: =IFERROR(__xludf.DUMMYFUNCTION("""COMPUTED_VALUE"""),"ほとんど行かない") -> ほとんど行かない | S61: =IFERROR(__xludf.DUMMYFUNCTION("""COMPUTED_VALUE"""),"その他：") -> その他： | T61: =IFERROR(__xludf.DUMMYFUNCTION("""COMPUTED_VALUE"""),"外出時に次の用事まで時間があって作業をしたい時の居場所") -> 外出時に次の用事まで時間があって作業をしたい時の居場所 | U61: =IFERROR(__xludf.DUMMYFUNCTION("""COMPUTED_VALUE"""),"雰囲気・心地良さ") -> 雰囲気・心地良さ | W61: =IFERROR(__xludf.DUMMYFUNCTION("""COMPUTED_VALUE"""),"いいえ") -> いいえ | X61: =IFERROR(__xludf.DUMMYFUNCTION("""COMPUTED_VALUE"""),"はい（日本的）") -> はい（日本的） | Y61: =IFERROR(__xludf.DUMMYFUNCTION("""COMPUTED_VALUE"""),7.0) -> 7 | Z61: =IFERROR(__xludf.DUMMYFUNCTION("""COMPUTED_VALUE"""),7.0) -> 7 | AA61: =IFERROR(__xludf.DUMMYFUNCTION("""COMPUTED_VALUE"""),2.0) -> 2 | AB61: =IFERROR(__xludf.DUMMYFUNCTION("""COMPUTED_VALUE"""),"いいえ") -> いいえ | AK61: 0Q4a71P | AL61: obArZ1x | AM61: 46062.298 | AN61: 36-45 | AO61: Male | AP61: ¥12,000,000 or more | AQ61: Kanto | AR61: Daily | AS61: Drip | AU61: Never | AX61: =IFERROR(__xludf.DUMMYFUNCTION("""COMPUTED_VALUE"""),"Routine/Ritual, Energy boost/Caffeine") -> Routine/Ritual, Energy boost/Caffeine | AY61: I don't know how to make matcha | AZ61: =IFERROR(__xludf.DUMMYFUNCTION("""COMPUTED_VALUE"""),"At home") -> At home | BB61: Rarely | BC61: Other: | BD61: A place to stay when I’m out and have time before my next appointment and want to get some work done. | BE61: Atmosphere | BG61: No | BH61: Yes, Japanese | BI61: 7 | BJ61: 7 | BK61: 2 | BL61: No
A62: =IFERROR(__xludf.DUMMYFUNCTION("""COMPUTED_VALUE"""),"ODRy7pR") -> ODRy7pR | B62: =IFERROR(__xludf.DUMMYFUNCTION("""COMPUTED_VALUE"""),"5BkXJlP") -> 5BkXJlP | C62: =IFERROR(__xludf.DUMMYFUNCTION("""COMPUTED_VALUE"""),46063.04516203704) -> 46063.045 | D62: =IFERROR(__xludf.DUMMYFUNCTION("""COMPUTED_VALUE"""),"36〜45歳") -> 36〜45歳 | E62: =IFERROR(__xludf.DUMMYFUNCTION("""COMPUTED_VALUE"""),"女性") -> 女性 | F62: =IFERROR(__xludf.DUMMYFUNCTION("""COMPUTED_VALUE"""),"1,200万円以上") -> 1,200万円以上 | G62: =IFERROR(__xludf.DUMMYFUNCTION("""COMPUTED_VALUE"""),"関東") -> 関東 | H62: =IFERROR(__xludf.DUMMYFUNCTION("""COMPUTED_VALUE"""),"毎日") -> 毎日 | I62: =IFERROR(__xludf.DUMMYFUNCTION("""COMPUTED_VALUE"""),"プアオーバー（ハンドドリップ）") -> プアオーバー（ハンドドリップ） | K62: =IFERROR(__xludf.DUMMYFUNCTION("""COMPUTED_VALUE"""),"まったく飲まない") -> まったく飲まない | N62: =IFERROR(__xludf.DUMMYFUNCTION("""COMPUTED_VALUE"""),"味・風味") -> 味・風味 | P62: =IFERROR(__xludf.DUMMYFUNCTION("""COMPUTED_VALUE"""),"自宅で, コンビニ（セブンイレブン、ローソンなど）") -> 自宅で, コンビニ（セブンイレブン、ローソンなど） | R62: =IFERROR(__xludf.DUMMYFUNCTION("""COMPUTED_VALUE"""),"月に数回") -> 月に数回 | S62: =IFERROR(__xludf.DUMMYFUNCTION("""COMPUTED_VALUE"""),"休憩・リラックスするため") -> 休憩・リラックスするため | U62: =IFERROR(__xludf.DUMMYFUNCTION("""COMPUTED_VALUE"""),"雰囲気・心地良さ") -> 雰囲気・心地良さ | W62: =IFERROR(__xludf.DUMMYFUNCTION("""COMPUTED_VALUE"""),"わからない") -> わからない | X62: =IFERROR(__xludf.DUMMYFUNCTION("""COMPUTED_VALUE"""),"はい（日本的）") -> はい（日本的） | Y62: =IFERROR(__xludf.DUMMYFUNCTION("""COMPUTED_VALUE"""),4.0) -> 4 | Z62: =IFERROR(__xludf.DUMMYFUNCTION("""COMPUTED_VALUE"""),6.0) -> 6 | AA62: =IFERROR(__xludf.DUMMYFUNCTION("""COMPUTED_VALUE"""),5.0) -> 5 | AB62: =IFERROR(__xludf.DUMMYFUNCTION("""COMPUTED_VALUE"""),"いいえ") -> いいえ | AK62: ODRy7pR | AL62: 5BkXJlP | AM62: 46063.045 | AN62: 36-45 | AO62: Female | AP62: ¥12,000,000 or more | AQ62: Kanto | AR62: Daily | AS62: Pour Over | AU62: Never | AX62: =IFERROR(__xludf.DUMMYFUNCTION("""COMPUTED_VALUE"""),"Taste/Flavor") -> Taste/Flavor | AZ62: =IFERROR(__xludf.DUMMYFUNCTION("""COMPUTED_VALUE"""),"At home, From convenience stores (7-Eleven, Lawson, etc.)") -> At home, From convenience stores (7-Eleven, Lawson, etc.) | BB62: A few times a month | BC62: To relax or take a break | BE62: Atmosphere | BG62: Unsure | BH62: Yes, Japanese | BI62: 4 | BJ62: 6 | BK62: 5 | BL62: No
A63: =IFERROR(__xludf.DUMMYFUNCTION("""COMPUTED_VALUE"""),"dW7VyRz") -> dW7VyRz | B63: =IFERROR(__xludf.DUMMYFUNCTION("""COMPUTED_VALUE"""),"b5kqxyo") -> b5kqxyo | C63: =IFERROR(__xludf.DUMMYFUNCTION("""COMPUTED_VALUE"""),46063.15777777778) -> 46063.158 | D63: =IFERROR(__xludf.DUMMYFUNCTION("""COMPUTED_VALUE"""),"18〜25歳") -> 18〜25歳 | E63: =IFERROR(__xludf.DUMMYFUNCTION("""COMPUTED_VALUE"""),"男性") -> 男性 | F63: =IFERROR(__xludf.DUMMYFUNCTION("""COMPUTED_VALUE"""),"600万円〜899万9,999円") -> 600万円〜899万9,999円 | G63: =IFERROR(__xludf.DUMMYFUNCTION("""COMPUTED_VALUE"""),"関東") -> 関東 | H63: =IFERROR(__xludf.DUMMYFUNCTION("""COMPUTED_VALUE"""),"毎日") -> 毎日 | I63: =IFERROR(__xludf.DUMMYFUNCTION("""COMPUTED_VALUE"""),"ドリップコーヒー") -> ドリップコーヒー | K63: =IFERROR(__xludf.DUMMYFUNCTION("""COMPUTED_VALUE"""),"ほとんど飲まない") -> ほとんど飲まない | L63: =IFERROR(__xludf.DUMMYFUNCTION("""COMPUTED_VALUE"""),"抹茶は飲まない") -> 抹茶は飲まない | N63: =IFERROR(__xludf.DUMMYFUNCTION("""COMPUTED_VALUE"""),"その他：") -> その他： | R63: =IFERROR(__xludf.DUMMYFUNCTION("""COMPUTED_VALUE"""),"月に数回") -> 月に数回 | S63: =IFERROR(__xludf.DUMMYFUNCTION("""COMPUTED_VALUE"""),"友人と会うため") -> 友人と会うため | U63: =IFERROR(__xludf.DUMMYFUNCTION("""COMPUTED_VALUE"""),"雰囲気・心地良さ") -> 雰囲気・心地良さ | W63: =IFERROR(__xludf.DUMMYFUNCTION("""COMPUTED_VALUE"""),"いいえ") -> いいえ | X63: =IFERROR(__xludf.DUMMYFUNCTION("""COMPUTED_VALUE"""),"はい（日本的）") -> はい（日本的） | Y63: =IFERROR(__xludf.DUMMYFUNCTION("""COMPUTED_VALUE"""),6.0) -> 6 | Z63: =IFERROR(__xludf.DUMMYFUNCTION("""COMPUTED_VALUE"""),6.0) -> 6 | AA63: =IFERROR(__xludf.DUMMYFUNCTION("""COMPUTED_VALUE"""),4.0) -> 4 | AB63: =IFERROR(__xludf.DUMMYFUNCTION("""COMPUTED_VALUE"""),"いいえ") -> いいえ | AK63: dW7VyRz | AL63: b5kqxyo | AM63: 46063.158 | AN63: 18-25 | AO63: Male | AP63: ¥6,000,000 – ¥8,999,999 | AQ63: Kanto | AR63: Daily | AS63: Drip | AU63: Rarely | AV63: I don’t drink matcha | AX63: =IFERROR(__xludf.DUMMYFUNCTION("""COMPUTED_VALUE"""),"Other:") -> Other: | AZ63: =IFERROR(__xludf.DUMMYFUNCTION("""COMPUTED_VALUE"""),"") | BB63: A few times a month | BC63: To meet friends | BE63: Atmosphere | BG63: No | BH63: Yes, Japanese | BI63: 6 | BJ63: 6 | BK63: 4 | BL63: No
A64: =IFERROR(__xludf.DUMMYFUNCTION("""COMPUTED_VALUE"""),"Ekpr5r4") -> Ekpr5r4 | B64: =IFERROR(__xludf.DUMMYFUNCTION("""COMPUTED_VALUE"""),"D41BQOZ") -> D41BQOZ | C64: =IFERROR(__xludf.DUMMYFUNCTION("""COMPUTED_VALUE"""),46063.376122685186) -> 46063.376 | D64: =IFERROR(__xludf.DUMMYFUNCTION("""COMPUTED_VALUE"""),"65歳以上") -> 65歳以上 | E64: =IFERROR(__xludf.DUMMYFUNCTION("""COMPUTED_VALUE"""),"男性") -> 男性 | F64: =IFERROR(__xludf.DUMMYFUNCTION("""COMPUTED_VALUE"""),"1,200万円以上") -> 1,200万円以上 | G64: =IFERROR(__xludf.DUMMYFUNCTION("""COMPUTED_VALUE"""),"関東") -> 関東 | H64: =IFERROR(__xludf.DUMMYFUNCTION("""COMPUTED_VALUE"""),"ほとんど飲まない") -> ほとんど飲まない | I64: =IFERROR(__xludf.DUMMYFUNCTION("""COMPUTED_VALUE"""),"コーヒーは飲まない") -> コーヒーは飲まない | K64: =IFERROR(__xludf.DUMMYFUNCTION("""COMPUTED_VALUE"""),"ほとんど飲まない") -> ほとんど飲まない | L64: =IFERROR(__xludf.DUMMYFUNCTION("""COMPUTED_VALUE"""),"抹茶は飲まない") -> 抹茶は飲まない | N64: =IFERROR(__xludf.DUMMYFUNCTION("""COMPUTED_VALUE"""),"味・風味") -> 味・風味 | P64: =IFERROR(__xludf.DUMMYFUNCTION("""COMPUTED_VALUE"""),"自宅で") -> 自宅で | R64: =IFERROR(__xludf.DUMMYFUNCTION("""COMPUTED_VALUE"""),"ほとんど行かない") -> ほとんど行かない | U64: =IFERROR(__xludf.DUMMYFUNCTION("""COMPUTED_VALUE"""),"飲み物の味・品質") -> 飲み物の味・品質 | W64: =IFERROR(__xludf.DUMMYFUNCTION("""COMPUTED_VALUE"""),"いいえ") -> いいえ | X64: =IFERROR(__xludf.DUMMYFUNCTION("""COMPUTED_VALUE"""),"はい（日本的）") -> はい（日本的） | Y64: =IFERROR(__xludf.DUMMYFUNCTION("""COMPUTED_VALUE"""),7.0) -> 7 | Z64: =IFERROR(__xludf.DUMMYFUNCTION("""COMPUTED_VALUE"""),2.0) -> 2 | AA64: =IFERROR(__xludf.DUMMYFUNCTION("""COMPUTED_VALUE"""),5.0) -> 5 | AB64: =IFERROR(__xludf.DUMMYFUNCTION("""COMPUTED_VALUE"""),"いいえ") -> いいえ | AK64: Ekpr5r4 | AL64: D41BQOZ | AM64: 46063.376 | AN64: 65+ | AO64: Male | AP64: ¥12,000,000 or more | AQ64: Kanto | AR64: Rarely | AS64: I don't drink coffee | AU64: Rarely | AV64: I don’t drink matcha | AX64: =IFERROR(__xludf.DUMMYFUNCTION("""COMPUTED_VALUE"""),"Taste/Flavor") -> Taste/Flavor | AZ64: =IFERROR(__xludf.DUMMYFUNCTION("""COMPUTED_VALUE"""),"At home") -> At home | BB64: Rarely | BE64: Quality of drinks | BG64: No | BH64: Yes, Japanese | BI64: 7 | BJ64: 2 | BK64: 5 | BL64: No
AX65: =IFERROR(__xludf.DUMMYFUNCTION("""COMPUTED_VALUE"""),"") | AZ65: =IFERROR(__xludf.DUMMYFUNCTION("""COMPUTED_VALUE"""),"")
AX66: =IFERROR(__xludf.DUMMYFUNCTION("""COMPUTED_VALUE"""),"") | AZ66: =IFERROR(__xludf.DUMMYFUNCTION("""COMPUTED_VALUE"""),"")
AX67: =IFERROR(__xludf.DUMMYFUNCTION("""COMPUTED_VALUE"""),"") | AZ67: =IFERROR(__xludf.DUMMYFUNCTION("""COMPUTED_VALUE"""),"")
AX68: =IFERROR(__xludf.DUMMYFUNCTION("""COMPUTED_VALUE"""),"") | AZ68: =IFERROR(__xludf.DUMMYFUNCTION("""COMPUTED_VALUE"""),"")
AX69: =IFERROR(__xludf.DUMMYFUNCTION("""COMPUTED_VALUE"""),"") | AZ69: =IFERROR(__xludf.DUMMYFUNCTION("""COMPUTED_VALUE"""),"")
AX70: =IFERROR(__xludf.DUMMYFUNCTION("""COMPUTED_VALUE"""),"") | AZ70: =IFERROR(__xludf.DUMMYFUNCTION("""COMPUTED_VALUE"""),"")
AX71: =IFERROR(__xludf.DUMMYFUNCTION("""COMPUTED_VALUE"""),"") | AZ71: =IFERROR(__xludf.DUMMYFUNCTION("""COMPUTED_VALUE"""),"")
AX72: =IFERROR(__xludf.DUMMYFUNCTION("""COMPUTED_VALUE"""),"") | AZ72: =IFERROR(__xludf.DUMMYFUNCTION("""COMPUTED_VALUE"""),"")
AX73: =IFERROR(__xludf.DUMMYFUNCTION("""COMPUTED_VALUE"""),"") | AZ73: =IFERROR(__xludf.DUMMYFUNCTION("""COMPUTED_VALUE"""),"")
AX74: =IFERROR(__xludf.DUMMYFUNCTION("""COMPUTED_VALUE"""),"") | AZ74: =IFERROR(__xludf.DUMMYFUNCTION("""COMPUTED_VALUE"""),"")
AX75: =IFERROR(__xludf.DUMMYFUNCTION("""COMPUTED_VALUE"""),"") | AZ75: =IFERROR(__xludf.DUMMYFUNCTION("""COMPUTED_VALUE"""),"")
AX76: =IFERROR(__xludf.DUMMYFUNCTION("""COMPUTED_VALUE"""),"") | AZ76: =IFERROR(__xludf.DUMMYFUNCTION("""COMPUTED_VALUE"""),"")
... AX1000: =IFERROR(__xludf.DUMMYFUNCTION("""COMPUTED_VALUE"""),"") | AZ1000: =IFERROR(__xludf.DUMMYFUNCTION("""COMPUTED_VALUE"""),"")

Sheet English Results
A1: =IFERROR(__xludf.DUMMYFUNCTION("IMPORTRANGE(""https://docs.google.com/spreadsheets/d/17nDSbOq8pjD5y7HTwiE77nsbddGAU2goxANoQt1pCwU/edit?gid=0#gid=0"",""Sheet1!A2:AB"")"),"ODxjxJ8") -> ODxjxJ8 | B1: =IFERROR(__xludf.DUMMYFUNCTION("""COMPUTED_VALUE"""),"dWdJZkK") -> dWdJZkK | C1: =IFERROR(__xludf.DUMMYFUNCTION("""COMPUTED_VALUE"""),46026.96828703704) -> 46026.968 | D1: =IFERROR(__xludf.DUMMYFUNCTION("""COMPUTED_VALUE"""),"46-55") -> 46-55 | E1: =IFERROR(__xludf.DUMMYFUNCTION("""COMPUTED_VALUE"""),"Male") -> Male | F1: =IFERROR(__xludf.DUMMYFUNCTION("""COMPUTED_VALUE"""),"¥12,000,000 or more") -> ¥12,000,000 or more | G1: =IFERROR(__xludf.DUMMYFUNCTION("""COMPUTED_VALUE"""),"Kanto") -> Kanto | H1: =IFERROR(__xludf.DUMMYFUNCTION("""COMPUTED_VALUE"""),"Daily") -> Daily | I1: =IFERROR(__xludf.DUMMYFUNCTION("""COMPUTED_VALUE"""),"Latte") -> Latte | K1: =IFERROR(__xludf.DUMMYFUNCTION("""COMPUTED_VALUE"""),"Rarely") -> Rarely | L1: =IFERROR(__xludf.DUMMYFUNCTION("""COMPUTED_VALUE"""),"Other:") -> Other: | M1: =IFERROR(__xludf.DUMMYFUNCTION("""COMPUTED_VALUE"""),"I don't know!!") -> I don't know!! | N1: =IFERROR(__xludf.DUMMYFUNCTION("""COMPUTED_VALUE"""),"Routine/Ritual, Social atmosphere") -> Routine/Ritual, Social atmosphere | P1: =IFERROR(__xludf.DUMMYFUNCTION("""COMPUTED_VALUE"""),"At cafés, At home") -> At cafés, At home | R1: =IFERROR(__xludf.DUMMYFUNCTION("""COMPUTED_VALUE"""),"Several times a week") -> Several times a week | S1: =IFERROR(__xludf.DUMMYFUNCTION("""COMPUTED_VALUE"""),"To relax or take a break") -> To relax or take a break | U1: =IFERROR(__xludf.DUMMYFUNCTION("""COMPUTED_VALUE"""),"Quality of drinks") -> Quality of drinks | W1: =IFERROR(__xludf.DUMMYFUNCTION("""COMPUTED_VALUE"""),"Yes, Western") -> Yes, Western | X1: =IFERROR(__xludf.DUMMYFUNCTION("""COMPUTED_VALUE"""),"Yes, Japanese") -> Yes, Japanese | Y1: =IFERROR(__xludf.DUMMYFUNCTION("""COMPUTED_VALUE"""),5.0) -> 5 | Z1: =IFERROR(__xludf.DUMMYFUNCTION("""COMPUTED_VALUE"""),7.0) -> 7 | AA1: =IFERROR(__xludf.DUMMYFUNCTION("""COMPUTED_VALUE"""),7.0) -> 7 | AB1: =IFERROR(__xludf.DUMMYFUNCTION("""COMPUTED_VALUE"""),"Yes") -> Yes
A2: =IFERROR(__xludf.DUMMYFUNCTION("""COMPUTED_VALUE"""),"PdZVGdx") -> PdZVGdx | B2: =IFERROR(__xludf.DUMMYFUNCTION("""COMPUTED_VALUE"""),"lbdea2N") -> lbdea2N | C2: =IFERROR(__xludf.DUMMYFUNCTION("""COMPUTED_VALUE"""),46030.33025462963) -> 46030.33 | D2: =IFERROR(__xludf.DUMMYFUNCTION("""COMPUTED_VALUE"""),"26-35") -> 26-35 | E2: =IFERROR(__xludf.DUMMYFUNCTION("""COMPUTED_VALUE"""),"Male") -> Male | F2: =IFERROR(__xludf.DUMMYFUNCTION("""COMPUTED_VALUE"""),"¥3,000,000 – ¥5,999,999") -> ¥3,000,000 – ¥5,999,999 | G2: =IFERROR(__xludf.DUMMYFUNCTION("""COMPUTED_VALUE"""),"Kanto") -> Kanto | H2: =IFERROR(__xludf.DUMMYFUNCTION("""COMPUTED_VALUE"""),"Daily") -> Daily | I2: =IFERROR(__xludf.DUMMYFUNCTION("""COMPUTED_VALUE"""),"Pour Over") -> Pour Over | K2: =IFERROR(__xludf.DUMMYFUNCTION("""COMPUTED_VALUE"""),"Rarely") -> Rarely | L2: =IFERROR(__xludf.DUMMYFUNCTION("""COMPUTED_VALUE"""),"I don’t drink matcha") -> I don’t drink matcha | N2: =IFERROR(__xludf.DUMMYFUNCTION("""COMPUTED_VALUE"""),"Taste/Flavor") -> Taste/Flavor | P2: =IFERROR(__xludf.DUMMYFUNCTION("""COMPUTED_VALUE"""),"At home") -> At home | R2: =IFERROR(__xludf.DUMMYFUNCTION("""COMPUTED_VALUE"""),"Every day") -> Every day | S2: =IFERROR(__xludf.DUMMYFUNCTION("""COMPUTED_VALUE"""),"To relax or take a break") -> To relax or take a break | U2: =IFERROR(__xludf.DUMMYFUNCTION("""COMPUTED_VALUE"""),"Quality of drinks") -> Quality of drinks | W2: =IFERROR(__xludf.DUMMYFUNCTION("""COMPUTED_VALUE"""),"Yes, Global") -> Yes, Global | X2: =IFERROR(__xludf.DUMMYFUNCTION("""COMPUTED_VALUE"""),"Yes, Western") -> Yes, Western | Y2: =IFERROR(__xludf.DUMMYFUNCTION("""COMPUTED_VALUE"""),6.0) -> 6 | Z2: =IFERROR(__xludf.DUMMYFUNCTION("""COMPUTED_VALUE"""),4.0) -> 4 | AA2: =IFERROR(__xludf.DUMMYFUNCTION("""COMPUTED_VALUE"""),6.0) -> 6 | AB2: =IFERROR(__xludf.DUMMYFUNCTION("""COMPUTED_VALUE"""),"No") -> No
A3: =IFERROR(__xludf.DUMMYFUNCTION("""COMPUTED_VALUE"""),"ODxONvY") -> ODxONvY | B3: =IFERROR(__xludf.DUMMYFUNCTION("""COMPUTED_VALUE"""),"KYl5lEM") -> KYl5lEM | C3: =IFERROR(__xludf.DUMMYFUNCTION("""COMPUTED_VALUE"""),46030.37069444444) -> 46030.371 | D3: =IFERROR(__xludf.DUMMYFUNCTION("""COMPUTED_VALUE"""),"36-45") -> 36-45 | E3: =IFERROR(__xludf.DUMMYFUNCTION("""COMPUTED_VALUE"""),"Male") -> Male | F3: =IFERROR(__xludf.DUMMYFUNCTION("""COMPUTED_VALUE"""),"¥3,000,000 – ¥5,999,999") -> ¥3,000,000 – ¥5,999,999 | G3: =IFERROR(__xludf.DUMMYFUNCTION("""COMPUTED_VALUE"""),"Kanto") -> Kanto | H3: =IFERROR(__xludf.DUMMYFUNCTION("""COMPUTED_VALUE"""),"Daily") -> Daily | I3: =IFERROR(__xludf.DUMMYFUNCTION("""COMPUTED_VALUE"""),"Latte") -> Latte | K3: =IFERROR(__xludf.DUMMYFUNCTION("""COMPUTED_VALUE"""),"Once a week") -> Once a week | L3: =IFERROR(__xludf.DUMMYFUNCTION("""COMPUTED_VALUE"""),"Matcha Latte") -> Matcha Latte | N3: =IFERROR(__xludf.DUMMYFUNCTION("""COMPUTED_VALUE"""),"Taste/Flavor") -> Taste/Flavor | O3: =IFERROR(__xludf.DUMMYFUNCTION("""COMPUTED_VALUE"""),"What the shop is famous for") -> What the shop is famous for | P3: =IFERROR(__xludf.DUMMYFUNCTION("""COMPUTED_VALUE"""),"At cafés") -> At cafés | R3: =IFERROR(__xludf.DUMMYFUNCTION("""COMPUTED_VALUE"""),"Once a week") -> Once a week | S3: =IFERROR(__xludf.DUMMYFUNCTION("""COMPUTED_VALUE"""),"To relax or take a break") -> To relax or take a break | U3: =IFERROR(__xludf.DUMMYFUNCTION("""COMPUTED_VALUE"""),"Quality of drinks") -> Quality of drinks | W3: =IFERROR(__xludf.DUMMYFUNCTION("""COMPUTED_VALUE"""),"Yes, Global") -> Yes, Global | X3: =IFERROR(__xludf.DUMMYFUNCTION("""COMPUTED_VALUE"""),"Yes, Western") -> Yes, Western | Y3: =IFERROR(__xludf.DUMMYFUNCTION("""COMPUTED_VALUE"""),7.0) -> 7 | Z3: =IFERROR(__xludf.DUMMYFUNCTION("""COMPUTED_VALUE"""),7.0) -> 7 | AA3: =IFERROR(__xludf.DUMMYFUNCTION("""COMPUTED_VALUE"""),7.0) -> 7 | AB3: =IFERROR(__xludf.DUMMYFUNCTION("""COMPUTED_VALUE"""),"No") -> No
A4: =IFERROR(__xludf.DUMMYFUNCTION("""COMPUTED_VALUE"""),"44VXbKA") -> 44VXbKA | B4: =IFERROR(__xludf.DUMMYFUNCTION("""COMPUTED_VALUE"""),"xXaJrqk") -> xXaJrqk | C4: =IFERROR(__xludf.DUMMYFUNCTION("""COMPUTED_VALUE"""),46030.72068287037) -> 46030.721 | D4: =IFERROR(__xludf.DUMMYFUNCTION("""COMPUTED_VALUE"""),"46-55") -> 46-55 | E4: =IFERROR(__xludf.DUMMYFUNCTION("""COMPUTED_VALUE"""),"Female") -> Female | F4: =IFERROR(__xludf.DUMMYFUNCTION("""COMPUTED_VALUE"""),"¥12,000,000 or more") -> ¥12,000,000 or more | G4: =IFERROR(__xludf.DUMMYFUNCTION("""COMPUTED_VALUE"""),"Kanto") -> Kanto | H4: =IFERROR(__xludf.DUMMYFUNCTION("""COMPUTED_VALUE"""),"Daily") -> Daily | I4: =IFERROR(__xludf.DUMMYFUNCTION("""COMPUTED_VALUE"""),"Pour Over") -> Pour Over | K4: =IFERROR(__xludf.DUMMYFUNCTION("""COMPUTED_VALUE"""),"Rarely") -> Rarely | L4: =IFERROR(__xludf.DUMMYFUNCTION("""COMPUTED_VALUE"""),"Matcha Latte") -> Matcha Latte | N4: =IFERROR(__xludf.DUMMYFUNCTION("""COMPUTED_VALUE"""),"Taste/Flavor") -> Taste/Flavor | P4: =IFERROR(__xludf.DUMMYFUNCTION("""COMPUTED_VALUE"""),"At home") -> At home | R4: =IFERROR(__xludf.DUMMYFUNCTION("""COMPUTED_VALUE"""),"A few times a month") -> A few times a month | S4: =IFERROR(__xludf.DUMMYFUNCTION("""COMPUTED_VALUE"""),"To meet friends") -> To meet friends | U4: =IFERROR(__xludf.DUMMYFUNCTION("""COMPUTED_VALUE"""),"Atmosphere") -> Atmosphere | W4: =IFERROR(__xludf.DUMMYFUNCTION("""COMPUTED_VALUE"""),"Yes, Global") -> Yes, Global | X4: =IFERROR(__xludf.DUMMYFUNCTION("""COMPUTED_VALUE"""),"Yes, Japanese") -> Yes, Japanese | Y4: =IFERROR(__xludf.DUMMYFUNCTION("""COMPUTED_VALUE"""),7.0) -> 7 | Z4: =IFERROR(__xludf.DUMMYFUNCTION("""COMPUTED_VALUE"""),7.0) -> 7 | AA4: =IFERROR(__xludf.DUMMYFUNCTION("""COMPUTED_VALUE"""),7.0) -> 7 | AB4: =IFERROR(__xludf.DUMMYFUNCTION("""COMPUTED_VALUE"""),"Yes") -> Yes
A5: =IFERROR(__xludf.DUMMYFUNCTION("""COMPUTED_VALUE"""),"kdBll9e") -> kdBll9e | B5: =IFERROR(__xludf.DUMMYFUNCTION("""COMPUTED_VALUE"""),"NpWo9Wb") -> NpWo9Wb | C5: =IFERROR(__xludf.DUMMYFUNCTION("""COMPUTED_VALUE"""),46031.07336805556) -> 46031.073 | D5: =IFERROR(__xludf.DUMMYFUNCTION("""COMPUTED_VALUE"""),"56-65") -> 56-65 | E5: =IFERROR(__xludf.DUMMYFUNCTION("""COMPUTED_VALUE"""),"Male") -> Male | F5: =IFERROR(__xludf.DUMMYFUNCTION("""COMPUTED_VALUE"""),"Prefer not to say") -> Prefer not to say | G5: =IFERROR(__xludf.DUMMYFUNCTION("""COMPUTED_VALUE"""),"Kanto") -> Kanto | H5: =IFERROR(__xludf.DUMMYFUNCTION("""COMPUTED_VALUE"""),"Daily") -> Daily | I5: =IFERROR(__xludf.DUMMYFUNCTION("""COMPUTED_VALUE"""),"Drip") -> Drip | K5: =IFERROR(__xludf.DUMMYFUNCTION("""COMPUTED_VALUE"""),"Rarely") -> Rarely | N5: =IFERROR(__xludf.DUMMYFUNCTION("""COMPUTED_VALUE"""),"It is never really a choice; I just drink coffee") -> It is never really a choice; I just drink coffee | P5: =IFERROR(__xludf.DUMMYFUNCTION("""COMPUTED_VALUE"""),"At home") -> At home | R5: =IFERROR(__xludf.DUMMYFUNCTION("""COMPUTED_VALUE"""),"A few times a month") -> A few times a month | S5: =IFERROR(__xludf.DUMMYFUNCTION("""COMPUTED_VALUE"""),"Other:") -> Other: | T5: =IFERROR(__xludf.DUMMYFUNCTION("""COMPUTED_VALUE"""),"To spend time when I am out and have a gap between obligations") -> To spend time when I am out and have a gap between obligations | U5: =IFERROR(__xludf.DUMMYFUNCTION("""COMPUTED_VALUE"""),"Atmosphere") -> Atmosphere | W5: =IFERROR(__xludf.DUMMYFUNCTION("""COMPUTED_VALUE"""),"No") -> No | X5: =IFERROR(__xludf.DUMMYFUNCTION("""COMPUTED_VALUE"""),"Yes, Japanese") -> Yes, Japanese | Y5: =IFERROR(__xludf.DUMMYFUNCTION("""COMPUTED_VALUE"""),5.0) -> 5 | Z5: =IFERROR(__xludf.DUMMYFUNCTION("""COMPUTED_VALUE"""),7.0) -> 7 | AA5: =IFERROR(__xludf.DUMMYFUNCTION("""COMPUTED_VALUE"""),6.0) -> 6 | AB5: =IFERROR(__xludf.DUMMYFUNCTION("""COMPUTED_VALUE"""),"Yes") -> Yes
A6: =IFERROR(__xludf.DUMMYFUNCTION("""COMPUTED_VALUE"""),"gD6aqNP") -> gD6aqNP | B6: =IFERROR(__xludf.DUMMYFUNCTION("""COMPUTED_VALUE"""),"9qDQY95") -> 9qDQY95 | C6: =IFERROR(__xludf.DUMMYFUNCTION("""COMPUTED_VALUE"""),46031.08563657408) -> 46031.086 | D6: =IFERROR(__xludf.DUMMYFUNCTION("""COMPUTED_VALUE"""),"36-45") -> 36-45 | E6: =IFERROR(__xludf.DUMMYFUNCTION("""COMPUTED_VALUE"""),"Female") -> Female | F6: =IFERROR(__xludf.DUMMYFUNCTION("""COMPUTED_VALUE"""),"¥12,000,000 or more") -> ¥12,000,000 or more | G6: =IFERROR(__xludf.DUMMYFUNCTION("""COMPUTED_VALUE"""),"Kanto") -> Kanto | H6: =IFERROR(__xludf.DUMMYFUNCTION("""COMPUTED_VALUE"""),"Rarely") -> Rarely | I6: =IFERROR(__xludf.DUMMYFUNCTION("""COMPUTED_VALUE"""),"Cappuccino") -> Cappuccino | K6: =IFERROR(__xludf.DUMMYFUNCTION("""COMPUTED_VALUE"""),"Rarely") -> Rarely | L6: =IFERROR(__xludf.DUMMYFUNCTION("""COMPUTED_VALUE"""),"Usucha") -> Usucha | N6: =IFERROR(__xludf.DUMMYFUNCTION("""COMPUTED_VALUE"""),"Social norms / influence (what people around me usually drink), Routine/Ritual") -> Social norms / influence (what people around me usually drink), Routine/Ritual | P6: =IFERROR(__xludf.DUMMYFUNCTION("""COMPUTED_VALUE"""),"At cafés") -> At cafés | R6: =IFERROR(__xludf.DUMMYFUNCTION("""COMPUTED_VALUE"""),"A few times a month") -> A few times a month | S6: =IFERROR(__xludf.DUMMYFUNCTION("""COMPUTED_VALUE"""),"To meet friends") -> To meet friends | U6: =IFERROR(__xludf.DUMMYFUNCTION("""COMPUTED_VALUE"""),"Atmosphere") -> Atmosphere | W6: =IFERROR(__xludf.DUMMYFUNCTION("""COMPUTED_VALUE"""),"Yes, Global") -> Yes, Global | X6: =IFERROR(__xludf.DUMMYFUNCTION("""COMPUTED_VALUE"""),"Yes, Japanese") -> Yes, Japanese | Y6: =IFERROR(__xludf.DUMMYFUNCTION("""COMPUTED_VALUE"""),6.0) -> 6 | Z6: =IFERROR(__xludf.DUMMYFUNCTION("""COMPUTED_VALUE"""),7.0) -> 7 | AA6: =IFERROR(__xludf.DUMMYFUNCTION("""COMPUTED_VALUE"""),5.0) -> 5 | AB6: =IFERROR(__xludf.DUMMYFUNCTION("""COMPUTED_VALUE"""),"No") -> No
A7: =IFERROR(__xludf.DUMMYFUNCTION("""COMPUTED_VALUE"""),"jaAyLo6") -> jaAyLo6 | B7: =IFERROR(__xludf.DUMMYFUNCTION("""COMPUTED_VALUE"""),"QK50r8A") -> QK50r8A | C7: =IFERROR(__xludf.DUMMYFUNCTION("""COMPUTED_VALUE"""),46032.075902777775) -> 46032.076 | D7: =IFERROR(__xludf.DUMMYFUNCTION("""COMPUTED_VALUE"""),"26-35") -> 26-35 | E7: =IFERROR(__xludf.DUMMYFUNCTION("""COMPUTED_VALUE"""),"Female") -> Female | F7: =IFERROR(__xludf.DUMMYFUNCTION("""COMPUTED_VALUE"""),"¥3,000,000 – ¥5,999,999") -> ¥3,000,000 – ¥5,999,999 | G7: =IFERROR(__xludf.DUMMYFUNCTION("""COMPUTED_VALUE"""),"Kanto") -> Kanto | H7: =IFERROR(__xludf.DUMMYFUNCTION("""COMPUTED_VALUE"""),"Daily") -> Daily | I7: =IFERROR(__xludf.DUMMYFUNCTION("""COMPUTED_VALUE"""),"Drip") -> Drip | K7: =IFERROR(__xludf.DUMMYFUNCTION("""COMPUTED_VALUE"""),"Rarely") -> Rarely | L7: =IFERROR(__xludf.DUMMYFUNCTION("""COMPUTED_VALUE"""),"Other:") -> Other: | M7: =IFERROR(__xludf.DUMMYFUNCTION("""COMPUTED_VALUE"""),"I drink dark sencha (green tea) at home several times a week but matcha only with friends who are visiting ") -> I drink dark sencha (green tea) at home several times a week but matcha only with friends who are visiting | N7: =IFERROR(__xludf.DUMMYFUNCTION("""COMPUTED_VALUE"""),"Routine/Ritual") -> Routine/Ritual | P7: =IFERROR(__xludf.DUMMYFUNCTION("""COMPUTED_VALUE"""),"At home, At cafés, From convenience stores (7-Eleven, Lawson, etc.), From vending machines") -> At home, At cafés, From convenience stores (7-Eleven, Lawson, etc.), From vending machines | R7: =IFERROR(__xludf.DUMMYFUNCTION("""COMPUTED_VALUE"""),"Several times a week") -> Several times a week | S7: =IFERROR(__xludf.DUMMYFUNCTION("""COMPUTED_VALUE"""),"To relax or take a break") -> To relax or take a break | U7: =IFERROR(__xludf.DUMMYFUNCTION("""COMPUTED_VALUE"""),"Atmosphere") -> Atmosphere | W7: =IFERROR(__xludf.DUMMYFUNCTION("""COMPUTED_VALUE"""),"Yes, Global") -> Yes, Global | X7: =IFERROR(__xludf.DUMMYFUNCTION("""COMPUTED_VALUE"""),"Yes, Western") -> Yes, Western | Y7: =IFERROR(__xludf.DUMMYFUNCTION("""COMPUTED_VALUE"""),7.0) -> 7 | Z7: =IFERROR(__xludf.DUMMYFUNCTION("""COMPUTED_VALUE"""),6.0) -> 6 | AA7: =IFERROR(__xludf.DUMMYFUNCTION("""COMPUTED_VALUE"""),7.0) -> 7 | AB7: =IFERROR(__xludf.DUMMYFUNCTION("""COMPUTED_VALUE"""),"Yes") -> Yes
A8: =IFERROR(__xludf.DUMMYFUNCTION("""COMPUTED_VALUE"""),"2EGLdp9") -> 2EGLdp9 | B8: =IFERROR(__xludf.DUMMYFUNCTION("""COMPUTED_VALUE"""),"jaQWdA9") -> jaQWdA9 | C8: =IFERROR(__xludf.DUMMYFUNCTION("""COMPUTED_VALUE"""),46032.78150462963) -> 46032.781 | D8: =IFERROR(__xludf.DUMMYFUNCTION("""COMPUTED_VALUE"""),"36-45") -> 36-45 | E8: =IFERROR(__xludf.DUMMYFUNCTION("""COMPUTED_VALUE"""),"Female") -> Female | F8: =IFERROR(__xludf.DUMMYFUNCTION("""COMPUTED_VALUE"""),"¥6,000,000 – ¥8,999,999") -> ¥6,000,000 – ¥8,999,999 | G8: =IFERROR(__xludf.DUMMYFUNCTION("""COMPUTED_VALUE"""),"Kanto") -> Kanto | H8: =IFERROR(__xludf.DUMMYFUNCTION("""COMPUTED_VALUE"""),"Several times a week") -> Several times a week | I8: =IFERROR(__xludf.DUMMYFUNCTION("""COMPUTED_VALUE"""),"Cappuccino") -> Cappuccino | K8: =IFERROR(__xludf.DUMMYFUNCTION("""COMPUTED_VALUE"""),"Rarely") -> Rarely | L8: =IFERROR(__xludf.DUMMYFUNCTION("""COMPUTED_VALUE"""),"I don’t drink matcha") -> I don’t drink matcha | N8: =IFERROR(__xludf.DUMMYFUNCTION("""COMPUTED_VALUE"""),"To try new things") -> To try new things | P8: =IFERROR(__xludf.DUMMYFUNCTION("""COMPUTED_VALUE"""),"At cafés") -> At cafés | R8: =IFERROR(__xludf.DUMMYFUNCTION("""COMPUTED_VALUE"""),"Once a week") -> Once a week | S8: =IFERROR(__xludf.DUMMYFUNCTION("""COMPUTED_VALUE"""),"To study/work") -> To study/work | U8: =IFERROR(__xludf.DUMMYFUNCTION("""COMPUTED_VALUE"""),"Quality of drinks") -> Quality of drinks | W8: =IFERROR(__xludf.DUMMYFUNCTION("""COMPUTED_VALUE"""),"No") -> No | X8: =IFERROR(__xludf.DUMMYFUNCTION("""COMPUTED_VALUE"""),"Yes, Japanese") -> Yes, Japanese | Y8: =IFERROR(__xludf.DUMMYFUNCTION("""COMPUTED_VALUE"""),6.0) -> 6 | Z8: =IFERROR(__xludf.DUMMYFUNCTION("""COMPUTED_VALUE"""),4.0) -> 4 | AA8: =IFERROR(__xludf.DUMMYFUNCTION("""COMPUTED_VALUE"""),6.0) -> 6 | AB8: =IFERROR(__xludf.DUMMYFUNCTION("""COMPUTED_VALUE"""),"No") -> No
A9: =IFERROR(__xludf.DUMMYFUNCTION("""COMPUTED_VALUE"""),"GxAD4Ep") -> GxAD4Ep | B9: =IFERROR(__xludf.DUMMYFUNCTION("""COMPUTED_VALUE"""),"MezJll8") -> MezJll8 | C9: =IFERROR(__xludf.DUMMYFUNCTION("""COMPUTED_VALUE"""),46032.9597337963) -> 46032.96 | D9: =IFERROR(__xludf.DUMMYFUNCTION("""COMPUTED_VALUE"""),"46-55") -> 46-55 | E9: =IFERROR(__xludf.DUMMYFUNCTION("""COMPUTED_VALUE"""),"Female") -> Female | F9: =IFERROR(__xludf.DUMMYFUNCTION("""COMPUTED_VALUE"""),"¥12,000,000 or more") -> ¥12,000,000 or more | G9: =IFERROR(__xludf.DUMMYFUNCTION("""COMPUTED_VALUE"""),"Kanto") -> Kanto | H9: =IFERROR(__xludf.DUMMYFUNCTION("""COMPUTED_VALUE"""),"Once a week") -> Once a week | I9: =IFERROR(__xludf.DUMMYFUNCTION("""COMPUTED_VALUE"""),"Latte") -> Latte | K9: =IFERROR(__xludf.DUMMYFUNCTION("""COMPUTED_VALUE"""),"Rarely") -> Rarely | L9: =IFERROR(__xludf.DUMMYFUNCTION("""COMPUTED_VALUE"""),"Koicha") -> Koicha | N9: =IFERROR(__xludf.DUMMYFUNCTION("""COMPUTED_VALUE"""),"Taste/Flavor, Health benefits") -> Taste/Flavor, Health benefits | P9: =IFERROR(__xludf.DUMMYFUNCTION("""COMPUTED_VALUE"""),"At cafés, At home") -> At cafés, At home | R9: =IFERROR(__xludf.DUMMYFUNCTION("""COMPUTED_VALUE"""),"Once a week") -> Once a week | S9: =IFERROR(__xludf.DUMMYFUNCTION("""COMPUTED_VALUE"""),"To try a new drink") -> To try a new drink | U9: =IFERROR(__xludf.DUMMYFUNCTION("""COMPUTED_VALUE"""),"Quality of drinks") -> Quality of drinks | W9: =IFERROR(__xludf.DUMMYFUNCTION("""COMPUTED_VALUE"""),"Yes, Global") -> Yes, Global | X9: =IFERROR(__xludf.DUMMYFUNCTION("""COMPUTED_VALUE"""),"Yes, Japanese") -> Yes, Japanese | Y9: =IFERROR(__xludf.DUMMYFUNCTION("""COMPUTED_VALUE"""),4.0) -> 4 | Z9: =IFERROR(__xludf.DUMMYFUNCTION("""COMPUTED_VALUE"""),7.0) -> 7 | AA9: =IFERROR(__xludf.DUMMYFUNCTION("""COMPUTED_VALUE"""),6.0) -> 6 | AB9: =IFERROR(__xludf.DUMMYFUNCTION("""COMPUTED_VALUE"""),"Yes") -> Yes
A10: =IFERROR(__xludf.DUMMYFUNCTION("""COMPUTED_VALUE"""),"jaAJg66") -> jaAJg66 | B10: =IFERROR(__xludf.DUMMYFUNCTION("""COMPUTED_VALUE"""),"0Q61NJ0") -> 0Q61NJ0 | C10: =IFERROR(__xludf.DUMMYFUNCTION("""COMPUTED_VALUE"""),46034.05678240741) -> 46034.057 | D10: =IFERROR(__xludf.DUMMYFUNCTION("""COMPUTED_VALUE"""),"26-35") -> 26-35 | E10: =IFERROR(__xludf.DUMMYFUNCTION("""COMPUTED_VALUE"""),"Female") -> Female | F10: =IFERROR(__xludf.DUMMYFUNCTION("""COMPUTED_VALUE"""),"¥3,000,000 – ¥5,999,999") -> ¥3,000,000 – ¥5,999,999 | G10: =IFERROR(__xludf.DUMMYFUNCTION("""COMPUTED_VALUE"""),"Kanto") -> Kanto | H10: =IFERROR(__xludf.DUMMYFUNCTION("""COMPUTED_VALUE"""),"Rarely") -> Rarely | I10: =IFERROR(__xludf.DUMMYFUNCTION("""COMPUTED_VALUE"""),"Latte") -> Latte | K10: =IFERROR(__xludf.DUMMYFUNCTION("""COMPUTED_VALUE"""),"Once a week") -> Once a week | L10: =IFERROR(__xludf.DUMMYFUNCTION("""COMPUTED_VALUE"""),"Matcha Latte") -> Matcha Latte | N10: =IFERROR(__xludf.DUMMYFUNCTION("""COMPUTED_VALUE"""),"Energy boost/Caffeine, Routine/Ritual") -> Energy boost/Caffeine, Routine/Ritual | P10: =IFERROR(__xludf.DUMMYFUNCTION("""COMPUTED_VALUE"""),"At cafés") -> At cafés | R10: =IFERROR(__xludf.DUMMYFUNCTION("""COMPUTED_VALUE"""),"Once a week") -> Once a week | S10: =IFERROR(__xludf.DUMMYFUNCTION("""COMPUTED_VALUE"""),"To study/work") -> To study/work | U10: =IFERROR(__xludf.DUMMYFUNCTION("""COMPUTED_VALUE"""),"Atmosphere") -> Atmosphere | W10: =IFERROR(__xludf.DUMMYFUNCTION("""COMPUTED_VALUE"""),"Yes, Global") -> Yes, Global | X10: =IFERROR(__xludf.DUMMYFUNCTION("""COMPUTED_VALUE"""),"Yes, Japanese") -> Yes, Japanese | Y10: =IFERROR(__xludf.DUMMYFUNCTION("""COMPUTED_VALUE"""),1.0) -> 1 | Z10: =IFERROR(__xludf.DUMMYFUNCTION("""COMPUTED_VALUE"""),6.0) -> 6 | AA10: =IFERROR(__xludf.DUMMYFUNCTION("""COMPUTED_VALUE"""),6.0) -> 6 | AB10: =IFERROR(__xludf.DUMMYFUNCTION("""COMPUTED_VALUE"""),"Yes") -> Yes
A11: =IFERROR(__xludf.DUMMYFUNCTION("""COMPUTED_VALUE"""),"q41JgOO") -> q41JgOO | B11: =IFERROR(__xludf.DUMMYFUNCTION("""COMPUTED_VALUE"""),"1A7Dqpb") -> 1A7Dqpb | C11: =IFERROR(__xludf.DUMMYFUNCTION("""COMPUTED_VALUE"""),46034.0577662037) -> 46034.058 | D11: =IFERROR(__xludf.DUMMYFUNCTION("""COMPUTED_VALUE"""),"46-55") -> 46-55 | E11: =IFERROR(__xludf.DUMMYFUNCTION("""COMPUTED_VALUE"""),"Male") -> Male | F11: =IFERROR(__xludf.DUMMYFUNCTION("""COMPUTED_VALUE"""),"¥12,000,000 or more") -> ¥12,000,000 or more | G11: =IFERROR(__xludf.DUMMYFUNCTION("""COMPUTED_VALUE"""),"Kanto") -> Kanto | H11: =IFERROR(__xludf.DUMMYFUNCTION("""COMPUTED_VALUE"""),"Daily") -> Daily | I11: =IFERROR(__xludf.DUMMYFUNCTION("""COMPUTED_VALUE"""),"Other:") -> Other: | J11: =IFERROR(__xludf.DUMMYFUNCTION("""COMPUTED_VALUE"""),"Espresso") -> Espresso | K11: =IFERROR(__xludf.DUMMYFUNCTION("""COMPUTED_VALUE"""),"Never") -> Never | N11: =IFERROR(__xludf.DUMMYFUNCTION("""COMPUTED_VALUE"""),"Taste/Flavor") -> Taste/Flavor | P11: =IFERROR(__xludf.DUMMYFUNCTION("""COMPUTED_VALUE"""),"At home, At cafés") -> At home, At cafés | R11: =IFERROR(__xludf.DUMMYFUNCTION("""COMPUTED_VALUE"""),"Several times a week") -> Several times a week | S11: =IFERROR(__xludf.DUMMYFUNCTION("""COMPUTED_VALUE"""),"To meet friends") -> To meet friends | U11: =IFERROR(__xludf.DUMMYFUNCTION("""COMPUTED_VALUE"""),"Atmosphere") -> Atmosphere | W11: =IFERROR(__xludf.DUMMYFUNCTION("""COMPUTED_VALUE"""),"No") -> No | X11: =IFERROR(__xludf.DUMMYFUNCTION("""COMPUTED_VALUE"""),"No") -> No | Y11: =IFERROR(__xludf.DUMMYFUNCTION("""COMPUTED_VALUE"""),7.0) -> 7 | Z11: =IFERROR(__xludf.DUMMYFUNCTION("""COMPUTED_VALUE"""),3.0) -> 3 | AA11: =IFERROR(__xludf.DUMMYFUNCTION("""COMPUTED_VALUE"""),7.0) -> 7 | AB11: =IFERROR(__xludf.DUMMYFUNCTION("""COMPUTED_VALUE"""),"Yes") -> Yes
A12: =IFERROR(__xludf.DUMMYFUNCTION("""COMPUTED_VALUE"""),"jaAJpD4") -> jaAJpD4 | B12: =IFERROR(__xludf.DUMMYFUNCTION("""COMPUTED_VALUE"""),"J9AX5N7") -> J9AX5N7 | C12: =IFERROR(__xludf.DUMMYFUNCTION("""COMPUTED_VALUE"""),46034.060902777775) -> 46034.061 | D12: =IFERROR(__xludf.DUMMYFUNCTION("""COMPUTED_VALUE"""),"46-55") -> 46-55 | E12: =IFERROR(__xludf.DUMMYFUNCTION("""COMPUTED_VALUE"""),"Female") -> Female | F12: =IFERROR(__xludf.DUMMYFUNCTION("""COMPUTED_VALUE"""),"¥12,000,000 or more") -> ¥12,000,000 or more | G12: =IFERROR(__xludf.DUMMYFUNCTION("""COMPUTED_VALUE"""),"Kanto") -> Kanto | H12: =IFERROR(__xludf.DUMMYFUNCTION("""COMPUTED_VALUE"""),"Daily") -> Daily | I12: =IFERROR(__xludf.DUMMYFUNCTION("""COMPUTED_VALUE"""),"Drip") -> Drip | K12: =IFERROR(__xludf.DUMMYFUNCTION("""COMPUTED_VALUE"""),"Rarely") -> Rarely | L12: =IFERROR(__xludf.DUMMYFUNCTION("""COMPUTED_VALUE"""),"Matcha Latte") -> Matcha Latte | N12: =IFERROR(__xludf.DUMMYFUNCTION("""COMPUTED_VALUE"""),"Routine/Ritual, Taste/Flavor") -> Routine/Ritual, Taste/Flavor | P12: =IFERROR(__xludf.DUMMYFUNCTION("""COMPUTED_VALUE"""),"At home, At cafés") -> At home, At cafés | R12: =IFERROR(__xludf.DUMMYFUNCTION("""COMPUTED_VALUE"""),"A few times a month") -> A few times a month | S12: =IFERROR(__xludf.DUMMYFUNCTION("""COMPUTED_VALUE"""),"To relax or take a break") -> To relax or take a break | U12: =IFERROR(__xludf.DUMMYFUNCTION("""COMPUTED_VALUE"""),"Atmosphere") -> Atmosphere | W12: =IFERROR(__xludf.DUMMYFUNCTION("""COMPUTED_VALUE"""),"Yes, Western") -> Yes, Western | X12: =IFERROR(__xludf.DUMMYFUNCTION("""COMPUTED_VALUE"""),"Yes, Japanese") -> Yes, Japanese | Y12: =IFERROR(__xludf.DUMMYFUNCTION("""COMPUTED_VALUE"""),7.0) -> 7 | Z12: =IFERROR(__xludf.DUMMYFUNCTION("""COMPUTED_VALUE"""),7.0) -> 7 | AA12: =IFERROR(__xludf.DUMMYFUNCTION("""COMPUTED_VALUE"""),7.0) -> 7 | AB12: =IFERROR(__xludf.DUMMYFUNCTION("""COMPUTED_VALUE"""),"No") -> No
A13: =IFERROR(__xludf.DUMMYFUNCTION("""COMPUTED_VALUE"""),"dWe8XLV") -> dWe8XLV | B13: =IFERROR(__xludf.DUMMYFUNCTION("""COMPUTED_VALUE"""),"vGyJGrD") -> vGyJGrD | C13: =IFERROR(__xludf.DUMMYFUNCTION("""COMPUTED_VALUE"""),46034.081875) -> 46034.082 | D13: =IFERROR(__xludf.DUMMYFUNCTION("""COMPUTED_VALUE"""),"46-55") -> 46-55 | E13: =IFERROR(__xludf.DUMMYFUNCTION("""COMPUTED_VALUE"""),"Male") -> Male | F13: =IFERROR(__xludf.DUMMYFUNCTION("""COMPUTED_VALUE"""),"¥12,000,000 or more") -> ¥12,000,000 or more | G13: =IFERROR(__xludf.DUMMYFUNCTION("""COMPUTED_VALUE"""),"Kanto") -> Kanto | H13: =IFERROR(__xludf.DUMMYFUNCTION("""COMPUTED_VALUE"""),"Daily") -> Daily | I13: =IFERROR(__xludf.DUMMYFUNCTION("""COMPUTED_VALUE"""),"Pour Over") -> Pour Over | K13: =IFERROR(__xludf.DUMMYFUNCTION("""COMPUTED_VALUE"""),"Rarely") -> Rarely | L13: =IFERROR(__xludf.DUMMYFUNCTION("""COMPUTED_VALUE"""),"Matcha Latte") -> Matcha Latte | N13: =IFERROR(__xludf.DUMMYFUNCTION("""COMPUTED_VALUE"""),"Energy boost/Caffeine") -> Energy boost/Caffeine | P13: =IFERROR(__xludf.DUMMYFUNCTION("""COMPUTED_VALUE"""),"At home, Other:") -> At home, Other: | Q13: =IFERROR(__xludf.DUMMYFUNCTION("""COMPUTED_VALUE"""),"matcha at cafe") -> matcha at cafe | R13: =IFERROR(__xludf.DUMMYFUNCTION("""COMPUTED_VALUE"""),"A few times a month") -> A few times a month | S13: =IFERROR(__xludf.DUMMYFUNCTION("""COMPUTED_VALUE"""),"To relax or take a break") -> To relax or take a break | U13: =IFERROR(__xludf.DUMMYFUNCTION("""COMPUTED_VALUE"""),"Service") -> Service | W13: =IFERROR(__xludf.DUMMYFUNCTION("""COMPUTED_VALUE"""),"Yes, Western") -> Yes, Western | X13: =IFERROR(__xludf.DUMMYFUNCTION("""COMPUTED_VALUE"""),"Yes, Japanese") -> Yes, Japanese | Y13: =IFERROR(__xludf.DUMMYFUNCTION("""COMPUTED_VALUE"""),5.0) -> 5 | Z13: =IFERROR(__xludf.DUMMYFUNCTION("""COMPUTED_VALUE"""),7.0) -> 7 | AA13: =IFERROR(__xludf.DUMMYFUNCTION("""COMPUTED_VALUE"""),5.0) -> 5 | AB13: =IFERROR(__xludf.DUMMYFUNCTION("""COMPUTED_VALUE"""),"No") -> No
A14: =IFERROR(__xludf.DUMMYFUNCTION("""COMPUTED_VALUE"""),"XxP865O") -> XxP865O | B14: =IFERROR(__xludf.DUMMYFUNCTION("""COMPUTED_VALUE"""),"vGyJXLQ") -> vGyJXLQ | C14: =IFERROR(__xludf.DUMMYFUNCTION("""COMPUTED_VALUE"""),46034.090532407405) -> 46034.091 | D14: =IFERROR(__xludf.DUMMYFUNCTION("""COMPUTED_VALUE"""),"26-35") -> 26-35 | E14: =IFERROR(__xludf.DUMMYFUNCTION("""COMPUTED_VALUE"""),"Male") -> Male | F14: =IFERROR(__xludf.DUMMYFUNCTION("""COMPUTED_VALUE"""),"¥3,000,000 – ¥5,999,999") -> ¥3,000,000 – ¥5,999,999 | G14: =IFERROR(__xludf.DUMMYFUNCTION("""COMPUTED_VALUE"""),"Kanto") -> Kanto | H14: =IFERROR(__xludf.DUMMYFUNCTION("""COMPUTED_VALUE"""),"Several times a week") -> Several times a week | I14: =IFERROR(__xludf.DUMMYFUNCTION("""COMPUTED_VALUE"""),"Americano") -> Americano | K14: =IFERROR(__xludf.DUMMYFUNCTION("""COMPUTED_VALUE"""),"Rarely") -> Rarely | L14: =IFERROR(__xludf.DUMMYFUNCTION("""COMPUTED_VALUE"""),"I don’t drink matcha") -> I don’t drink matcha | N14: =IFERROR(__xludf.DUMMYFUNCTION("""COMPUTED_VALUE"""),"Taste") -> Taste | P14: =IFERROR(__xludf.DUMMYFUNCTION("""COMPUTED_VALUE"""),"At cafés, At home, From convenience stores (7-Eleven, Lawson, etc.)") -> At cafés, At home, From convenience stores (7-Eleven, Lawson, etc.) | R14: =IFERROR(__xludf.DUMMYFUNCTION("""COMPUTED_VALUE"""),"Several times a week") -> Several times a week | S14: =IFERROR(__xludf.DUMMYFUNCTION("""COMPUTED_VALUE"""),"Other:") -> Other: | T14: =IFERROR(__xludf.DUMMYFUNCTION("""COMPUTED_VALUE"""),"A, B, and C") -> A, B, and C | U14: =IFERROR(__xludf.DUMMYFUNCTION("""COMPUTED_VALUE"""),"Atmosphere") -> Atmosphere | W14: =IFERROR(__xludf.DUMMYFUNCTION("""COMPUTED_VALUE"""),"Unsure") -> Unsure | X14: =IFERROR(__xludf.DUMMYFUNCTION("""COMPUTED_VALUE"""),"Unsure") -> Unsure | Y14: =IFERROR(__xludf.DUMMYFUNCTION("""COMPUTED_VALUE"""),7.0) -> 7 | Z14: =IFERROR(__xludf.DUMMYFUNCTION("""COMPUTED_VALUE"""),5.0) -> 5 | AA14: =IFERROR(__xludf.DUMMYFUNCTION("""COMPUTED_VALUE"""),7.0) -> 7 | AB14: =IFERROR(__xludf.DUMMYFUNCTION("""COMPUTED_VALUE"""),"No") -> No
A15: =IFERROR(__xludf.DUMMYFUNCTION("""COMPUTED_VALUE"""),"A7ejP6o") -> A7ejP6o | B15: =IFERROR(__xludf.DUMMYFUNCTION("""COMPUTED_VALUE"""),"81Q6xjz") -> 81Q6xjz | C15: =IFERROR(__xludf.DUMMYFUNCTION("""COMPUTED_VALUE"""),46034.13444444445) -> 46034.134 | D15: =IFERROR(__xludf.DUMMYFUNCTION("""COMPUTED_VALUE"""),"46-55") -> 46-55 | E15: =IFERROR(__xludf.DUMMYFUNCTION("""COMPUTED_VALUE"""),"Male") -> Male | F15: =IFERROR(__xludf.DUMMYFUNCTION("""COMPUTED_VALUE"""),"¥12,000,000 or more") -> ¥12,000,000 or more | G15: =IFERROR(__xludf.DUMMYFUNCTION("""COMPUTED_VALUE"""),"Kanto") -> Kanto | H15: =IFERROR(__xludf.DUMMYFUNCTION("""COMPUTED_VALUE"""),"Several times a week") -> Several times a week | I15: =IFERROR(__xludf.DUMMYFUNCTION("""COMPUTED_VALUE"""),"Pour Over") -> Pour Over | K15: =IFERROR(__xludf.DUMMYFUNCTION("""COMPUTED_VALUE"""),"Rarely") -> Rarely | L15: =IFERROR(__xludf.DUMMYFUNCTION("""COMPUTED_VALUE"""),"Matcha Latte") -> Matcha Latte | N15: =IFERROR(__xludf.DUMMYFUNCTION("""COMPUTED_VALUE"""),"Taste/Flavor, Energy boost/Caffeine") -> Taste/Flavor, Energy boost/Caffeine | P15: =IFERROR(__xludf.DUMMYFUNCTION("""COMPUTED_VALUE"""),"At home, At cafés, From convenience stores (7-Eleven, Lawson, etc.)") -> At home, At cafés, From convenience stores (7-Eleven, Lawson, etc.) | R15: =IFERROR(__xludf.DUMMYFUNCTION("""COMPUTED_VALUE"""),"Several times a week") -> Several times a week | S15: =IFERROR(__xludf.DUMMYFUNCTION("""COMPUTED_VALUE"""),"To study/work") -> To study/work | U15: =IFERROR(__xludf.DUMMYFUNCTION("""COMPUTED_VALUE"""),"Quality of drinks") -> Quality of drinks | W15: =IFERROR(__xludf.DUMMYFUNCTION("""COMPUTED_VALUE"""),"Yes, Western") -> Yes, Western | X15: =IFERROR(__xludf.DUMMYFUNCTION("""COMPUTED_VALUE"""),"Yes, Japanese") -> Yes, Japanese | Y15: =IFERROR(__xludf.DUMMYFUNCTION("""COMPUTED_VALUE"""),7.0) -> 7 | Z15: =IFERROR(__xludf.DUMMYFUNCTION("""COMPUTED_VALUE"""),7.0) -> 7 | AA15: =IFERROR(__xludf.DUMMYFUNCTION("""COMPUTED_VALUE"""),7.0) -> 7 | AB15: =IFERROR(__xludf.DUMMYFUNCTION("""COMPUTED_VALUE"""),"No") -> No
A16: =IFERROR(__xludf.DUMMYFUNCTION("""COMPUTED_VALUE"""),"9qjoN6p") -> 9qjoN6p | B16: =IFERROR(__xludf.DUMMYFUNCTION("""COMPUTED_VALUE"""),"1A7N7Ng") -> 1A7N7Ng | C16: =IFERROR(__xludf.DUMMYFUNCTION("""COMPUTED_VALUE"""),46034.1430787037) -> 46034.143 | D16: =IFERROR(__xludf.DUMMYFUNCTION("""COMPUTED_VALUE"""),"26-35") -> 26-35 | E16: =IFERROR(__xludf.DUMMYFUNCTION("""COMPUTED_VALUE"""),"Female") -> Female | F16: =IFERROR(__xludf.DUMMYFUNCTION("""COMPUTED_VALUE"""),"¥12,000,000 or more") -> ¥12,000,000 or more | G16: =IFERROR(__xludf.DUMMYFUNCTION("""COMPUTED_VALUE"""),"Kanto") -> Kanto | H16: =IFERROR(__xludf.DUMMYFUNCTION("""COMPUTED_VALUE"""),"Several times a week") -> Several times a week | I16: =IFERROR(__xludf.DUMMYFUNCTION("""COMPUTED_VALUE"""),"Americano") -> Americano | K16: =IFERROR(__xludf.DUMMYFUNCTION("""COMPUTED_VALUE"""),"Rarely") -> Rarely | L16: =IFERROR(__xludf.DUMMYFUNCTION("""COMPUTED_VALUE"""),"Usucha") -> Usucha | N16: =IFERROR(__xludf.DUMMYFUNCTION("""COMPUTED_VALUE"""),"Routine/Ritual, Availability") -> Routine/Ritual, Availability | P16: =IFERROR(__xludf.DUMMYFUNCTION("""COMPUTED_VALUE"""),"At cafés, At home") -> At cafés, At home | R16: =IFERROR(__xludf.DUMMYFUNCTION("""COMPUTED_VALUE"""),"Several times a week") -> Several times a week | S16: =IFERROR(__xludf.DUMMYFUNCTION("""COMPUTED_VALUE"""),"To meet friends") -> To meet friends | U16: =IFERROR(__xludf.DUMMYFUNCTION("""COMPUTED_VALUE"""),"Atmosphere") -> Atmosphere | W16: =IFERROR(__xludf.DUMMYFUNCTION("""COMPUTED_VALUE"""),"Yes, Japanese") -> Yes, Japanese | X16: =IFERROR(__xludf.DUMMYFUNCTION("""COMPUTED_VALUE"""),"Yes, Japanese") -> Yes, Japanese | Y16: =IFERROR(__xludf.DUMMYFUNCTION("""COMPUTED_VALUE"""),7.0) -> 7 | Z16: =IFERROR(__xludf.DUMMYFUNCTION("""COMPUTED_VALUE"""),7.0) -> 7 | AA16: =IFERROR(__xludf.DUMMYFUNCTION("""COMPUTED_VALUE"""),7.0) -> 7 | AB16: =IFERROR(__xludf.DUMMYFUNCTION("""COMPUTED_VALUE"""),"No") -> No
A17: =IFERROR(__xludf.DUMMYFUNCTION("""COMPUTED_VALUE"""),"yP5d4lX") -> yP5d4lX | B17: =IFERROR(__xludf.DUMMYFUNCTION("""COMPUTED_VALUE"""),"1A7NrOL") -> 1A7NrOL | C17: =IFERROR(__xludf.DUMMYFUNCTION("""COMPUTED_VALUE"""),46034.160104166665) -> 46034.16 | D17: =IFERROR(__xludf.DUMMYFUNCTION("""COMPUTED_VALUE"""),"36-45") -> 36-45 | E17: =IFERROR(__xludf.DUMMYFUNCTION("""COMPUTED_VALUE"""),"Male") -> Male | F17: =IFERROR(__xludf.DUMMYFUNCTION("""COMPUTED_VALUE"""),"¥12,000,000 or more") -> ¥12,000,000 or more | G17: =IFERROR(__xludf.DUMMYFUNCTION("""COMPUTED_VALUE"""),"Kanto") -> Kanto | H17: =IFERROR(__xludf.DUMMYFUNCTION("""COMPUTED_VALUE"""),"Daily") -> Daily | I17: =IFERROR(__xludf.DUMMYFUNCTION("""COMPUTED_VALUE"""),"Drip") -> Drip | K17: =IFERROR(__xludf.DUMMYFUNCTION("""COMPUTED_VALUE"""),"Once a week") -> Once a week | L17: =IFERROR(__xludf.DUMMYFUNCTION("""COMPUTED_VALUE"""),"Koicha") -> Koicha | N17: =IFERROR(__xludf.DUMMYFUNCTION("""COMPUTED_VALUE"""),"Taste/Flavor, Energy boost/Caffeine") -> Taste/Flavor, Energy boost/Caffeine | P17: =IFERROR(__xludf.DUMMYFUNCTION("""COMPUTED_VALUE"""),"At cafés, At home") -> At cafés, At home | R17: =IFERROR(__xludf.DUMMYFUNCTION("""COMPUTED_VALUE"""),"Several times a week") -> Several times a week | S17: =IFERROR(__xludf.DUMMYFUNCTION("""COMPUTED_VALUE"""),"To relax or take a break") -> To relax or take a break | U17: =IFERROR(__xludf.DUMMYFUNCTION("""COMPUTED_VALUE"""),"Atmosphere") -> Atmosphere | W17: =IFERROR(__xludf.DUMMYFUNCTION("""COMPUTED_VALUE"""),"Yes, Western") -> Yes, Western | X17: =IFERROR(__xludf.DUMMYFUNCTION("""COMPUTED_VALUE"""),"Yes, Japanese") -> Yes, Japanese | Y17: =IFERROR(__xludf.DUMMYFUNCTION("""COMPUTED_VALUE"""),5.0) -> 5 | Z17: =IFERROR(__xludf.DUMMYFUNCTION("""COMPUTED_VALUE"""),7.0) -> 7 | AA17: =IFERROR(__xludf.DUMMYFUNCTION("""COMPUTED_VALUE"""),5.0) -> 5 | AB17: =IFERROR(__xludf.DUMMYFUNCTION("""COMPUTED_VALUE"""),"No") -> No
A18: =IFERROR(__xludf.DUMMYFUNCTION("""COMPUTED_VALUE"""),"dWekxYq") -> dWekxYq | B18: =IFERROR(__xludf.DUMMYFUNCTION("""COMPUTED_VALUE"""),"2ENlrAL") -> 2ENlrAL | C18: =IFERROR(__xludf.DUMMYFUNCTION("""COMPUTED_VALUE"""),46034.17319444445) -> 46034.173 | D18: =IFERROR(__xludf.DUMMYFUNCTION("""COMPUTED_VALUE"""),"36-45") -> 36-45 | E18: =IFERROR(__xludf.DUMMYFUNCTION("""COMPUTED_VALUE"""),"Male") -> Male | F18: =IFERROR(__xludf.DUMMYFUNCTION("""COMPUTED_VALUE"""),"¥6,000,000 – ¥8,999,999") -> ¥6,000,000 – ¥8,999,999 | G18: =IFERROR(__xludf.DUMMYFUNCTION("""COMPUTED_VALUE"""),"Kanto") -> Kanto | H18: =IFERROR(__xludf.DUMMYFUNCTION("""COMPUTED_VALUE"""),"Once a week") -> Once a week | I18: =IFERROR(__xludf.DUMMYFUNCTION("""COMPUTED_VALUE"""),"Latte") -> Latte | J18: =IFERROR(__xludf.DUMMYFUNCTION("""COMPUTED_VALUE"""),"Oat milk") -> Oat milk | K18: =IFERROR(__xludf.DUMMYFUNCTION("""COMPUTED_VALUE"""),"Rarely") -> Rarely | L18: =IFERROR(__xludf.DUMMYFUNCTION("""COMPUTED_VALUE"""),"Koicha") -> Koicha | N18: =IFERROR(__xludf.DUMMYFUNCTION("""COMPUTED_VALUE"""),"Social norms / influence (what people around me usually drink), Energy boost/Caffeine") -> Social norms / influence (what people around me usually drink), Energy boost/Caffeine | P18: =IFERROR(__xludf.DUMMYFUNCTION("""COMPUTED_VALUE"""),"At home") -> At home | R18: =IFERROR(__xludf.DUMMYFUNCTION("""COMPUTED_VALUE"""),"Rarely") -> Rarely | S18: =IFERROR(__xludf.DUMMYFUNCTION("""COMPUTED_VALUE"""),"To study/work") -> To study/work | U18: =IFERROR(__xludf.DUMMYFUNCTION("""COMPUTED_VALUE"""),"Atmosphere") -> Atmosphere | W18: =IFERROR(__xludf.DUMMYFUNCTION("""COMPUTED_VALUE"""),"Yes, Western") -> Yes, Western | X18: =IFERROR(__xludf.DUMMYFUNCTION("""COMPUTED_VALUE"""),"Yes, Japanese") -> Yes, Japanese | Y18: =IFERROR(__xludf.DUMMYFUNCTION("""COMPUTED_VALUE"""),5.0) -> 5 | Z18: =IFERROR(__xludf.DUMMYFUNCTION("""COMPUTED_VALUE"""),7.0) -> 7 | AA18: =IFERROR(__xludf.DUMMYFUNCTION("""COMPUTED_VALUE"""),5.0) -> 5 | AB18: =IFERROR(__xludf.DUMMYFUNCTION("""COMPUTED_VALUE"""),"No") -> No
A19: =IFERROR(__xludf.DUMMYFUNCTION("""COMPUTED_VALUE"""),"lbkMR2k") -> lbkMR2k | B19: =IFERROR(__xludf.DUMMYFUNCTION("""COMPUTED_VALUE"""),"0Q6ZvjN") -> 0Q6ZvjN | C19: =IFERROR(__xludf.DUMMYFUNCTION("""COMPUTED_VALUE"""),46034.192824074074) -> 46034.193 | D19: =IFERROR(__xludf.DUMMYFUNCTION("""COMPUTED_VALUE"""),"26-35") -> 26-35 | E19: =IFERROR(__xludf.DUMMYFUNCTION("""COMPUTED_VALUE"""),"Male") -> Male | F19: =IFERROR(__xludf.DUMMYFUNCTION("""COMPUTED_VALUE"""),"¥12,000,000 or more") -> ¥12,000,000 or more | G19: =IFERROR(__xludf.DUMMYFUNCTION("""COMPUTED_VALUE"""),"Kanto") -> Kanto | H19: =IFERROR(__xludf.DUMMYFUNCTION("""COMPUTED_VALUE"""),"Daily") -> Daily | I19: =IFERROR(__xludf.DUMMYFUNCTION("""COMPUTED_VALUE"""),"Drip") -> Drip | K19: =IFERROR(__xludf.DUMMYFUNCTION("""COMPUTED_VALUE"""),"Never") -> Never | N19: =IFERROR(__xludf.DUMMYFUNCTION("""COMPUTED_VALUE"""),"Taste/Flavor, Availability in the area") -> Taste/Flavor, Availability in the area | P19: =IFERROR(__xludf.DUMMYFUNCTION("""COMPUTED_VALUE"""),"At home, At cafés") -> At home, At cafés | R19: =IFERROR(__xludf.DUMMYFUNCTION("""COMPUTED_VALUE"""),"Several times a week") -> Several times a week | S19: =IFERROR(__xludf.DUMMYFUNCTION("""COMPUTED_VALUE"""),"To relax or take a break") -> To relax or take a break | U19: =IFERROR(__xludf.DUMMYFUNCTION("""COMPUTED_VALUE"""),"Quality of drinks") -> Quality of drinks | W19: =IFERROR(__xludf.DUMMYFUNCTION("""COMPUTED_VALUE"""),"Yes, Western") -> Yes, Western | X19: =IFERROR(__xludf.DUMMYFUNCTION("""COMPUTED_VALUE"""),"Yes, Japanese") -> Yes, Japanese | Y19: =IFERROR(__xludf.DUMMYFUNCTION("""COMPUTED_VALUE"""),5.0) -> 5 | Z19: =IFERROR(__xludf.DUMMYFUNCTION("""COMPUTED_VALUE"""),7.0) -> 7 | AA19: =IFERROR(__xludf.DUMMYFUNCTION("""COMPUTED_VALUE"""),5.0) -> 5 | AB19: =IFERROR(__xludf.DUMMYFUNCTION("""COMPUTED_VALUE"""),"No") -> No
A20: =IFERROR(__xludf.DUMMYFUNCTION("""COMPUTED_VALUE"""),"1Aop20Q") -> 1Aop20Q | B20: =IFERROR(__xludf.DUMMYFUNCTION("""COMPUTED_VALUE"""),"dWx82Qr") -> dWx82Qr | C20: =IFERROR(__xludf.DUMMYFUNCTION("""COMPUTED_VALUE"""),46034.210868055554) -> 46034.211 | D20: =IFERROR(__xludf.DUMMYFUNCTION("""COMPUTED_VALUE"""),"36-45") -> 36-45 | E20: =IFERROR(__xludf.DUMMYFUNCTION("""COMPUTED_VALUE"""),"Male") -> Male | F20: =IFERROR(__xludf.DUMMYFUNCTION("""COMPUTED_VALUE"""),"¥12,000,000 or more") -> ¥12,000,000 or more | G20: =IFERROR(__xludf.DUMMYFUNCTION("""COMPUTED_VALUE"""),"Okinawa") -> Okinawa | H20: =IFERROR(__xludf.DUMMYFUNCTION("""COMPUTED_VALUE"""),"Daily") -> Daily | I20: =IFERROR(__xludf.DUMMYFUNCTION("""COMPUTED_VALUE"""),"Pour Over") -> Pour Over | K20: =IFERROR(__xludf.DUMMYFUNCTION("""COMPUTED_VALUE"""),"Rarely") -> Rarely | N20: =IFERROR(__xludf.DUMMYFUNCTION("""COMPUTED_VALUE"""),"Taste/Flavor, Routine/Ritual") -> Taste/Flavor, Routine/Ritual | R20: =IFERROR(__xludf.DUMMYFUNCTION("""COMPUTED_VALUE"""),"A few times a month") -> A few times a month | S20: =IFERROR(__xludf.DUMMYFUNCTION("""COMPUTED_VALUE"""),"Other:") -> Other: | T20: =IFERROR(__xludf.DUMMYFUNCTION("""COMPUTED_VALUE"""),"Looking for a coffee if I am out running errands.") -> Looking for a coffee if I am out running errands. | U20: =IFERROR(__xludf.DUMMYFUNCTION("""COMPUTED_VALUE"""),"Quality of drinks") -> Quality of drinks | W20: =IFERROR(__xludf.DUMMYFUNCTION("""COMPUTED_VALUE"""),"Yes, Global") -> Yes, Global | X20: =IFERROR(__xludf.DUMMYFUNCTION("""COMPUTED_VALUE"""),"Yes, Japanese") -> Yes, Japanese | Y20: =IFERROR(__xludf.DUMMYFUNCTION("""COMPUTED_VALUE"""),5.0) -> 5 | Z20: =IFERROR(__xludf.DUMMYFUNCTION("""COMPUTED_VALUE"""),6.0) -> 6 | AA20: =IFERROR(__xludf.DUMMYFUNCTION("""COMPUTED_VALUE"""),5.0) -> 5 | AB20: =IFERROR(__xludf.DUMMYFUNCTION("""COMPUTED_VALUE"""),"No") -> No
A21: =IFERROR(__xludf.DUMMYFUNCTION("""COMPUTED_VALUE"""),"pbpkJZ8") -> pbpkJZ8 | B21: =IFERROR(__xludf.DUMMYFUNCTION("""COMPUTED_VALUE"""),"NpWb88G") -> NpWb88G | C21: =IFERROR(__xludf.DUMMYFUNCTION("""COMPUTED_VALUE"""),46034.22730324074) -> 46034.227 | D21: =IFERROR(__xludf.DUMMYFUNCTION("""COMPUTED_VALUE"""),"56-65") -> 56-65 | E21: =IFERROR(__xludf.DUMMYFUNCTION("""COMPUTED_VALUE"""),"Female") -> Female | F21: =IFERROR(__xludf.DUMMYFUNCTION("""COMPUTED_VALUE"""),"¥12,000,000 or more") -> ¥12,000,000 or more | G21: =IFERROR(__xludf.DUMMYFUNCTION("""COMPUTED_VALUE"""),"Kanto") -> Kanto | H21: =IFERROR(__xludf.DUMMYFUNCTION("""COMPUTED_VALUE"""),"Once a week") -> Once a week | I21: =IFERROR(__xludf.DUMMYFUNCTION("""COMPUTED_VALUE"""),"Cappuccino") -> Cappuccino | K21: =IFERROR(__xludf.DUMMYFUNCTION("""COMPUTED_VALUE"""),"Rarely") -> Rarely | N21: =IFERROR(__xludf.DUMMYFUNCTION("""COMPUTED_VALUE"""),"Mood") -> Mood | P21: =IFERROR(__xludf.DUMMYFUNCTION("""COMPUTED_VALUE"""),"At cafés") -> At cafés | R21: =IFERROR(__xludf.DUMMYFUNCTION("""COMPUTED_VALUE"""),"A few times a month") -> A few times a month | S21: =IFERROR(__xludf.DUMMYFUNCTION("""COMPUTED_VALUE"""),"To relax or take a break") -> To relax or take a break | U21: =IFERROR(__xludf.DUMMYFUNCTION("""COMPUTED_VALUE"""),"Atmosphere") -> Atmosphere | W21: =IFERROR(__xludf.DUMMYFUNCTION("""COMPUTED_VALUE"""),"No") -> No | X21: =IFERROR(__xludf.DUMMYFUNCTION("""COMPUTED_VALUE"""),"No") -> No | Y21: =IFERROR(__xludf.DUMMYFUNCTION("""COMPUTED_VALUE"""),7.0) -> 7 | Z21: =IFERROR(__xludf.DUMMYFUNCTION("""COMPUTED_VALUE"""),7.0) -> 7 | AA21: =IFERROR(__xludf.DUMMYFUNCTION("""COMPUTED_VALUE"""),7.0) -> 7 | AB21: =IFERROR(__xludf.DUMMYFUNCTION("""COMPUTED_VALUE"""),"No") -> No
A22: =IFERROR(__xludf.DUMMYFUNCTION("""COMPUTED_VALUE"""),"PdJGJZB") -> PdJGJZB | B22: =IFERROR(__xludf.DUMMYFUNCTION("""COMPUTED_VALUE"""),"J9AeG1K") -> J9AeG1K | C22: =IFERROR(__xludf.DUMMYFUNCTION("""COMPUTED_VALUE"""),46034.28375) -> 46034.284 | D22: =IFERROR(__xludf.DUMMYFUNCTION("""COMPUTED_VALUE"""),"26-35") -> 26-35 | E22: =IFERROR(__xludf.DUMMYFUNCTION("""COMPUTED_VALUE"""),"Female") -> Female | F22: =IFERROR(__xludf.DUMMYFUNCTION("""COMPUTED_VALUE"""),"¥3,000,000 – ¥5,999,999") -> ¥3,000,000 – ¥5,999,999 | G22: =IFERROR(__xludf.DUMMYFUNCTION("""COMPUTED_VALUE"""),"Kyushu") -> Kyushu | H22: =IFERROR(__xludf.DUMMYFUNCTION("""COMPUTED_VALUE"""),"Never") -> Never | K22: =IFERROR(__xludf.DUMMYFUNCTION("""COMPUTED_VALUE"""),"Rarely") -> Rarely | L22: =IFERROR(__xludf.DUMMYFUNCTION("""COMPUTED_VALUE"""),"Koicha") -> Koicha | N22: =IFERROR(__xludf.DUMMYFUNCTION("""COMPUTED_VALUE"""),"Health benefits, Taste/Flavor") -> Health benefits, Taste/Flavor | P22: =IFERROR(__xludf.DUMMYFUNCTION("""COMPUTED_VALUE"""),"At cafés") -> At cafés | R22: =IFERROR(__xludf.DUMMYFUNCTION("""COMPUTED_VALUE"""),"A few times a month") -> A few times a month | S22: =IFERROR(__xludf.DUMMYFUNCTION("""COMPUTED_VALUE"""),"To meet friends") -> To meet friends | U22: =IFERROR(__xludf.DUMMYFUNCTION("""COMPUTED_VALUE"""),"Atmosphere") -> Atmosphere | W22: =IFERROR(__xludf.DUMMYFUNCTION("""COMPUTED_VALUE"""),"Yes, Global") -> Yes, Global | X22: =IFERROR(__xludf.DUMMYFUNCTION("""COMPUTED_VALUE"""),"Yes, Japanese") -> Yes, Japanese | Y22: =IFERROR(__xludf.DUMMYFUNCTION("""COMPUTED_VALUE"""),4.0) -> 4 | Z22: =IFERROR(__xludf.DUMMYFUNCTION("""COMPUTED_VALUE"""),7.0) -> 7 | AA22: =IFERROR(__xludf.DUMMYFUNCTION("""COMPUTED_VALUE"""),3.0) -> 3 | AB22: =IFERROR(__xludf.DUMMYFUNCTION("""COMPUTED_VALUE"""),"No") -> No
